Workbook

Sheet All
A1: documentID | B1: images | C1: title | D1: desc | E1: warnings | F1: categories | G1: disposals | H1: tr_title | I1: tr_desc | J1: tr_warnings | K1: tr_categories | L1: tr_disposals | M1: en_title | N1: en_desc | O1: en_warnings | P1: en_categories | Q1: en_disposals
A2: H9YyUss4ecpyxbtZiPEK | B2: https://firebasestorage.googleapis.com/v0/b/easy-recycle-app.firebasestorage.app/o/users%2Fo3Wr784unsMIuBcveBaZZyxEt6J2%2Fuploads%2F1733786205657000_0.jpg?alt=media&token=9720250c-1077-4b78-9915-a052b8ae0838 | C2: Abbeizer | D2: Bis zu 30 Kg (Gesamtmenge/ haushaltsübliche Mengen) Ihrer gefährlichen Abfälle täglich können Sie kostenlos auf den Wertstoffhöfen der Region Hannover oder der Deponie Hannover im Sonderabfallzwischenlager abgeben. Größere Mengen können Sie kostenpflichtig an der Sonderannahmestelle auf der Deponie Hannover abgeben. Bitte beachten Sie hierzu die Preisliste für Sonderabfall. Bitte achten Sie bei dem Transport darauf, die Gebinde gut zu kennzeichnen und auf keinen Fall mit anderen Flüssigkeiten zu vermischen. Am sichersten transportieren Sie Sonderabfälle nur dicht verschlossen in den originalen Behältern (Gebinden) sowie aufrecht stehend (z.B in einer Wanne, die Behälter aufrecht hält). | F2: Sonderabfall | G2: Wertstoffhof, Deponie | H2: Rahip | I2: Günlük 30 kg'a kadar (toplam miktar/normal ev miktarı) tehlikeli atıklarınızı Hannover bölgesindeki geri dönüşüm merkezlerine veya Hannover'deki geçici tehlikeli atık depolama tesisindeki atık depolama sahasına ücretsiz olarak teslim edebilirsiniz. Daha büyük miktarları ücret karşılığında Hannover atık depolama sahasındaki özel toplama noktasına teslim edebilirsiniz. Lütfen tehlikeli atık fiyat listesine dikkat edin. Taşıma sırasında lütfen kapların iyi etiketlendiğinden emin olun ve asla başka sıvılarla karıştırmayın. Tehlikeli atığı taşımanın en güvenli yolu, onu yalnızca orijinal kaplarında (konteynerlerde) sıkıca kapalı olarak ve dik bir şekilde (örn. kapları dik tutan bir tepside) ayakta taşımaktır. | K2: Tehlikeli atık | L2: Geri dönüşüm merkezi, depolama sahası | M2: Abbeizer | N2: You can dispose of up to 30 kg (total amount/normal household amounts) of your hazardous waste daily free of charge at the recycling centers in the Hanover region or at the Hanover landfill in the temporary hazardous waste storage facility. Larger amounts can be disposed of at the special collection point at the Hanover landfill for a fee. Please note the price list for hazardous waste. When transporting, please ensure that the containers are clearly labeled and under no circumstances mixed with other liquids. The safest way to transport hazardous waste is to keep it tightly sealed in the original containers (containers) and in an upright position (e.g. in a tub that holds the container upright). | P2: hazardous waste | Q2: recycling center, landfill
A3: 7DGCkjtd5Te9ZknFOABD | B3: https://firebasestorage.googleapis.com/v0/b/easy-recycle-app.firebasestorage.app/o/users%2Fo3Wr784unsMIuBcveBaZZyxEt6J2%2Fuploads%2F1733786228051000_0.jpg?alt=media&token=c008c189-2e4a-44ad-bd3a-651a96ad286e | C3: Abbeizmittel | D3: Bis zu 30 Kg (Gesamtmenge/ haushaltsübliche Mengen) Ihrer gefährlichen Abfälle täglich können Sie kostenlos auf den Wertstoffhöfen der Region Hannover oder der Deponie Hannover im Sonderabfallzwischenlager abgeben. Größere Mengen können Sie kostenpflichtig an der Sonderannahmestelle auf der Deponie Hannover abgeben. Bitte beachten Sie hierzu die Preisliste für Sonderabfall. Bitte achten Sie bei dem Transport darauf, die Gebinde gut zu kennzeichnen und auf keinen Fall mit anderen Flüssigkeiten zu vermischen. Am sichersten transportieren Sie Sonderabfälle nur dicht verschlossen in den originalen Behältern (Gebinden) sowie aufrecht stehend (z.B in einer Wanne, die Behälter aufrecht hält). | F3: Sonderabfall | G3: Wertstoffhof, Deponie | H3: Boya sökücü | I3: Günlük 30 kg'a kadar (toplam miktar/normal ev miktarı) tehlikeli atıklarınızı Hannover bölgesindeki geri dönüşüm merkezlerine veya Hannover'deki geçici tehlikeli atık depolama tesisindeki atık depolama sahasına ücretsiz olarak teslim edebilirsiniz. Daha büyük miktarları ücret karşılığında Hannover atık depolama sahasındaki özel toplama noktasına teslim edebilirsiniz. Lütfen tehlikeli atık fiyat listesine dikkat edin. Taşıma sırasında lütfen kapların iyi etiketlendiğinden emin olun ve asla başka sıvılarla karıştırmayın. Tehlikeli atığı taşımanın en güvenli yolu, onu yalnızca orijinal kaplarında (konteynerlerde) sıkıca kapalı olarak ve dik konumda (örneğin kapları dik tutan bir tepside) taşımaktır. | K3: Tehlikeli atık | L3: Geri dönüşüm merkezi, depolama sahası | M3: paint stripper | N3: You can dispose of up to 30 kg (total amount/normal household amounts) of your hazardous waste daily free of charge at the recycling centers in the Hanover region or at the Hanover landfill in the temporary hazardous waste storage facility. Larger amounts can be disposed of at the special collection point at the Hanover landfill for a fee. Please note the price list for hazardous waste. When transporting, please ensure that the containers are clearly labeled and under no circumstances mixed with other liquids. The safest way to transport hazardous waste is to keep it tightly sealed in the original containers (containers) and in an upright position (e.g. in a tub that holds the container upright). | P3: hazardous waste | Q3: recycling center, landfill
A4: Fjh9KMz5nQcliulip9GT | C4: Abbruchholz | D4: Bis zu 1 m³ (Gesamtmenge/ haushaltsübliche Mengen) Ihrer Holzabfälle täglich können Sie kostenlos auf den Wertstoffhöfen der Region Hannover abgeben. Größere Mengen können Sie kostenpflichtig an den Deponien der Region Hannover abgeben. Bitte beachten Sie hierzu die Preisliste für die Deponieanlieferung. Die Annahmebedingungen unserer Deponien und Wertstoffhöfe finden Sie , (Deponien) und , (Wertstoffhöfe). | E4: kostenpflichtig, KEIN Sperrmüll | F4: Holzabfall | G4: Wertstoffhof | H4: Abbruchholz | I4: Günlük 1 m³'e kadar (toplam miktar/normal ev miktarı) ahşap atıklarınızı Hannover bölgesindeki geri dönüşüm merkezlerine ücretsiz olarak teslim edebilirsiniz. Daha büyük miktarları bir ücret karşılığında Hannover bölgesindeki atık depolama sahalarına atabilirsiniz. Lütfen çöp sahası teslimatı için fiyat listesine dikkat edin. Atık depolama alanlarımız ve geri dönüşüm merkezlerimiz için kabul koşulları , (atık depolama alanları) ve , (geri dönüşüm merkezleri)'de bulunabilir. | J4: ücretli, hacimli atık YOK | K4: Holzabfall | L4: Geri dönüşüm merkezi | M4: Abbruchholz | N4: You can dispose of up to 1 m³ (total amount/normal household amounts) of your wood waste daily free of charge at the recycling centers in the Hanover region. Larger amounts can be disposed of at the landfills in the Hanover region for a fee. Please note the price list for landfill delivery. The acceptance conditions of our landfills and recycling centers can be found at , (landfills) and , (recycling centers). | O4: fee-based, NO bulky waste | P4: Holzabfall | Q4: recycling center
A5: kEw5ezlLgHpDEtLxXVQP | C5: Abdeckfolie (sauber - ohne Farbreste etc.) | F5: Wertstoff | G5: Wertstoffhof, Gelber Sack | H5: Kaplama filmi (temiz - boya kalıntısı vs yok) | K5: Geri dönüştürülebilir malzeme | L5: Geri dönüşüm merkezi, sarı çanta | M5: Covering film (clean - without paint residue etc.) | P5: recyclable material | Q5: recycling center, yellow bag
A6: 4cbHcKoNJNb5lxmPWr33 | C6: Abdeckfolie (verschmutzt, Gewebe, Plane) | F6: Restabfall | G6: Restabfalltonne | H6: Kaplama filmi (kirli, kumaş, branda) | K6: Yeniden düşme | L6: Yeniden yerleştirme | M6: Covering film (dirty, fabric, tarpaulin) | P6: Restabfall | Q6: Restabfalltonne
A7: mcruBrdK5SPqltBBiSHj | C7: Abdeckfolien | D7: Abdeckfolien aus Kunststoff sind aus Polyethylen (PE). Saubere PE-Folien können wiederverwertet werden. Kleine Mengen nehmen die Wertstoffhöfe im Wertstoffsack an. Größere Mengen aus Gewerbe oder Industrie werden ebenfalls von aha in Containern gesammelt. Wenden Sie sich an den Gewerbekundenservice von aha. | F7: Leichtverpackungen | G7: Wertstoffhof, Gelber Sack | H7: Kapak filmleri | I7: Plastik kaplama filmleri polietilenden (PE) yapılmıştır. Temiz PE filmler geri dönüştürülebilir. Geri dönüşüm merkezleri geri dönüşüm torbalarındaki küçük miktarları kabul etmektedir. İşletme veya endüstriden gelen daha büyük miktarlar da aha tarafından kaplarda toplanıyor. aha'nın ticari müşteri hizmetleriyle iletişime geçin. | K7: Hafif ambalaj | L7: Geri dönüşüm merkezi, sarı çanta | M7: covering foils | N7: Plastic covering films are made of polyethylene (PE). Clean PE films can be recycled. Recycling centers accept small quantities in recycling bags. Larger quantities from commercial or industrial use are also collected by aha in containers. Contact aha's commercial customer service. | P7: lightweight packaging | Q7: recycling center, yellow bag
A8: Tl7G2ZzT7LQnUaHMPwKU | C8: Abdeckfolien (Landwirtschaft: Silo-, Stretch-, Wickelfolien etc.) | D8: Abdeckfolien aus Kunststoff sind aus Polyethylen (PE). Saubere PE-Folien können wiederverwertet werden. Kleine Mengen nehmen die Wertstoffhöfe im Wertstoffsack an. Größere Mengen aus Gewerbe oder Industrie werden ebenfalls von aha in Containern gesammelt. Wenden Sie sich an den Gewerbekundenservice von aha. | E8: NICHT in die Wertstofftonne! | F8: Gewerbeabfall | G8: Gewerbeabfall | H8: Kaplama filmleri (tarım: silo, streç, sarma filmleri vb.) | I8: Plastik kaplama filmleri polietilenden (PE) yapılmıştır. Temiz PE filmler geri dönüştürülebilir. Geri dönüşüm merkezleri geri dönüşüm torbalarındaki küçük miktarları kabul etmektedir. İşletme veya endüstriden gelen daha büyük miktarlar da aha tarafından kaplarda toplanıyor. aha'nın ticari müşteri hizmetleriyle iletişime geçin. | J8: Geri dönüşüm kutusunda DEĞİLDİR! | K8: Ticari atık | L8: Ticari atık | M8: Covering films (agriculture: silo, stretch, wrapping films, etc.) | N8: Plastic covering films are made of polyethylene (PE). Clean PE films can be recycled. Small quantities are accepted at recycling centers in recycling bags. Larger quantities from commercial or industrial use are also collected by aha in containers. Contact aha's commercial customer service. | O8: NOT in the recycling bin! | P8: commercial waste | Q8: commercial waste
A9: uBRCwSrFLd9Pkmto3nC0 | C9: Abflussreiniger | D9: Bis zu 30 Kg (Gesamtmenge/ haushaltsübliche Mengen) Ihrer gefährlichen Abfälle täglich können Sie kostenlos auf den Wertstoffhöfen der Region Hannover oder der Deponie Hannover im Sonderabfallzwischenlager abgeben. Größere Mengen können Sie kostenpflichtig an der Sonderannahmestelle auf der Deponie Hannover abgeben. Bitte beachten Sie hierzu die Preisliste für Sonderabfall. Bitte achten Sie bei dem Transport darauf, die Gebinde gut zu kennzeichnen und auf keinen Fall mit anderen Flüssigkeiten zu vermischen. Am sichersten transportieren Sie Sonderabfälle nur dicht verschlossen in den originalen Behältern (Gebinden) sowie aufrecht stehend (z.B in einer Wanne, die Behälter aufrecht hält). | F9: Sonderabfall | G9: Wertstoffhof, Deponie | H9: Drenaj temizleyici | I9: Günlük 30 kg'a kadar (toplam miktar/normal ev miktarı) tehlikeli atıklarınızı Hannover bölgesindeki geri dönüşüm merkezlerine veya Hannover'deki geçici tehlikeli atık depolama tesisindeki atık depolama sahasına ücretsiz olarak teslim edebilirsiniz. Daha büyük miktarları ücret karşılığında Hannover atık depolama sahasındaki özel toplama noktasına teslim edebilirsiniz. Lütfen tehlikeli atık fiyat listesine dikkat edin. Taşıma sırasında lütfen kapların iyi etiketlendiğinden emin olun ve asla başka sıvılarla karıştırmayın. Tehlikeli atığı taşımanın en güvenli yolu, onu yalnızca orijinal kaplarında (konteynerlerde) sıkıca kapalı olarak ve dik bir şekilde (örn. kapları dik tutan bir tepside) ayakta taşımaktır. | K9: Tehlikeli atık | L9: Geri dönüşüm merkezi, depolama sahası | M9: drain cleaner | N9: You can dispose of up to 30 kg (total amount/normal household amounts) of your hazardous waste daily free of charge at the recycling centers in the Hanover region or at the Hanover landfill in the temporary hazardous waste storage facility. Larger amounts can be disposed of at the special collection point at the Hanover landfill for a fee. Please note the price list for hazardous waste. When transporting, please ensure that the containers are clearly labeled and under no circumstances mixed with other liquids. The safest way to transport hazardous waste is to keep it tightly sealed in the original containers (containers) and in an upright position (e.g. in a tub that holds the container upright). | P9: hazardous waste | Q9: recycling center, landfill
A10: IeVNe2z02dRZe2qHbJGH | C10: Abscheideranlage | D10: aha entsorgt in der Region Hannover die Inhalte von Benzin- und Ölabscheidern und von Sand- und Schlammfängen. Im Auftrag von aha führt die Stadtentwässerung Hannover die Reinigung von Abscheideranlagen regionsweit aus. Ansprechpartner bei der Stadtentwässerung Hannover sind Herr Münder und Herr Wagner, Tel: 0511 - 168 - 47440. Bei Abwesenheit nimmt ein Anrufbeantworter die Anfragen auf. Störungsmeldestelle der Stadtentwässerung, Tel: 0511 - 168 - 47377 tagsüber besetzt, oder Tel: 0511 - 168 - 47333, 24 Std. besetzt. | F10: Sonderabfall | G10: Der Zweckverband Abfallwirtschaft Region Hannover (aha) | H10: Ayırıcı sistemi | I10: aha, Hannover bölgesindeki benzin ve yağ ayırıcıların ve kum ve çamur tutucularının içeriğini bertaraf ediyor. Aha adına Hannover Şehir Drenajı bölge genelindeki separatör sistemlerinin temizliğini gerçekleştirmektedir. Hannover Şehir Drenajındaki irtibat kişileri Bay Münder ve Bay Wagner'dir. Tel: 0511 - 168 - 47440. Eğer orada değilseniz, bir telesekreter sorularınızı kaydedecektir. Şehir drenaj arıza raporlama merkezi, Tel: 0511 - 168 - 47377, gün boyunca personel bulunur veya Tel: 0511 - 168 - 47333, günün 24 saati personel bulunur. | K10: Tehlikeli atık | L10: Atık Yönetimi Bölgesi Hannover Derneği (aha) | M10: separator system | N10: aha disposes of the contents of petrol and oil separators and sand and sludge traps in the Hanover region. On behalf of aha, the Hanover city drainage department carries out the cleaning of separator systems throughout the region. Contact persons at the Hanover city drainage department are Mr. Münder and Mr. Wagner, Tel: 0511 - 168 - 47440. If you are not available, an answering machine will take your enquiries. The city drainage department's fault reporting center, Tel: 0511 - 168 - 47377, manned during the day, or Tel: 0511 - 168 - 47333, manned 24 hours. | P10: hazardous waste | Q10: The Hannover Region Waste Management Association (aha)
A11: ewO50e32XAXt8Wde9wZD | C11: Abschminkpads | E11: nicht in die Kanalisation! | F11: Restabfall, Hygieneabfall | G11: Restabfalltonne | H11: Makyaj temizleme pedleri | J11: kanalizasyona değil! | K11: Yeniden kurulum, Hijyen kurulumu | L11: Yeniden yerleştirme | M11: makeup removal pads | O11: not into the sewer system! | P11: Restabfall, Hygieneabfall | Q11: Restabfalltonne
A12: eCf0HlSPFnB9mcRfMmfP | C12: Abschminktücher | E12: nicht in die Kanalisation! | F12: Restabfall, Hygieneabfall | G12: Restabfalltonne | H12: Makyaj temizleme mendilleri | J12: kanalizasyon sistemine değil! | K12: Yeniden kurulum, Hijyen kurulumu | L12: Yeniden yerleştirme | M12: makeup remover wipes | O12: not into the sewer system! | P12: Restabfall, Hygieneabfall | Q12: Restabfalltonne
A13: hDEubKz42LcbbHjYmhvk | B13: https://storage.googleapis.com/easy-recycle-app.firebasestorage.app/images/47.jpg | C13: Absperrband | F13: Wertstoff | G13: Wertstoffhof, Gelber Sack | H13: Bariyer bandı | K13: Geri dönüştürülebilir malzeme | L13: Geri dönüşüm merkezi, sarı çanta | M13: barrier tape | P13: recyclable material | Q13: recycling center, yellow bag
A14: lYzpziWuzKIY31NRHWBr | C14: Abtönfarbe (Eingetrocknete oder eingedickte) | D14: Binderfarben sind wasserlöslich und zählen nicht zu den gefährlichen Abfällen, verursachen uneingedickt allerding böse Flecken. Eingetrocknete oder eingedickte (mit Sand, Gips oder Sägespäne vermischte Binderfarbe) können dem Restabfall zugeführt werden. Flüssige Binderfarben geben Sie bitte an den Wertstoffhöfen der Region Hannover oder der Deponie Hannover im Sonderabfallzwischenlager ab. | F14: Restabfall | G14: Restabfalltonne | H14: Renk tonu (kurutulmuş veya kalınlaştırılmış) | I14: Bağlayıcı boyalar suda çözünür ve tehlikeli atık olarak sınıflandırılmaz, ancak kalınlaştırılmadan bırakılırsa kötü lekelere neden olurlar. Kurutulmuş veya kalınlaştırılmış bağlayıcı boya (kum, alçı veya talaşla karıştırılmış) artık atık olarak bertaraf edilebilir. Lütfen sıvı bağlayıcı boyaları Hannover bölgesindeki geri dönüşüm merkezlerine veya Hannover atık depolama sahasındaki geçici tehlikeli atık depolama tesisine teslim edin. | K14: Yeniden düşme | L14: Yeniden yerleştirme | M14: tinting paint (dried or thickened) | N14: Binder paints are water-soluble and are not classified as hazardous waste, but if not thickened they cause unpleasant stains. Dried or thickened binder paints (mixed with sand, plaster or sawdust) can be disposed of as residual waste. Please dispose of liquid binder paints at the recycling centers in the Hanover region or at the Hanover landfill in the interim storage facility for hazardous waste. | P14: Restabfall | Q14: Restabfalltonne
A15: uMIzAIf15Slkd0J2uQjW | C15: Abtönfarbe (Flüssige) | D15: Binderfarben sind wasserlöslich und zählen nicht zu den gefährlichen Abfällen, verursachen uneingedickt allerding böse Flecken. Eingetrocknete oder eingedickte (mit Sand, Gips oder Sägespäne vermischte Binderfarbe) können dem Restabfall zugeführt werden. Flüssige Binderfarben geben Sie bitte an den Wertstoffhöfen der Region Hannover oder der Deponie Hannover im Sonderabfallzwischenlager ab. | F15: Sonderabfall, Wertstoff | G15: Wertstoffhof, Deponie | H15: Renklendirme boyası (sıvı) | I15: Bağlayıcı boyalar suda çözünür ve tehlikeli atık olarak sınıflandırılmaz, ancak kalınlaştırılmadan bırakılırsa kötü lekelere neden olurlar. Kurutulmuş veya kalınlaştırılmış bağlayıcı boya (kum, alçı veya talaşla karıştırılmış) artık atık olarak bertaraf edilebilir. Lütfen sıvı bağlayıcı boyaları Hannover bölgesindeki geri dönüşüm merkezlerine veya Hannover atık depolama sahasındaki geçici tehlikeli atık depolama tesisine teslim edin. | K15: Tehlikeli atık, geri dönüştürülebilir malzeme | L15: Geri dönüşüm merkezi, depolama sahası | M15: tinting color (liquid) | N15: Binder paints are water-soluble and are not classified as hazardous waste, but if not thickened they cause unpleasant stains. Dried or thickened binder paints (mixed with sand, plaster or sawdust) can be disposed of as residual waste. Please dispose of liquid binder paints at the recycling centers in the Hanover region or at the Hanover landfill in the interim storage facility for hazardous waste. | P15: hazardous waste, recyclable material | Q15: recycling center, landfill
A16: SeQDa3p6YX7pUruBaPkX | C16: Aceton | D16: Bis zu 30 Kg (Gesamtmenge/ haushaltsübliche Mengen) Ihrer gefährlichen Abfälle täglich können Sie kostenlos auf den Wertstoffhöfen der Region Hannover oder der Deponie Hannover im Sonderabfallzwischenlager abgeben. Größere Mengen können Sie kostenpflichtig an der Sonderannahmestelle auf der Deponie Hannover abgeben. Bitte beachten Sie hierzu die Preisliste für Sonderabfall. Bitte achten Sie bei dem Transport darauf, die Gebinde gut zu kennzeichnen und auf keinen Fall mit anderen Flüssigkeiten zu vermischen. Am sichersten transportieren Sie Sonderabfälle nur dicht verschlossen in den originalen Behältern (Gebinden) sowie aufrecht stehend (z.B in einer Wanne, die Behälter aufrecht hält). | F16: Sonderabfall | G16: Wertstoffhof, Deponie | H16: Aseton | I16: Günlük 30 kg'a kadar (toplam miktar/normal ev miktarı) tehlikeli atıklarınızı Hannover bölgesindeki geri dönüşüm merkezlerine veya Hannover'deki geçici tehlikeli atık depolama tesisindeki atık depolama sahasına ücretsiz olarak teslim edebilirsiniz. Daha büyük miktarları ücret karşılığında Hannover atık depolama sahasındaki özel toplama noktasına teslim edebilirsiniz. Lütfen tehlikeli atık fiyat listesine dikkat edin. Taşıma sırasında lütfen kapların iyi etiketlendiğinden emin olun ve asla başka sıvılarla karıştırmayın. Tehlikeli atığı taşımanın en güvenli yolu, onu yalnızca orijinal kaplarında (konteynerlerde) sıkıca kapalı olarak ve dik bir şekilde (örn. kapları dik tutan bir tepside) ayakta taşımaktır. | K16: Tehlikeli atık | L16: Geri dönüşüm merkezi, depolama sahası | M16: Acetone | N16: You can dispose of up to 30 kg (total amount/normal household amounts) of your hazardous waste daily free of charge at the recycling centers in the Hanover region or at the Hanover landfill in the temporary hazardous waste storage facility. Larger amounts can be disposed of at the special collection point at the Hanover landfill for a fee. Please note the price list for hazardous waste. When transporting, please ensure that the containers are clearly labeled and under no circumstances mixed with other liquids. The safest way to transport hazardous waste is to keep it tightly sealed in the original containers (containers) and in an upright position (e.g. in a tub that holds the container upright). | P16: hazardous waste | Q16: recycling center, landfill
A17: OTiwRc8zw8qgnIAbwd6a | C17: Acetondose (leer - Deckel ablassen) | F17: Wertstoff | G17: Wertstoffhof, Gelber Sack | H17: Aseton kutusu (boş - kapağını açık bırakın) | K17: Geri dönüştürülebilir malzeme | L17: Geri dönüşüm merkezi, sarı çanta | M17: Acetone can (empty - remove lid) | P17: recyclable material | Q17: recycling center, yellow bag
A18: vI27UXBBFDvxaZEYpZWq | C18: Acrylbadewanne | F18: Bauabfall | G18: Deponie | H18: Akrilik küvet | K18: Baufall'da | L18: Depolama sahası | M18: acrylic bathtub | P18: Bauabfall | Q18: landfill
A19: x6UHwOqsAXvKso91hgs5 | C19: Acrylfarbe | F19: Sonderabfall | G19: Wertstoffhof, Deponie | H19: Akrilik boya | K19: Tehlikeli atık | L19: Geri dönüşüm merkezi, depolama sahası | M19: acrylic paint | P19: hazardous waste | Q19: recycling center, landfill
A20: mst4zqVgJas9rllqpawd | C20: Acrylfarbe (ausgehärtet) | F20: Restabfall | G20: Restabfalltonne | H20: Akrilik boya (kürlenmiş) | K20: Yeniden düşme | L20: Yeniden yerleştirme | M20: acrylic paint (cured) | P20: Restabfall | Q20: Restabfalltonne
A21: GGj2c25xxJcaSuY60zXP | C21: Acrylglas, Stegplatten, Plexiglas® | E21: In Kleinmengen Restabfall | F21: Bauabfall | G21: Deponie | H21: Akrilik cam, çok duvarlı levhalar, Plexiglas® | J21: Az miktarda artık atık | K21: Baufall'da | L21: Depolama sahası | M21: acrylic glass, multi-wall sheets, Plexiglas® | O21: In small quantities of residual waste | P21: Bauabfall | Q21: landfill
A22: OinsSn6PrE6Q7xDcHCRF | C22: Adapter, Stecker | F22: Elektrogeräte | G22: Wertstoffhof | H22: Adaptör, fiş | K22: Elektrikli ev aletleri | L22: Geri dönüşüm merkezi | M22: adapter, plug | P22: electrical appliances | Q22: recycling center
A23: iTcDnGQ2BnChxUuL1Sm7 | C23: Adventsbeleuchtung | E23: ACHTUNG enthaltene Akkus/Batterien entfernen | F23: Elektrogeräte | G23: Wertstoffhof | H23: Noel aydınlatması | J23: DİKKAT birlikte verilen şarj edilebilir pilleri/pilleri çıkarın | K23: Elektrikli ev aletleri | L23: Geri dönüşüm merkezi | M23: Advent lighting | O23: ATTENTION: Remove any batteries | P23: electrical appliances | Q23: recycling center
A24: vrphJXRM79aYrpmVYlVK | C24: Adventskalender (bitte in Kunststoff und Pappe trennen) | F24: Wertstoff, Papier | G24: Wertstoffhof, Papiertonne, Papiersack | H24: Advent takvimi (lütfen plastik ve kartonu ayırın) | K24: Geri dönüştürülebilir malzeme, kağıt | L24: Geri dönüşüm merkezi, kağıt kutusu, kağıt torba | M24: Advent calendar (please separate into plastic and cardboard) | P24: recyclable material, paper | Q24: recycling center, paper bin, paper bag
A25: mDQRJlSyBZvY4IoknH2f | C25: Adventskerze | F25: Restabfall | G25: Restabfalltonne | H25: Macera Oyunları | K25: Yeniden düşme | L25: Yeniden yerleştirme | M25: Adventskerze | P25: Restabfall | Q25: Restabfalltonne
A26: 2LFzCWVhZp6F6msxnOxm | C26: Adventskranz (komplett mit Schaumkern, Draht usw.) | F26: Restabfall | G26: Restabfalltonne | H26: Advent çelengi (köpük çekirdek, tel vb. ile birlikte) | K26: Yeniden düşme | L26: Yeniden yerleştirme | M26: Advent wreath (complete with foam core, wire, etc.) | P26: Restabfall | Q26: Restabfalltonne
A27: LCUEdVfWurG0C5ZOzfVA | C27: Adventszweige (ohne Schmuck, Anhaftungen) | F27: Bioabfall | G27: Biotonne, Biosack | H27: Advent dalları (dekorasyonlar ve eklentiler olmadan) | K27: Biyolojik çöküş | L27: Organik çöp kutusu, organik çanta | M27: Advent branches (without decorations, attachments) | P27: Bioabfall | Q27: organic waste bin, organic waste bag
A28: fb8GfSLF8HMe5hw6Onra | C28: Aerosol-Spraydosen (drucklos) | F28: Wertstoff | G28: Wertstoffhof, Gelber Sack | H28: Aerosol sprey kutuları (basınçsız) | K28: Geri dönüştürülebilir malzeme | L28: Geri dönüşüm merkezi, sarı çanta | M28: aerosol spray cans (non-pressurized) | P28: recyclable material | Q28: recycling center, yellow bag
A29: QavqTXSIpASwiS3EV5LS | C29: Aerosol-Spraydosen (mit Inhalt) | F29: Sonderabfall | G29: Wertstoffhof, Deponie | H29: Aerosol sprey kutuları (içerikle birlikte) | K29: Tehlikeli atık | L29: Geri dönüşüm merkezi, depolama sahası | M29: aerosol spray cans (with contents) | P29: hazardous waste | Q29: recycling center, landfill
A30: VT4t5aoFORc834EYtNbz | C30: Agrarfolien (Landwirtschaft: Silo-, Stretch-, Wickelfolien etc..) | E30: NICHT in die Wertstofftonne! | F30: Gewerbeabfall | G30: Gewerbeabfall | H30: Tarımsal filmler (tarım: silo, streç, sarma filmleri vb.) | J30: Geri dönüşüm kutusunda DEĞİLDİR! | K30: Ticari atık | L30: Ticari atık | M30: Agricultural films (agriculture: silo, stretch, wrapping films, etc.) | O30: NOT in the recycling bin! | P30: commercial waste | Q30: commercial waste
A31: oD0mhKdRQUm2L2Xl70Kb | C31: Akkumulatoren (Akkus) | D31: aha nimmt Gerätebatterien, z. B. aus Taschenlampen, Uhren, Radios usw. an. Bis zu 30 kg Ihrer gefährlichen Abfälle täglich können Sie kostenlos auf den Wertstoffhöfen der Region Hannover oder der Deponie Hannover im Sonderabfallzwischenlager abgeben. Ausgediente Akkus von E-Bikes und E-Scootern gehören zu laut §8 Batteriegesetz zu den Industriebatterien. Industriebatterien werden von aha nicht angenommen. Bitte geben Sie diese an den Fachhandel zurück. Die einzige Ausnahme von dieser Regel stellen Starterbatterien auf Bleibasis von LKWs und PKWs sowie Motorrädern dar. Ausgediente Akkus von E-Bikes, E-Scootern und Motorrädern gehören zu laut §8 Batteriegesetz zu den Industriebatterien. Industriebatterien werden von aha nicht angenommen. Bitte geben Sie diese an den Fachhandel zurück. | F31: Sonderabfall | G31: Wertstoffhof, Deponie | H31: Akümülatörler (şarj edilebilir piller) | I31: aha cihazın pillerini alır, ör. B. el fenerlerinden, saatlerden, radyolardan vb. Günde 30 kg'a kadar tehlikeli atıklarınızı Hannover bölgesindeki geri dönüşüm merkezlerine veya Hannover'deki geçici tehlikeli atık depolama tesisindeki atık depolama sahasına ücretsiz olarak teslim edebilirsiniz. Pil Yasası'nın 8. Maddesine göre, e-bisiklet ve e-scooter'ların kullanılmış pilleri endüstriyel pillerdir. aha endüstriyel pilleri kabul etmemektedir. Lütfen bunları yetkili satıcıya iade edin. Bu kuralın tek istisnası kamyonlar, arabalar ve motosikletler için kurşun bazlı marş aküleridir. E-bisikletler, e-scooterlar ve motosikletlerde kullanılan kullanılmış aküler, Pil Yasasının 8. Maddesine göre endüstriyel piller olarak sınıflandırılır. aha endüstriyel pilleri kabul etmemektedir. Lütfen bunları yetkili satıcıya iade edin. | K31: Tehlikeli atık | L31: Geri dönüşüm merkezi, depolama sahası | M31: accumulators (batteries) | N31: aha accepts device batteries, e.g. from flashlights, watches, radios, etc. You can dispose of up to 30 kg of your hazardous waste daily free of charge at the recycling centers in the Hanover region or at the Hanover landfill in the special waste interim storage facility. According to Section 8 of the Battery Act, used batteries from e-bikes and e-scooters are classified as industrial batteries. Industrial batteries are not accepted by aha. Please return them to the specialist retailer. The only exception to this rule are lead-based starter batteries from trucks and cars as well as motorcycles. According to Section 8 of the Battery Act, used batteries from e-bikes, e-scooters and motorcycles are classified as industrial batteries. Industrial batteries are not accepted by aha. Please return them to the specialist retailer. | P31: hazardous waste | Q31: recycling center, landfill
A32: xaauI2vCQg3yU98pHIhv | C32: Akku-Schrauber | E32: ACHTUNG enthaltene Akkus/Batterien entfernen | F32: Elektrogeräte | G32: Wertstoffhof | H32: Akülü tornavida | J32: DİKKAT birlikte verilen şarj edilebilir pilleri/pilleri çıkarın | K32: Elektrikli ev aletleri | L32: Geri dönüşüm merkezi | M32: cordless screwdriver | O32: ATTENTION: Remove any batteries | P32: electrical appliances | Q32: recycling center
A33: coqy3nFHtop7X8CYfaA9 | C33: Akten, Datenrelevante Papiere | D33: Altpapier Die Papierschnipsel bitte in einer Papiertüte sammeln, beim Entleerungsvorgang der Altpapiertonne wehen lose Papierschnipsel häufig heraus. | E33: Persönliche Daten schützen! | F33: Papier | G33: Fachverwerter, Papiertonne, Papiersack | H33: Dosyalar, verilerle ilgili belgeler | I33: Atık kağıt Lütfen kağıt parçalarını bir kese kağıdı içinde toplayın; gevşek kağıt parçaları genellikle atık kağıt kutusu boşaltıldığında havaya uçar. | J33: Kişisel verileri koruyun! | K33: Kağıt | L33: Uzman geri dönüşümcü, kağıt kutusu, kağıt torba | M33: files, data-relevant papers | N33: Waste paper Please collect the paper scraps in a paper bag; when emptying the waste paper bin, loose paper scraps often blow out. | O33: Protect personal data! | P33: Paper | Q33: specialist recycler, paper bin, paper bag
A34: e7UftQ0wVHLlcnAWrZOV | C34: Aktenordner (Karton/Pappe) | D34: Ein Metallbügel stellt kein Problem dar. | F34: Papier | G34: Papiertonne, Papiersack | H34: Dosya klasörü (karton/karton) | I34: Metal bir braket sorun değildir. | K34: Kağıt | L34: Kağıt kutusu, kağıt çuval | M34: file folder (cardboard) | N34: A metal bracket is not a problem. | P34: Paper | Q34: paper bin, paper bag
A35: plYztTv7LKBshSp3ZqFk | C35: Aktenordner (Komplette) | D35: Alte Akten können (soweit es der Datenschutz es erfordert) durch spezielle Aktenvernichtungsfirmen entsorgt bzw. der Verwertung zugeführt werden. Aktendeckel aus Papier/Karton (unbeschichtet) gehören nur ohne Metallinlett in die Papiersammlung. Komplette Ordner ohne Inhalt gehören in den Restabfall. | F35: Restabfall | G35: Restabfalltonne | H35: Dosya klasörü (tamamlandı) | I35: Eski dosyalar (veri koruması gerektiriyorsa) özel belge imha şirketleri tarafından imha edilebilir veya geri dönüştürülebilir. Kağıt/kartondan (kaplamasız) yapılmış dosya kapakları yalnızca metal astarsız kağıt koleksiyonuna aittir. İçeriği olmayan komple klasörler artık atık kapsamına girer. | K35: Yeniden düşme | L35: Yeniden yerleştirme | M35: File Folder (Complete) | N35: Old files can be disposed of or recycled by special document destruction companies (if data protection requires it). File covers made of paper/cardboard (uncoated) only belong in the paper collection without a metal insert. Complete folders without contents belong in the residual waste. | P35: Restabfall | Q35: Restabfalltonne
A36: AMRn8cNrSvHoxYA9lUra | C36: Aktenordner (Kunststoff/Papier Mix) | D36: Restabfall Alles was in Säcke paßt ist kostenpflichtig. | F36: Restabfall | G36: Restabfalltonne | H36: Dosya klasörü (plastik/kağıt karışımı) | I36: Artık atık Torbalara sığan her şey ücrete tabidir. | K36: Yeniden düşme | L36: Yeniden yerleştirme | M36: file folder (plastic/paper mix) | N36: Residual waste Everything that fits in bags is subject to a fee. | P36: Restabfall | Q36: Restabfalltonne
A37: eqgPHWXnG8k5DmZM0oXY | C37: Aktenordner (Papier/Karton) | D37: Alte Akten können (soweit es der Datenschutz es erfordert) durch spezielle Aktenvernichtungsfirmen entsorgt bzw. der Verwertung zugeführt werden. Aktendeckel aus Papier/Karton (unbeschichtet) gehören nur ohne Metallinlett in die Papiersammlung. Komplette Ordner ohne Inhalt gehören in den Restabfall. | F37: Papier | G37: Papiertonne, Papiersack | H37: Dosya klasörleri (kağıt/karton) | I37: Eski dosyalar, özel belge imha şirketleri tarafından imha edilebilir veya geri dönüştürülebilir (veri koruması gerektiriyorsa). Kağıt/kartondan (kaplamasız) yapılmış dosya kapakları yalnızca metal astarı olmayan kağıt koleksiyonuna aittir. İçeriği olmayan komple klasörler artık atık kapsamına girer. | K37: Kağıt | L37: Kağıt kutusu, kağıt çuval | M37: file folders (paper/cardboard) | N37: Old files can be disposed of or recycled by special document destruction companies (if data protection requires it). File covers made of paper/cardboard (uncoated) only belong in the paper collection without a metal insert. Complete folders without contents belong in the residual waste. | P37: Paper | Q37: paper bin, paper bag
A38: XTR2wPNmQwIWXxnk9asu | C38: Aktenordner/Hefter (Kunststoff (ohne Pappe)) | F38: Wertstoff | G38: Wertstoffhof, Gelber Sack | H38: Dosya klasörü/zımbalayıcı (plastik (kartonsuz)) | K38: Geri dönüştürülebilir malzeme | L38: Geri dönüşüm merkezi, sarı çanta | M38: File folder/stapler (plastic (without cardboard)) | P38: recyclable material | Q38: recycling center, yellow bag
A39: y8D4lzJ6i9AMUkmdMzaa | C39: Aktenvernichter | F39: Elektrogeräte | G39: Wertstoffhof | H39: Kağıt parçalayıcı | K39: Elektrikli ev aletleri | L39: Geri dönüşüm merkezi | M39: document shredder | P39: electrical appliances | Q39: recycling center
A40: DCs2IHx8ii44FItt7EpJ | C40: Aktivkohlefilter | D40: Alles was in Säcke passt ist kostenpflichtig. Nur ohne Schadstoffbelastung aus der privaten Nutzung | F40: Restabfall | G40: Restabfalltonne | H40: Aktif karbon filtresi | I40: Çantalara sığan her şey ücretlidir. Sadece özel kullanımdan kaynaklanan kirlilik olmadan | K40: Yeniden düşme | L40: Yeniden yerleştirme | M40: activated carbon filter | N40: Everything that fits in bags is subject to a fee. Only without pollutants from private use | P40: Restabfall | Q40: Restabfalltonne
A41: JXrQqeiVb5VizsfCioo6 | C41: Akustikdecke (Lärmschutzplatten) | E41: verwertbarer Bauabfall | F41: Bauabfall | G41: Deponie | H41: Akustik tavan (gürültü koruma panelleri) | J41: kullanılabilir inşaat atıkları | K41: Baufall'da | L41: Depolama sahası | M41: acoustic ceiling (noise protection panels) | O41: recyclable construction waste | P41: Bauabfall | Q41: landfill
A42: jJVqyXdEDtwkyywPiukV | C42: Album (Karton/Pappe) | F42: Papier | G42: Papiertonne, Papiersack | H42: Albüm (karton/karton) | K42: Kağıt | L42: Kağıt kutusu, kağıt çuval | M42: Album (cardboard) | P42: Paper | Q42: paper bin, paper bag
A43: DLP8DNf2lO2hNuuTy3kw | C43: Alkali-Mangan-Batterien | F43: Sonderabfall | G43: Wertstoffhof, Deponie, Händler | H43: Alkali manganez piller | K43: Tehlikeli atık | L43: Geri dönüşüm merkezi, depolama sahası, bayi | M43: alkaline manganese batteries | P43: hazardous waste | Q43: recycling center, landfill, dealer
A44: pkL7F9GuDIzVOCHsUnUI | B44: https://storage.googleapis.com/easy-recycle-app.firebasestorage.app/images/68.jpg | C44: Alkohol (Industriealkohol, Reiniger) | F44: Sonderabfall | G44: Wertstoffhof, Deponie | H44: Alkol (endüstriyel alkol, temizleyici) | K44: Tehlikeli atık | L44: Geri dönüşüm merkezi, depolama sahası | M44: alcohol (industrial alcohol, cleaner) | P44: hazardous waste | Q44: recycling center, landfill
A45: r2n6VfZ2dYBUXdjTcbHK | C45: Alleskleber | D45: Klebstoffe gehören zu den gefährlichen Abfällen (Sonderabfall). Bis zu 30 Kg (Gesamtmenge/ haushaltsübliche Mengen) Ihrer gefährlichen Abfälle täglich können Sie kostenlos auf den Wertstoffhöfen der Region Hannover oder der Deponie Hannover im Sonderabfallzwischenlager abgeben. Größere Mengen können Sie kostenpflichtig an der Sonderannahmestelle auf der Deponie Hannover abgeben. Bitte beachten Sie hierzu die Preisliste für Sonderabfall. Bitte achten Sie bei dem Transport darauf, die Gebinde gut zu kennzeichnen und auf keinen Fall mit anderen Flüssigkeiten zu vermischen. Am sichersten transportieren Sie Sonderabfälle nur dicht verschlossen in den originalen Behältern (Gebinden) sowie aufrecht stehend (z.B in einer Wanne, die Behälter aufrecht hält). Natürliche Klebstoffe, die aus pflanzlichen oder tierischen Produkten hergestellt werden, können über den Restabfall entsorgt werden. | F45: Sonderabfall | G45: Wertstoffhof, Deponie | H45: Çok amaçlı yapıştırıcı | I45: Yapıştırıcılar tehlikeli atıklardır (tehlikeli atık). Günlük 30 kg'a kadar (toplam miktar/normal ev miktarı) tehlikeli atıklarınızı Hannover bölgesindeki geri dönüşüm merkezlerine veya Hannover'deki geçici tehlikeli atık depolama tesisindeki atık depolama sahasına ücretsiz olarak teslim edebilirsiniz. Daha büyük miktarları ücret karşılığında Hannover atık depolama sahasındaki özel toplama noktasına teslim edebilirsiniz. Lütfen tehlikeli atık fiyat listesine dikkat edin. Taşıma sırasında lütfen kapların iyi etiketlendiğinden emin olun ve asla başka sıvılarla karıştırmayın. Tehlikeli atığı taşımanın en güvenli yolu, onu yalnızca orijinal kaplarında (konteynerlerde) sıkıca kapalı olarak ve dik bir şekilde (örn. kapları dik tutan bir tepside) ayakta taşımaktır. Bitkisel veya hayvansal ürünlerden yapılan doğal yapıştırıcılar atık atıklarla birlikte bertaraf edilebilir. | K45: Tehlikeli atık | L45: Geri dönüşüm merkezi, depolama sahası | M45: all-purpose glue | N45: Adhesives are classified as hazardous waste (special waste). You can dispose of up to 30 kg (total amount/normal household amounts) of your hazardous waste per day free of charge at the recycling centers in the Hanover region or at the Hanover landfill in the special waste interim storage facility. Larger quantities can be disposed of at the special collection point at the Hanover landfill for a fee. Please note the price list for special waste. When transporting, please ensure that the containers are clearly labeled and under no circumstances mixed with other liquids. The safest way to transport special waste is to keep it tightly sealed in the original containers (containers) and in an upright position (e.g. in a tub that holds the container upright). Natural adhesives made from plant or animal products can be disposed of with the residual waste. | P45: hazardous waste | Q45: recycling center, landfill
A46: TfTzmGuc70DwBIzCkphb | C46: Allzweckreiniger | D46: Bis zu 30 Kg (Gesamtmenge/ haushaltsübliche Mengen) Ihrer gefährlichen Abfälle täglich können Sie kostenlos auf den Wertstoffhöfen der Region Hannover oder der Deponie Hannover im Sonderabfallzwischenlager abgeben. Größere Mengen können Sie kostenpflichtig an der Sonderannahmestelle auf der Deponie Hannover abgeben. Bitte beachten Sie hierzu die Preisliste für Sonderabfall. Bitte achten Sie bei dem Transport darauf, die Gebinde gut zu kennzeichnen und auf keinen Fall mit anderen Flüssigkeiten zu vermischen. Am sichersten transportieren Sie Sonderabfälle nur dicht verschlossen in den originalen Behältern (Gebinden) sowie aufrecht stehend (z.B in einer Wanne, die Behälter aufrecht hält). | F46: Sonderabfall | G46: Wertstoffhof, Deponie | H46: Çok amaçlı temizleyici | I46: Günlük 30 kg'a kadar (toplam miktar/normal ev miktarı) tehlikeli atıklarınızı Hannover bölgesindeki geri dönüşüm merkezlerine veya Hannover'deki geçici tehlikeli atık depolama tesisindeki atık depolama sahasına ücretsiz olarak teslim edebilirsiniz. Daha büyük miktarları ücret karşılığında Hannover atık depolama sahasındaki özel toplama noktasına teslim edebilirsiniz. Lütfen tehlikeli atık fiyat listesine dikkat edin. Taşıma sırasında lütfen kapların iyi etiketlendiğinden emin olun ve asla başka sıvılarla karıştırmayın. Tehlikeli atığı taşımanın en güvenli yolu, onu yalnızca orijinal kaplarında (konteynerlerde) sıkıca kapalı olarak ve dik bir şekilde (örn. kapları dik tutan bir tepside) ayakta taşımaktır. | K46: Tehlikeli atık | L46: Geri dönüşüm merkezi, depolama sahası | M46: all-purpose cleaner | N46: You can dispose of up to 30 kg (total amount/normal household amounts) of your hazardous waste daily free of charge at the recycling centers in the Hanover region or at the Hanover landfill in the temporary hazardous waste storage facility. Larger amounts can be disposed of at the special collection point at the Hanover landfill for a fee. Please note the price list for hazardous waste. When transporting, please ensure that the containers are clearly labeled and under no circumstances mixed with other liquids. The safest way to transport hazardous waste is to keep it tightly sealed in the original containers (containers) and in an upright position (e.g. in a tub that holds the container upright). | P46: hazardous waste | Q46: recycling center, landfill
A47: IZ8FdbWKZJE1AlriXnAs | C47: Altakten (Komplette) | D47: Alte Akten können (soweit es der Datenschutz erfordert) durch spezielle Aktenvernichtungsfirmen entsorgt bzw. verwertet werden. Aktendeckel aus Papier/Karton gehören - wenn sie unbeschichtet sind und das Metallinlett entfernt wurden - in die Papiersammlung. Komplette Ordner können über den Restabfallsack/-behälter entsorgt werden. | F47: Restabfall | G47: Restabfalltonne | H47: Eski dosyalar (tamamlandı) | I47: Eski dosyalar (veri koruma gerektiriyorsa) özel belge imha şirketleri tarafından imha edilebilir veya geri dönüştürülebilir. Kağıt/kartondan yapılmış dosya kapakları, kaplanmamış ve metal astarı çıkarılmışsa kağıt koleksiyonuna aittir. Komple klasörler artık atık torbasına/konteynırına atılabilir. | K47: Yeniden düşme | L47: Yeniden yerleştirme | M47: Old Files (Complete) | N47: Old files can be disposed of or recycled by special document destruction companies (if data protection requires it). Paper/cardboard file covers - if they are uncoated and the metal insert has been removed - belong in the paper collection. Complete folders can be disposed of in the residual waste bag/container. | P47: Restabfall | Q47: Restabfalltonne
A48: bfsoQbkOvK7moFIiwv0e | C48: Altakten (Papier/Karton) | D48: Alte Akten können (soweit es der Datenschutz erfordert) durch spezielle Aktenvernichtungsfirmen entsorgt bzw. verwertet werden. Aktendeckel aus Papier/Karton gehören - wenn sie unbeschichtet sind und das Metallinlett entfernt wurden - in die Papiersammlung. Komplette Ordner können über den Restabfallsack/-behälter entsorgt werden. | F48: Papier | G48: Papiertonne, Papiersack | H48: Eski dosyalar (kağıt/karton) | I48: Eski dosyalar (veri koruma gerektiriyorsa) özel belge imha şirketleri tarafından imha edilebilir veya geri dönüştürülebilir. Kağıt/kartondan yapılmış dosya kapakları, kaplanmamış ve metal astarı çıkarılmışsa kağıt koleksiyonuna aittir. Komple klasörler artık atık torbasına/konteynırına atılabilir. | K48: Kağıt | L48: Kağıt kutusu, kağıt çuval | M48: old files (paper/cardboard) | N48: Old files can be disposed of or recycled by special document destruction companies (if data protection requires it). Paper/cardboard file covers - if they are uncoated and the metal insert has been removed - belong in the paper collection. Complete folders can be disposed of in the residual waste bag/container. | P48: Paper | Q48: paper bin, paper bag
A49: PcXmNEe4UVYse4h5JCAR | C49: Altauto | D49: Altfahrzeuge, Fahrzeugwracks, und Autoteile werden von zertifizierten Verwertungsbetrieben angenommen und einer Verwertung zugeführt (siehe ,). Sie werden nicht an den Wertstoffhöfen von aha angenommen; auch bei der Sperrabfallsammlung werden sie nicht mitgenommen. In zertifizierten Verwertungsbetrieben wird Ihnen ein Verwertungsnachweis für Ihr Altfahrzeug ausgehändigt; verlangen Sie diesen unbedingt!, In den Fachbetrieben werden aus diesen Fahrzeuge die Betriebsflüssigkeiten entfernt und einer fachgerechten Aufbereitung (z.B. Öle aller Art) oder Entsorgung zugeführt. Zusätzlich werden aus den Fahrzeugen die weiter einsetzbaren Ersatzteile demontiert und dem Markt zur weiteren Nutzung als kostengünstige Ersatzteile erhalten. Kabel, Metalle u.a. werden der Wiederverwertung zugeführt. Der nicht mehr nutzbare Rest des Fahrzeuges wird ordnungsgemäß entsorgt. Im Umland wenden Sie sich bitte an die entsprechende Stadt- oder Gemeindeverwaltung, bzw. an die Region Hannover. | F49: Altfahrzeug | G49: Altfahrzeugverwertung | H49: Altoto | I49: Ömrünü tamamlamış araçlar, araç enkazları ve araba parçaları, sertifikalı geri dönüşüm şirketleri tarafından kabul edilir ve geri dönüştürülür (bkz. ,). aha geri dönüşüm merkezlerine kabul edilmeyecektir; Hacimli atıkların toplanması sırasında da yanınıza alınmayacaktır. Sertifikalı geri dönüşüm şirketlerinde, ömrünü tamamlamış aracınız için size bir geri dönüşüm sertifikası verilecektir; Bunu mutlaka talep edin! Bu araçlardaki işletim sıvıları uzman atölyelerde alınır ve profesyonel işlemlere (örn. her türlü yağlar) veya imhaya gönderilir. Ayrıca halen kullanılabilecek durumda olan yedek parçalar da araçlardan sökülerek daha sonra kullanılmak üzere uygun maliyetli yedek parça olarak piyasada bulundurulmaktadır. Kablolar, metaller vb. geri dönüştürülür. Aracın artık kullanılamayan geri kalanı uygun şekilde imha edilecektir. Çevredeki bölgede lütfen ilgili şehir veya belediye idaresi veya Hannover bölgesi ile iletişime geçin. | K49: Eski araç | L49: Ömrünü tamamlamış araçların geri dönüşümü | M49: Altauto | N49: Old vehicles, vehicle wrecks and car parts are accepted by certified recycling companies and recycled (see ,). They are not accepted at aha recycling centers; they are also not taken away during bulky waste collection. Certified recycling companies will give you a recycling certificate for your old vehicle; be sure to ask for this! In the specialist companies, the operating fluids are removed from these vehicles and sent for professional processing (e.g. oils of all kinds) or disposal. In addition, the spare parts that can still be used are dismantled from the vehicles and made available to the market for further use as inexpensive spare parts. Cables, metals, etc. are recycled. The rest of the vehicle that is no longer usable is disposed of properly. In the surrounding area, please contact the relevant city or municipal administration, or the Hanover region. | P49: old vehicle | Q49: end-of-life vehicle recycling
A50: CftZrjPnJPGWeWqypF7a | B50: https://storage.googleapis.com/easy-recycle-app.firebasestorage.app/images/6.jpg | C50: Altauto, -teile | D50: Altfahrzeuge, Fahrzeugwracks, und Autoteile werden von zertifizierten Verwertungsbetrieben angenommen und einer Verwertung zugeführt (siehe ,). Sie werden nicht an den Wertstoffhöfen von aha angenommen; auch bei der Sperrabfallsammlung werden sie nicht mitgenommen. In zertifizierten Verwertungsbetrieben wird Ihnen ein Verwertungsnachweis für Ihr Altfahrzeug ausgehändigt; verlangen Sie diesen unbedingt!, In den Fachbetrieben werden aus diesen Fahrzeuge die Betriebsflüssigkeiten entfernt und einer fachgerechten Aufbereitung (z.B. Öle aller Art) oder Entsorgung zugeführt. Zusätzlich werden aus den Fahrzeugen die weiter einsetzbaren Ersatzteile demontiert und dem Markt zur weiteren Nutzung als kostengünstige Ersatzteile erhalten. Kabel, Metalle u.a. werden der Wiederverwertung zugeführt. Der nicht mehr nutzbare Rest des Fahrzeuges wird ordnungsgemäß entsorgt. Im Umland wenden Sie sich bitte an die entsprechende Stadt- oder Gemeindeverwaltung, bzw. an die Region Hannover. | F50: Altfahrzeug | G50: Altfahrzeugverwertung | H50: Altauto, sizin için | I50: Ömrünü tamamlamış araçlar, araç enkazları ve araba parçaları, sertifikalı geri dönüşüm şirketleri tarafından kabul edilir ve geri dönüştürülür (bkz. ,). aha geri dönüşüm merkezlerine kabul edilmeyecektir; Hacimli atıkların toplanması sırasında da yanınıza alınmayacaktır. Sertifikalı geri dönüşüm şirketlerinde, ömrünü tamamlamış aracınız için size bir geri dönüşüm sertifikası verilecektir; Bunu mutlaka talep edin! Bu araçlardaki işletim sıvıları uzman atölyelerde alınır ve profesyonel işlemlere (örn. her türlü yağlar) veya imhaya gönderilir. Ayrıca halen kullanılabilecek durumda olan yedek parçalar da araçlardan sökülerek daha sonra kullanılmak üzere uygun maliyetli yedek parça olarak piyasada bulundurulmaktadır. Kablolar, metaller vb. geri dönüştürülür. Aracın artık kullanılamayan geri kalanı uygun şekilde imha edilecektir. Çevredeki bölgede lütfen ilgili şehir veya belediye idaresi veya Hannover bölgesi ile iletişime geçin. | K50: Eski araç | L50: Ömrünü tamamlamış araçların geri dönüşümü | M50: Altauto, for you | N50: Old vehicles, vehicle wrecks and car parts are accepted by certified recycling companies and recycled (see ,). They are not accepted at aha recycling centers; they are also not taken away during bulky waste collection. Certified recycling companies will give you a recycling certificate for your old vehicle; be sure to ask for this! In the specialist companies, the operating fluids are removed from these vehicles and sent for professional processing (e.g. oils of all kinds) or disposal. In addition, the spare parts that can still be used are dismantled from the vehicles and given to the market for further use as inexpensive spare parts. Cables, metals, etc. are recycled. The rest of the vehicle that is no longer usable is disposed of properly. In the surrounding area, please contact the relevant city or municipal administration, or the Hanover region. | P50: old vehicle | Q50: end-of-life vehicle recycling
A51: tw7AbONJRt40sBQgcnUl | C51: Altbatterien | F51: Sonderabfall | G51: Wertstoffhof, Deponie, Händler | H51: Atık piller | K51: Tehlikeli atık | L51: Geri dönüşüm merkezi, depolama sahası, bayi | M51: old batteries | P51: hazardous waste | Q51: recycling center, landfill, dealer
A52: ibaQhiWeAFPdDYR0SnUA | B52: https://storage.googleapis.com/easy-recycle-app.firebasestorage.app/images/253.jpg | C52: Alteisen | F52: Altmetall | G52: Wertstoffhof | H52: hurda demir | K52: Altmetall | L52: Geri dönüşüm merkezi | M52: scrap iron | P52: Altmetall | Q52: recycling center
A53: uvAEGAxidHi2Jd1SjNqt | C53: Alteisen (Kleinmetall, Schraube bis Topf) | F53: Wertstoff | G53: Wertstoffhof, Gelber Sack | H53: Hurda demir (küçük metal, tencereye vidalayın) | K53: Geri dönüştürülebilir malzeme | L53: Geri dönüşüm merkezi, sarı çanta | M53: Scrap iron (small metal, screw to pot) | P53: recyclable material | Q53: recycling center, yellow bag
A54: 8lDHKi0ZmOjsNIgOtNL7 | C54: Altfahrzeuge, -teile | D54: Altfahrzeuge, Fahrzeugwracks, und Autoteile werden von zertifizierten Verwertungsbetrieben angenommen und einer Verwertung zugeführt (siehe ,). Sie werden nicht an den Wertstoffhöfen von aha angenommen; auch bei der Sperrabfallsammlung werden sie nicht mitgenommen. In zertifizierten Verwertungsbetrieben wird Ihnen ein Verwertungsnachweis für Ihr Altfahrzeug ausgehändigt; verlangen Sie diesen unbedingt!, In den Fachbetrieben werden aus diesen Fahrzeuge die Betriebsflüssigkeiten entfernt und einer fachgerechten Aufbereitung (z.B. Öle aller Art) oder Entsorgung zugeführt. Zusätzlich werden aus den Fahrzeugen die weiter einsetzbaren Ersatzteile demontiert und dem Markt zur weiteren Nutzung als kostengünstige Ersatzteile erhalten. Kabel, Metalle u.a. werden der Wiederverwertung zugeführt. Der nicht mehr nutzbare Rest des Fahrzeuges wird ordnungsgemäß entsorgt. Im Umland wenden Sie sich bitte an die entsprechende Stadt- oder Gemeindeverwaltung, bzw. an die Region Hannover. | F54: Altfahrzeug | G54: Altfahrzeugverwertung | H54: Eski araçlar, parçalar | I54: Ömrünü tamamlamış araçlar, araç enkazları ve araba parçaları, sertifikalı geri dönüşüm şirketleri tarafından kabul edilir ve geri dönüştürülür (bkz. ,). aha geri dönüşüm merkezlerine kabul edilmeyecektir; Hacimli atıkların toplanması sırasında da yanınıza alınmayacaktır. Sertifikalı geri dönüşüm şirketlerinde, ömrünü tamamlamış aracınız için size bir geri dönüşüm sertifikası verilecektir; Bunu mutlaka talep edin! Bu araçlardaki işletim sıvıları uzman atölyelerde alınır ve profesyonel işlemlere (örn. her türlü yağlar) veya imhaya gönderilir. Ayrıca halen kullanılabilecek durumda olan yedek parçalar da araçlardan sökülerek daha sonra kullanılmak üzere uygun maliyetli yedek parça olarak piyasada bulundurulmaktadır. Kablolar, metaller vb. geri dönüştürülür. Aracın artık kullanılamayan geri kalanı uygun şekilde imha edilecektir. Çevredeki bölgede lütfen ilgili şehir veya belediye idaresi veya Hannover bölgesi ile iletişime geçin. | K54: Eski araç | L54: Ömrünü tamamlamış araçların geri dönüşümü | M54: old vehicles, parts | N54: Old vehicles, vehicle wrecks and car parts are accepted by certified recycling companies and recycled (see ,). They are not accepted at aha recycling centers; they are also not taken away during bulky waste collection. Certified recycling companies will give you a recycling certificate for your old vehicle; be sure to ask for this! In the specialist companies, the operating fluids are removed from these vehicles and sent for professional processing (e.g. oils of all kinds) or disposal. In addition, the spare parts that can still be used are dismantled from the vehicles and given to the market for further use as inexpensive spare parts. Cables, metals, etc. are recycled. The rest of the vehicle that is no longer usable is disposed of properly. In the surrounding area, please contact the relevant city or municipal administration, or the Hanover region. | P54: old vehicle | Q54: end-of-life vehicle recycling
A55: Ftts7ZBj2ujbcoRr3UtP | C55: Altfette (Pflanzen-, Schlachtfett, -öl) | D55: ausgehärtet oder in einer Flasche z.B. Originalverpackung. Erkaltete Fette/Öle sind als Restabfall zu entsorgen. Auch in kleinen Mengen gehören Fette und Öle nicht in den Abfluss. Größere Mengen, z. B. aus der Gastronomie, müssen über spezielle Entsorgungsunternehmen entsorgt werden oder wenden Sie sich an unseren Gewerbekundenservice. | E55: Nie in die Spüle oder Toilette! | F55: Restabfall | G55: Restabfalltonne | H55: Kullanılmış yağlar (bitkisel, kesim yağı, sıvı yağ) | I55: kürlenmiş veya bir şişede, örneğin orijinal ambalajında. Soğutulmuş katı/sıvı yağlar artık atık olarak imha edilmelidir. Küçük miktarlarda bile katı ve sıvı yağlar çöpe atılmaz. Daha büyük miktarlar, örn. B. catering endüstrisinden gelenler, özel imha şirketleri aracılığıyla imha edilmeli veya ticari müşteri hizmetlerimizle iletişime geçilmelidir. | J55: Asla lavaboya veya tuvalete girmeyin! | K55: Yeniden düşme | L55: Yeniden yerleştirme | M55: waste fats (vegetable fat, slaughterhouse fat, oil) | N55: hardened or in a bottle, e.g. original packaging. Cooled fats/oils are to be disposed of as residual waste. Even small amounts of fats and oils do not belong in the drain. Larger amounts, e.g. from the catering industry, must be disposed of via special disposal companies or contact our commercial customer service. | O55: Never in the sink or toilet! | P55: Restabfall | Q55: Restabfalltonne
A56: ImiFpPpsZmFcVyFvOpyn | C56: Altglas (Autoscheiben, Bleiglas, Keramik usw.) | D56: Fensterglas, Sicherheitsglas, hitzebeständiges Glas, Spiegel, Keramik usw. | E56: NICHT in den Glascontainer! | F56: Restabfall | G56: Restabfalltonne | H56: Atık camlar (araba camları, kurşun camlar, seramikler vb.) | I56: Pencere camı, emniyet camı, ısıya dayanıklı cam, ayna, seramik vb. | J56: Cam kapta DEĞİLDİR! | K56: Yeniden düşme | L56: Yeniden yerleştirme | M56: Waste glass (car windows, lead glass, ceramics, etc.) | N56: Window glass, safety glass, heat-resistant glass, mirrors, ceramics, etc. | O56: NOT in the glass container! | P56: Restabfall | Q56: Restabfalltonne
A57: Iyvq2Sz1lnC6I7vunhrq | C57: Altglas (Fensterscheiben) | D57: Fensterglas, Sicherheitsglas, hitzebeständiges Glas, Spiegel, Keramik usw. | E57: NICHT in den Glascontainer! | F57: Bauabfall | G57: Deponie | H57: Atık cam (pencere camları) | I57: Pencere camı, emniyet camı, ısıya dayanıklı cam, ayna, seramik vb. | J57: Cam kapta DEĞİLDİR! | K57: Baufall'da | L57: Depolama sahası | M57: waste glass (window panes) | N57: Window glass, safety glass, heat-resistant glass, mirrors, ceramics, etc. | O57: NOT in the glass container! | P57: Bauabfall | Q57: landfill
A58: PF4QRAfLtHmCyPsJnAZU | C58: Altglas (Scherben) | D58: Fensterglas, Sicherheitsglas, hitzebeständiges Glas, Spiegel, Keramik usw. | E58: NICHT in den Glascontainer! | F58: Restabfall | G58: Restabfalltonne | H58: Atık cam (parçalar) | I58: Pencere camı, emniyet camı, ısıya dayanıklı cam, ayna, seramik vb. | J58: Cam kapta DEĞİLDİR! | K58: Yeniden düşme | L58: Yeniden yerleştirme | M58: waste glass (shards) | N58: Window glass, safety glass, heat-resistant glass, mirrors, ceramics, etc. | O58: NOT in the glass container! | P58: Restabfall | Q58: Restabfalltonne
A59: 85d9CBz3anLpfkbKrtRW | C59: Altglas als Verpackung (Konserven, Flaschen etc.) | F59: Verpackungen aus Glas | G59: Altglascontainer | H59: Ambalaj olarak atık cam (konserve ürünler, şişeler vb.) | K59: Cam ambalaj | L59: Atık cam kabı | M59: Used glass as packaging (cans, bottles, etc.) | P59: glass packaging | Q59: waste glass container
A60: UHVpt5SZU7MnGA8A6D6D | B60: https://storage.googleapis.com/easy-recycle-app.firebasestorage.app/images/29.jpg | C60: Altholz (Baumaßnahme usw.) | D60: Bis zu 1 m³ (Gesamtmenge/ haushaltsübliche Mengen) Ihrer Holzabfälle täglich können Sie kostenlos auf den Wertstoffhöfen der Region Hannover abgeben. Größere Mengen können Sie kostenpflichtig an den Deponien der Region Hannover abgeben. Bitte beachten Sie hierzu die Preisliste für die Deponieanlieferung. Die Annahmebedingungen unserer Deponien und Wertstoffhöfe finden Sie , (Deponien) und , (Wertstoffhöfe). | E60: kostenpflichtig, KEIN Sperrmüll | F60: Holzabfall | G60: Wertstoffhof | H60: Atık odun (inşaat projesi vb.) | I60: Günlük 1 m³'e kadar (toplam miktar/normal ev miktarı) ahşap atıklarınızı Hannover bölgesindeki geri dönüşüm merkezlerine ücretsiz olarak teslim edebilirsiniz. Daha büyük miktarları bir ücret karşılığında Hannover bölgesindeki atık depolama sahalarına atabilirsiniz. Lütfen çöp sahası teslimatı için fiyat listesine dikkat edin. Depolama alanlarımızın ve geri dönüşüm merkezlerimizin kabul koşulları , (çöp depolama alanları) ve , (geri dönüşüm merkezleri)'de bulunabilir. | J60: ücretli, hacimli atık YOK | K60: Holzabfall | L60: Geri dönüşüm merkezi | M60: old wood (construction work, etc.) | N60: You can dispose of up to 1 m³ (total amount/normal household amounts) of your wood waste daily free of charge at the recycling centers in the Hanover region. Larger amounts can be disposed of at the landfills in the Hanover region for a fee. Please note the price list for landfill delivery. The acceptance conditions of our landfills and recycling centers can be found at , (landfills) and , (recycling centers). | O60: fee-based, NO bulky waste | P60: Holzabfall | Q60: recycling center
A61: KihJ1VYKFhZQZ2zFpbIO | C61: Altholz, gefährlicher Abfall | D61: Hölzer wie z. B. Bahnschwellen, Jägerzäune, Pfähle, Masten sind durch umwelt- und gesundheitsschädigende Holzschutzmittel belastet. Aus Privathaushalten erfolgt die Annahme an der Deponie Hannover in Lahe bis zur Menge von 1 m³ kostenlos, größere Mengen nur gegen Gebühr. Das kontaminierte Altholz wird in einem separaten Behälter gesammelt und einer gesonderten Entsorgung zugeführt. Kontaminiertes Altholz aus Gewerbebetrieben wird an der Deponie Hannover gebührenpflichtig in einem separaten Behälter angenommen. | F61: Holzabfall, Sonderabfall | G61: Deponie | H61: Atık odun, tehlikeli atık | I61: Orman gibi B. demiryolu traversleri, av çitleri, direkleri ve direkleri çevreye ve sağlığa zararlı ahşap koruyucu maddelerle kirlenmiştir. Özel evlerden 1 m³'e kadar olan miktarlar Lahe'deki Hannover atık depolama sahasında ücretsiz olarak kabul edilir, daha büyük miktarlar ise yalnızca ücret karşılığında kabul edilir. Kirlenmiş atık odun ayrı bir kapta toplanır ve ayrı olarak bertaraf edilir. Ticari faaliyetlerden kaynaklanan kirlenmiş atık odun, Hannover atık depolama sahasına ücret karşılığında ayrı bir konteynırda kabul edilmektedir. | K61: Ahşap atıklar, tehlikeli atıklar | L61: Depolama sahası | M61: waste wood, hazardous waste | N61: Wood such as railway sleepers, picket fences, posts and masts is contaminated with wood preservatives that are harmful to the environment and health. Up to 1 m³ of waste from private households is accepted free of charge at the Hannover landfill in Lahe, larger quantities are subject to a fee. The contaminated waste wood is collected in a separate container and disposed of separately. Contaminated waste wood from commercial enterprises is accepted in a separate container at the Hannover landfill for a fee. | P61: wood waste, hazardous waste | Q61: landfill
A62: ss5ICYaKenyqbBqVQu5n | C62: Altholz, ungefährlicher Abfall | D62: Ungefährliche Abfallhölzer sind unbehandelte Hölzer, beispielsweise Voll- und Massivhölzer, Möbel, Dielen, Spanplatten, Türen aus dem Innenbereich und Holzverpackungen. Altholz wird in Kleinmengen aus Privathaushalten auf den Wertstoffhöfen angenommen (bis 1 m³ pro Tag). Größere Mengen und gewerbliche Abfälle sind kostenpflichtig an den Deponien anzuliefern. Bis zur Menge von 5 m³ holt aha auch kostenlos (größer 5 m³ gegen Gebühr) vor Ihrem Grundstück ab. Melden Sie Ihren Sperrmüll einfach , an oder vereinbaren Sie telefonisch einen Termin beim aha-Service, Tel.: 0800 - 999 11 99. | F62: Sperrabfall | G62: Wertstoffhof, Sperrabfallabholung | H62: Atık odun, tehlikesiz atık | I62: Tehlikeli olmayan atık ahşap, masif ahşap, mobilya, döşeme tahtaları, sunta, iç kapılar ve ahşap ambalajlar gibi işlenmemiş ahşaptır. Atık odun, özel evlerden küçük miktarlarda geri dönüşüm merkezlerinde kabul edilmektedir (günde 1 m³'e kadar). Daha büyük miktarlar ve ticari atıklar bir ücret karşılığında düzenli depolama alanlarına teslim edilmelidir. Aha, 5 m³'e kadar olan eşyaları da mülkünüzden ücretsiz olarak toplayacaktır (5 m³'ten fazlası ücrete tabidir). Hacimli atıklarınızı kaydettirmeniz veya aha-Service'den telefonla randevu almanız yeterlidir, Tel.: 0800 - 999 11 99. | K62: Sperrabfall | L62: Geri dönüşüm merkezi, hacimli atık toplama | M62: waste wood, non-hazardous waste | N62: Non-hazardous waste wood is untreated wood, for example solid and solid wood, furniture, floorboards, chipboard, interior doors and wooden packaging. Small amounts of old wood from private households are accepted at recycling centers (up to 1 m³ per day). Larger amounts and commercial waste must be delivered to landfills for a fee. Aha will also collect up to 5 m³ from your property free of charge (a fee applies for quantities larger than 5 m³). Simply report your bulky waste to , or make an appointment by calling the aha service, Tel.: 0800 - 999 11 99. | P62: Sperrabfall | Q62: recycling center, bulky waste collection
A63: Xay8KvLytFGlGSfx7ig7 | C63: Altkleider | D63: Zur Entsorgung Ihrer Textilien und Schuhe ( Kleidungsstücke wie Hosen, Blusen und Mäntel, Bettwäsche, Federbetten usw.) finden Sie Sammelcontainer an allen Wertstoffhöfen, den Deponien, auf öffentlichen Plätzen (Wertstoffinseln) sowie bei vielen Supermärkten. | F63: Alttextilien | G63: Wertstoffhof, Wertstoffinsel | H63: Eski giysiler | I63: Tekstil ürünlerinizin ve ayakkabılarınızın (pantolon, bluz ve mont gibi giysiler, nevresimler, yorganlar vb.) imhası için tüm geri dönüşüm merkezlerinde, atık depolama alanlarında, halka açık yerlerde (geri dönüşüm adaları) ve birçok süpermarkette toplama kapları bulacaksınız. | K63: Eski tekstiller | L63: Geri dönüşüm merkezi, geri dönüşüm adası | M63: old clothes | N63: To dispose of your textiles and shoes (items of clothing such as trousers, blouses and coats, bed linen, duvets, etc.) you will find collection containers at all recycling centers, landfills, in public places (recycling islands) and at many supermarkets. | P63: old textiles | Q63: recycling center, recycling island
A64: Cm2sV4vjqbZ2tILcn48k | C64: Altkleidung (unbrauchbar, verschmutzt) | F64: Restabfall | G64: Restabfalltonne | H64: Eski giysiler (kullanılamaz, kirli) | K64: Yeniden düşme | L64: Yeniden yerleştirme | M64: Old clothes (unusable, dirty) | P64: Restabfall | Q64: Restabfalltonne
A65: b5EUKjM7PJIgcGAIIc3E | C65: Altmedikamente | F65: Sonderabfall | G65: Wertstoffhof, Deponie | H65: Altmedikal olarak | K65: Tehlikeli atık | L65: Geri dönüşüm merkezi, depolama sahası | M65: Altmedikamente | P65: hazardous waste | Q65: recycling center, landfill
A66: NCZrUjnQLuaUoX32LEAo | C66: Altmedikamente (Praxis, Pflege oder vergleichbar) | D66: Abfälle aus der Pflege, human- und tiermedizinischen Einrichtungen und im Falle von Altmedikamenten auch Apotheken... | F66: Praxisabfall | G66: Fachbetriebe | H66: Eski ilaçlar (uygulama, bakım veya karşılaştırılabilir) | I66: Bakım, insan ve veteriner tıbbi tesislerinden ve eski ilaçlar söz konusu olduğunda eczanelerden kaynaklanan atıklar... | K66: Atık alıştırması yapın | L66: Uzman şirketler | M66: Old medicines (practice, nursing or similar) | N66: Waste from care, human and veterinary medical facilities and, in the case of old medicines, also pharmacies... | P66: practice waste | Q66: specialist companies
A67: bK9oz5jYM3PN70kjk42d | C67: Altmetall | F67: Altmetall | G67: Wertstoffhof | H67: Altmetall | K67: Altmetall | L67: Geri dönüşüm merkezi | M67: Altmetall | P67: Altmetall | Q67: recycling center
A68: fkC26tpEC0jTBFiJlwY4 | C68: Altmetall (Kleinmetall, Schraube bis Topf) | F68: Wertstoff | G68: Wertstoffhof, Gelber Sack | H68: Hurda metal (küçük metal, tencereye vida) | K68: Geri dönüştürülebilir malzeme | L68: Geri dönüşüm merkezi, sarı çanta | M68: scrap metal (small metal, screw to pot) | P68: recyclable material | Q68: recycling center, yellow bag
A69: PWFjGv1JbNhYvllIJ3Pn | C69: Altöl | D69: Altöle gehören zur Gruppe der Sonderabfälle (gefährlicher Abfall). Bei Altölen besteht eine gesetzliche Rücknahmepflicht für den Handel. Die Entsorgung von den Altölen hat aus diesem Grund über den Handel zu erfolgen. Wichtig hierfür ist die Vorlage eines Kaufbeleges. Auf Grund dessen kann eine entsprechende Menge Altöl zurückgegeben werden. Sollte der Kaufbeleg nicht mehr vorliegen, so kann in Ausnahmefällen eine Entsorgung von 30 kg (haushaltsübliche Menge/Gesamtmenge) über die Sonderabfallannahme auf der Deponie Hannover erfolgen. Altöle werden nicht auf den Wertstoffhöfen angenommen. | F69: Sonderabfall | G69: Deponie | H69: Atık yağ | I69: Atık yağlar özel atık (tehlikeli atık) grubuna aittir. Perakendecilerin kullanılmış yağları geri alma zorunluluğu yasal olarak bulunmaktadır. Bu nedenle atık yağların perakendeciler aracılığıyla bertaraf edilmesi gerekmektedir. Satın alma belgesinin ibraz edilmesi önemlidir. Bu nedenle ilgili miktarda kullanılmış yağ iade edilebilir. Satın alma belgesinin artık mevcut olmaması durumunda, istisnai durumlarda 30 kg (normal ev miktarı/toplam miktar) Hannover atık depolama sahasındaki tehlikeli atık kabulü yoluyla bertaraf edilebilir. Kullanılmış yağlar geri dönüşüm merkezlerine kabul edilmez. | K69: Tehlikeli atık | L69: Depolama sahası | M69: waste oil | N69: Used oils belong to the group of hazardous waste. There is a legal obligation for retailers to take used oils back. For this reason, used oils must be disposed of through retailers. It is important to present a purchase receipt. This allows a corresponding amount of used oil to be returned. If the purchase receipt is no longer available, in exceptional cases 30 kg (normal household amount/total amount) of used oil can be disposed of via the hazardous waste collection point at the Hanover landfill. Used oils are not accepted at recycling centers. | P69: hazardous waste | Q69: landfill
A70: jiAvXsXhGyT3GRRIVVU2 | C70: Altöl (Pflanzen-, Schlachtfett, -öl) | D70: • nur in haushaltsüblichen Mengen (kein Gewerbe),• ausgehärtet oder in einer Flasche z.B. Originalverpackung,Nie in die Spüle oder Toilette! | F70: Restabfall | G70: Restabfalltonne | H70: Atık yağlar (bitkisel, kesim yağı, sıvı yağ) | I70: • yalnızca normal ev miktarlarında (ticari değil), • sertleştirilmiş veya şişede, örneğin orijinal ambalajında, asla lavaboda veya tuvalette değil! | K70: Yeniden düşme | L70: Yeniden yerleştirme | M70: used oil (vegetable fat, slaughterhouse fat, oil) | N70: • only in normal household quantities (not for commercial use), • hardened or in a bottle e.g. original packaging, Never pour into the sink or toilet! | P70: Restabfall | Q70: Restabfalltonne
A71: LIxyjDHFMvB1U5CJfSvo | C71: Altöl (technische Schmiermittel) | F71: Sonderabfall | G71: Wertstoffhof, Deponie | H71: Atık yağ (teknik yağlayıcılar) | K71: Tehlikeli atık | L71: Geri dönüşüm merkezi, depolama sahası | M71: used oil (technical lubricants) | P71: hazardous waste | Q71: recycling center, landfill
A72: 5z75zN6gGHEPAfGs6CcP | C72: Altöl (Verbrennungsmotoren- oder Getriebeöl) | D72: Problemstoff mit gesonderten Abgabebedingungen | F72: Sonderabfall | G72: Händler | H72: Kullanılmış yağ (yanmalı motor veya şanzıman yağı) | I72: Özel teslimat koşullarına sahip sorunlu madde | K72: Tehlikeli atık | L72: Satıcı | M72: used oil (combustion engine or transmission oil) | N72: problematic substance with special delivery conditions | P72: hazardous waste | Q72: dealers
A73: idaAp6okSWqPnAPLkSxm | C73: Altölbehälter (Dose, Flasche, Kanister - Mineralöl, schadstoffhaltige Verpackung) | D73: bestimmte Verpackungen die Schadstoffe enthalten haben, dürfen NICHT in die Wertstofftonne!,An den Tankstellen sind für die dort verkauften Mineralölbehälter (bis 1 Liter)... | F73: Sonderabfall | G73: Wertstoffhof, Deponie | H73: Atık yağ kabı (teneke, şişe, bidon – madeni yağ, kirletici içeren ambalajlar) | I73: Benzin istasyonlarında, satılan madeni yağ kaplarının (1 litreye kadar) geri dönüşüm kutusuna atılmasına izin VERİLMEZ! | K73: Tehlikeli atık | L73: Geri dönüşüm merkezi, depolama sahası | M73: Used oil container (can, bottle, canister - mineral oil, packaging containing harmful substances) | N73: Certain packaging containing harmful substances must NOT be put in the recycling bin! At petrol stations, the mineral oil containers (up to 1 litre) sold there... | P73: hazardous waste | Q73: recycling center, landfill
A74: FMruPJjXt4KbmDvpdqBz | C74: Altpapier | F74: Papier | G74: Papiertonne, Papiersack | H74: Atık kağıt | K74: Kağıt | L74: Kağıt kutusu, kağıt çuval | M74: waste paper | P74: Paper | Q74: paper bin, paper bag
A75: nCeCu0OLSMag1IKhsxd6 | C75: Altreifen | D75: Auto- und Motorradreifen dürfen nicht in den Restabfall | F75: Wertstoff | G75: Verwerter, Wertstoffhof | H75: eski lastikler | I75: Araba ve motosiklet lastiklerinin genel çöp kutusuna atılmasına izin verilmez | K75: Geri dönüştürülebilir malzeme | L75: geri dönüşümcü, geri dönüşüm merkezi | M75: old tires | N75: Car and motorcycle tires must not be disposed of in residual waste | P75: recyclable material | Q75: recycler, recycling center
A76: PjEipsRKzgT8l3exZAjF | C76: Alttextilien | F76: Wertstoff | G76: Wertstoffhof, Wertstoffinsel | H76: Eski tekstiller | K76: Geri dönüştürülebilir malzeme | L76: Geri dönüşüm merkezi, geri dönüşüm adası | M76: old textiles | P76: recyclable material | Q76: recycling center, recycling island
A77: Ie6P5tDmOsx7oYR4Oiv7 | C77: Aluminium | F77: Altmetall | G77: Wertstoffhof | H77: Alüminyum | K77: Altmetall | L77: Geri dönüşüm merkezi | M77: Aluminium | P77: Altmetall | Q77: recycling center
A78: 8zzZeBAk3pt5xXJcIAkS | C78: Aluminium (Kleinmetall, Schraube bis Topf) | D78: Aluminiumdeckel von Joghurt- und Sahnebechern oder auch die Aluschalen der Teelichter können gesammelt und über die Wertstoffsammlung im Wertstoffsack verwertet werden. Größere Aluminiumteile können beim Schrotthandel (siehe <link http: www.gelbeseiten.de yp quick.yp external-link-new-window einen externen link in einem neuen>Gelbe Seiten) oder bei den Wertstoffhöfen abgegeben werden. | F78: Wertstoff | G78: Wertstoffhof, Gelber Sack | H78: Alüminyum (küçük metal, tencereye vidalayın) | I78: Yoğurt ve krema kaplarının alüminyum kapakları veya çay ışıklarının alüminyum kabukları, geri dönüşüm torbasında toplanıp geri dönüştürülebilir. Daha büyük alüminyum parçalar hurda satıcılarına (bkz. <link http: www.gelbeseiten.de yp quick.yp external-link-new-window ve harici bağlantı yeni>Sarı Sayfalar) veya geri dönüşüm merkezlerine teslim edilebilir. | K78: Geri dönüştürülebilir malzeme | L78: Geri dönüşüm merkezi, sarı çanta | M78: Aluminum (small metal, screw to pot) | N78: Aluminum lids from yogurt and cream pots or the aluminum cups from tea lights can be collected and recycled in recycling bags. Larger aluminum parts can be handed in to scrap dealers (see <link http: www.gelbeseiten.de yp quick.yp external-link-new-window an external link in a new>Yellow Pages) or to recycling centers. | P78: recyclable material | Q78: recycling center, yellow bag
A79: 3dNaXApC296Ex43GC10A | C79: Aluminiumteile (Groß) | D79: Aluminiumdeckel von Joghurt- und Sahnebechern oder auch die Aluschalen der Teelichter können gesammelt und über die Wertstoffsammlung im Wertstoffsack verwertet werden. Größere Aluminiumteile können beim Schrotthandel (siehe <link http: www.gelbeseiten.de yp quick.yp external-link-new-window einen externen link in einem neuen>Gelbe Seiten) oder bei den Wertstoffhöfen abgegeben werden. | F79: Altmetall | G79: Schrotthandel | H79: Alüminyum Parçalar (Büyük) | I79: Yoğurt ve krema kaplarının alüminyum kapakları veya çay ışıklarının alüminyum kabukları toplanıp geri dönüşüm torbasında geri dönüştürülebilir. Daha büyük alüminyum parçalar hurda satıcılarına (bkz. <link http: www.gelbeseiten.de yp quick.yp external-link-new-window ve yeni>Sarı Sayfalarda harici bağlantı) veya geri dönüşüm merkezlerine teslim edilebilir. | K79: Alt metal | L79: hurda ticareti | M79: aluminum parts (large) | N79: Aluminum lids from yogurt and cream pots or the aluminum cups from tea lights can be collected and recycled in recycling bags. Larger aluminum parts can be handed in to scrap dealers (see <link http: www.gelbeseiten.de yp quick.yp external-link-new-window an external link in a new>Yellow Pages) or to recycling centers. | P79: Altmetall | Q79: scrap metal trade
A80: Z6rEilIUqTv4J85Tz47d | C80: Aluminiumverpackung (z.B. Deckel, Folien, Tuben, Grillschale, Jogurtdeckel (ausgekratzt)) | F80: Wertstoff | G80: Wertstoffhof, Gelber Sack | H80: Alüminyum ambalaj (örn. kapaklar, folyo, tüpler, ızgara tepsisi, yoğurt kapakları (kazınmış)) | K80: Geri dönüştürülebilir malzeme | L80: Geri dönüşüm merkezi, sarı çanta | M80: Aluminium packaging (e.g. lids, foils, tubes, grill trays, yogurt lids (scraped out)) | P80: recyclable material | Q80: recycling center, yellow bag
A81: h2HHAi9rzt5ARjsbCmx7 | C81: Amalgam (Quecksilberhaltig) | F81: Sonderabfall | G81: Wertstoffhof, Deponie | H81: Amalgam (cıva içerir) | K81: Tehlikeli atık | L81: Geri dönüşüm merkezi, depolama sahası | M81: amalgam (mercury-containing) | P81: hazardous waste | Q81: recycling center, landfill
A82: AO39B2SoWJI3JXmsrWwj | C82: Ambrosia | D82: Bitte verpacken Sie die giftigen Pflanzen gut und gesondert von anderen Materialien. Bis zu 1 m³ (Gesamtmenge/ haushaltsübliche Mengen) Ihrer giftigen oder invasiven Pflanzen täglich können Sie kostenlos auf den Wertstoffhöfen der Region Hannover (im Sperrabfall) abgeben. Größere Mengen können Sie kostenpflichtig an den Deponien der Region Hannover abgeben. Bitte beachten Sie hierzu die Preisliste für die Deponieanlieferung. finden Sie die Annahmebedingungen unserer Wertstoffhofe, die der Deponien. | F82: giftigen oder invasiven Pflanzen | G82: Wertstoffhof, Deponie | H82: Ambrosia | I82: Lütfen zehirli bitkileri iyi bir şekilde ve diğer malzemelerden ayrı olarak paketleyiniz. Zehirli veya istilacı bitkilerinizin günlük 1 m³'e (toplam miktar/normal ev miktarı) kadarını Hannover bölgesindeki geri dönüşüm merkezlerinde (hacimli atık olarak) ücretsiz olarak imha edebilirsiniz. Daha büyük miktarları bir ücret karşılığında Hannover bölgesindeki atık depolama sahalarına atabilirsiniz. Lütfen çöp sahası teslimatı için fiyat listesine dikkat edin. Geri dönüşüm merkezlerimizin ve atık depolama sahalarının kabul koşullarını bulacaksınız. | K82: zehirli veya istilacı bitkiler | L82: Geri dönüşüm merkezi, depolama sahası | M82: Ambrosia | N82: Please pack the poisonous plants well and separately from other materials. You can dispose of up to 1 m³ (total quantity/normal household quantities) of your poisonous or invasive plants per day free of charge at the recycling centers in the Hanover region (in bulky waste). Larger quantities can be disposed of at the landfills in the Hanover region for a fee. Please note the price list for landfill delivery. You can find the acceptance conditions of our recycling centers and those of the landfills. | P82: poisonous or invasive plants | Q82: recycling center, landfill
A83: QC82rNxYvRAfqLg5E408 | C83: Ameisengift | D83: Bis zu 30 Kg (Gesamtmenge/ haushaltsübliche Mengen) Ihrer gefährlichen Abfälle täglich können Sie kostenlos auf den Wertstoffhöfen der Region Hannover oder der Deponie Hannover im Sonderabfallzwischenlager abgeben. Größere Mengen können Sie kostenpflichtig an der Sonderannahmestelle auf der Deponie Hannover abgeben. Bitte beachten Sie hierzu die Preisliste für Sonderabfall. Bitte achten Sie bei dem Transport darauf, die Gebinde gut zu kennzeichnen und auf keinen Fall mit anderen Flüssigkeiten zu vermischen. Am sichersten transportieren Sie Sonderabfälle nur dicht verschlossen in den originalen Behältern (Gebinden) sowie aufrecht stehend (z.B in einer Wanne, die Behälter aufrecht hält). | F83: Sonderabfall | G83: Wertstoffhof, Deponie | H83: Karınca zehiri | I83: Günlük 30 kg'a kadar (toplam miktar/normal ev miktarı) tehlikeli atıklarınızı Hannover bölgesindeki geri dönüşüm merkezlerine veya Hannover'deki geçici tehlikeli atık depolama tesisindeki atık depolama sahasına ücretsiz olarak teslim edebilirsiniz. Daha büyük miktarları ücret karşılığında Hannover atık depolama sahasındaki özel toplama noktasına teslim edebilirsiniz. Lütfen tehlikeli atık fiyat listesine dikkat edin. Taşıma sırasında lütfen kapların iyi etiketlendiğinden emin olun ve asla başka sıvılarla karıştırmayın. Tehlikeli atığı taşımanın en güvenli yolu, onu yalnızca orijinal kaplarında (konteynerlerde) sıkıca kapalı olarak ve dik bir şekilde (örn. kapları dik tutan bir tepside) ayakta taşımaktır. | K83: Tehlikeli atık | L83: Geri dönüşüm merkezi, depolama sahası | M83: ant poison | N83: You can dispose of up to 30 kg (total amount/normal household amounts) of your hazardous waste daily free of charge at the recycling centers in the Hanover region or at the Hanover landfill in the temporary hazardous waste storage facility. Larger amounts can be disposed of at the special collection point at the Hanover landfill for a fee. Please note the price list for hazardous waste. When transporting, please ensure that the containers are clearly labeled and under no circumstances mixed with other liquids. The safest way to transport hazardous waste is to keep it tightly sealed in the original containers (containers) and in an upright position (e.g. in a tub that holds the container upright). | P83: hazardous waste | Q83: recycling center, landfill
A84: vNwXyVpnfMwLtXcljKvr | C84: Ameisenmittel | F84: Sonderabfall | G84: Wertstoffhof, Deponie | H84: Karınca ilaçları | K84: Tehlikeli atık | L84: Geri dönüşüm merkezi, depolama sahası | M84: ant repellents | P84: hazardous waste | Q84: recycling center, landfill
A85: ZvBG9cnlDT8tu8pQPDz1 | C85: Ammoniak | D85: Bis zu 30 Kg (Gesamtmenge/ haushaltsübliche Mengen) Ihrer gefährlichen Abfälle täglich können Sie kostenlos auf den Wertstoffhöfen der Region Hannover oder der Deponie Hannover im Sonderabfallzwischenlager abgeben. Größere Mengen können Sie kostenpflichtig an der Sonderannahmestelle auf der Deponie Hannover abgeben. Bitte beachten Sie hierzu die Preisliste für Sonderabfall. Bitte achten Sie bei dem Transport darauf, die Gebinde gut zu kennzeichnen und auf keinen Fall mit anderen Flüssigkeiten zu vermischen. Am sichersten transportieren Sie Sonderabfälle nur dicht verschlossen in den originalen Behältern (Gebinden) sowie aufrecht stehend (z.B in einer Wanne, die Behälter aufrecht hält). | F85: Sonderabfall | G85: Wertstoffhof, Deponie | H85: Amonyak | I85: Günlük 30 kg'a kadar (toplam miktar/normal ev miktarı) tehlikeli atıklarınızı Hannover bölgesindeki geri dönüşüm merkezlerine veya Hannover'deki geçici tehlikeli atık depolama tesisindeki atık depolama sahasına ücretsiz olarak teslim edebilirsiniz. Daha büyük miktarları ücret karşılığında Hannover atık depolama sahasındaki özel toplama noktasına teslim edebilirsiniz. Lütfen tehlikeli atık fiyat listesine dikkat edin. Taşıma sırasında lütfen kapların iyi etiketlendiğinden emin olun ve asla başka sıvılarla karıştırmayın. Tehlikeli atığı taşımanın en güvenli yolu, onu yalnızca orijinal kaplarında (konteynerlerde) sıkıca kapalı olarak ve dik bir şekilde (örn. kapları dik tutan bir tepside) ayakta taşımaktır. | K85: Tehlikeli atık | L85: Geri dönüşüm merkezi, depolama sahası | M85: Ammonia | N85: You can dispose of up to 30 kg (total amount/normal household amounts) of your hazardous waste daily free of charge at the recycling centers in the Hanover region or at the Hanover landfill in the temporary hazardous waste storage facility. Larger amounts can be disposed of at the special collection point at the Hanover landfill for a fee. Please note the price list for hazardous waste. When transporting, please ensure that the containers are clearly labeled and under no circumstances mixed with other liquids. The safest way to transport hazardous waste is to keep it tightly sealed in the original containers (containers) and in an upright position (e.g. in a tub that holds the container upright). | P85: hazardous waste | Q85: recycling center, landfill
A86: 4iVufcNjSoOcd1RZMQer | C86: Ammoniaklösung | F86: Sonderabfall | G86: Wertstoffhof, Deponie | H86: amonyak çözeltisi | K86: Tehlikeli atık | L86: Geri dönüşüm merkezi, depolama sahası | M86: ammonia solution | P86: hazardous waste | Q86: recycling center, landfill
A87: cQr0lWN9JELxe6jZiJFK | C87: Anpflanztöpfe (Kunststoff) | F87: Wertstoff | G87: Wertstoffhof, Gelber Sack | H87: Bitki saksıları (plastik) | K87: Geri dönüştürülebilir malzeme | L87: Geri dönüşüm merkezi, sarı çanta | M87: plant pots (plastic) | P87: recyclable material | Q87: recycling center, yellow bag
A88: BNM9AcOmCxH1tr7wvwX0 | C88: Anrufbeantworter | E88: ACHTUNG enthaltene Akkus/Batterien entfernen | F88: Elektrogeräte | G88: Wertstoffhof | H88: telesekreter | J88: DİKKAT birlikte verilen şarj edilebilir pilleri/pilleri çıkarın | K88: Elektrikli ev aletleri | L88: Geri dönüşüm merkezi | M88: answering machine | O88: ATTENTION: Remove any batteries | P88: electrical appliances | Q88: recycling center
A89: KCVIcQTPds1QTnPSElOf | C89: Anstreichfarbe | D89: Bis zu 30 Kg (Gesamtmenge/ haushaltsübliche Mengen) Ihrer gefährlichen Abfälle täglich können Sie kostenlos auf den Wertstoffhöfen der Region Hannover oder der Deponie Hannover im Sonderabfallzwischenlager abgeben. Größere Mengen können Sie kostenpflichtig an der Sonderannahmestelle auf der Deponie Hannover abgeben. Bitte beachten Sie hierzu die Preisliste für Sonderabfall. Bitte achten Sie bei dem Transport darauf, die Gebinde gut zu kennzeichnen und auf keinen Fall mit anderen Flüssigkeiten zu vermischen. Am sichersten transportieren Sie Sonderabfälle nur dicht verschlossen in den originalen Behältern (Gebinden) sowie aufrecht stehend (z.B in einer Wanne, die Behälter aufrecht hält). | F89: Sonderabfall | G89: Wertstoffhof, Deponie | H89: boyamak | I89: Günlük 30 kg'a kadar (toplam miktar/normal ev miktarı) tehlikeli atıklarınızı Hannover bölgesindeki geri dönüşüm merkezlerine veya Hannover'deki geçici tehlikeli atık depolama tesisindeki atık depolama sahasına ücretsiz olarak teslim edebilirsiniz. Daha büyük miktarları ücret karşılığında Hannover atık depolama sahasındaki özel toplama noktasına teslim edebilirsiniz. Lütfen tehlikeli atık fiyat listesine dikkat edin. Taşıma sırasında lütfen kapların iyi etiketlendiğinden emin olun ve asla başka sıvılarla karıştırmayın. Tehlikeli atığı taşımanın en güvenli yolu, onu yalnızca orijinal kaplarında (konteynerlerde) sıkıca kapalı olarak ve dik bir şekilde (örn. kapları dik tutan bir tepside) ayakta taşımaktır. | K89: Tehlikeli atık | L89: Geri dönüşüm merkezi, depolama sahası | M89: paint | N89: You can dispose of up to 30 kg (total amount/normal household amounts) of your hazardous waste daily free of charge at the recycling centers in the Hanover region or at the Hanover landfill in the temporary hazardous waste storage facility. Larger amounts can be disposed of at the special collection point at the Hanover landfill for a fee. Please note the price list for hazardous waste. When transporting, please ensure that the containers are clearly labeled and under no circumstances mixed with other liquids. The safest way to transport hazardous waste is to keep it tightly sealed in the original containers (containers) and in an upright position (e.g. in a tub that holds the container upright). | P89: hazardous waste | Q89: recycling center, landfill
A90: 5c9918L3QMwvQHWJgsFt | C90: Antenne | F90: Altmetall, Sperrabfall | G90: Wertstoffhof, Sperrabfallabholung | H90: Anten | K90: Demir dışı metaller, atık malzemeler | L90: Geri dönüşüm merkezi, hacimli atık toplama | M90: Antenna | P90: Non-ferrous metals, waste materials | Q90: recycling center, bulky waste collection
A91: Tc41OjOWPpw7jYt9bQN2 | C91: Antenne (mit elektr. Verstärker) | F91: Elektrogeräte | G91: Wertstoffhof | H91: Anten (elektrik amplifikatörlü) | K91: Elektrikli ev aletleri | L91: Geri dönüşüm merkezi | M91: antenna (with electric amplifier) | P91: electrical appliances | Q91: recycling center
A92: LuoAI4rxbTe5HeyzVEYv | C92: Antibeschlagmittel | F92: Sonderabfall | G92: Wertstoffhof, Deponie | H92: Buğu önleyici madde | K92: Tehlikeli atık | L92: Geri dönüşüm merkezi, depolama sahası | M92: anti-fog agents | P92: hazardous waste | Q92: recycling center, landfill
A93: KEvvUO4H0Z7cOj7pEeqC | C93: Antifouling | F93: Sonderabfall | G93: Wertstoffhof, Deponie | H93: Kirlenme önleyici | K93: Tehlikeli atık | L93: Geri dönüşüm merkezi, depolama sahası | M93: Antifouling | P93: hazardous waste | Q93: recycling center, landfill
A94: DpKe7Xdd7AJ5Gk2jAe63 | B94: https://storage.googleapis.com/easy-recycle-app.firebasestorage.app/images/120.jpg | C94: Apfelsinenschalen | F94: Bioabfall | G94: Biotonne, Biosack | H94: Portakal kabukları | K94: Biyolojik çöküş | L94: Biyo bin, biyo çanta | M94: orange peels | P94: Bioabfall | Q94: organic waste bin, organic waste bag
A95: j6Qe68wRRAkVnY39izdD | C95: Aquarienpumpe, -filter, -heizung | D95: ACHTUNG enthaltene Akkus/Batterien entfernen | F95: Elektrogeräte | G95: Wertstoffhof | H95: Akvaryum pompası, filtre, ısıtıcı | I95: DİKKAT birlikte verilen şarj edilebilir pilleri/pilleri çıkarın | K95: Elektrikli ev aletleri | L95: Geri dönüşüm merkezi | M95: aquarium pump, filter, heater | N95: ATTENTION: Remove any batteries | P95: electrical appliances | Q95: recycling center
A96: wkGfZH1a3SXtLVc2Gb8s | B96: https://storage.googleapis.com/easy-recycle-app.firebasestorage.app/images/178.jpg | C96: Aquarium | F96: Sperrabfall | G96: Wertstoffhof, Sperrabfallabholung | H96: Akvaryum | K96: Sperrabfall | L96: Geri dönüşüm merkezi, hacimli atık toplama | M96: Aquarium | P96: Sperrabfall | Q96: recycling center, bulky waste collection
A97: I7ffWzuYtG54uoROCa00 | B97: https://storage.googleapis.com/easy-recycle-app.firebasestorage.app/images/141.jpg | C97: Aquariumkies | D97: Bis zu 1m ³ reinen Kies können Sie täglich auf den Wertstoffhöfen oder den Deponien der Region Hannover kostenlos entsorgen. Bitte beachten Sie, dass möglichst keine Erde an dem Kies haftet. | F97: Wertstoff | G97: Wertstoffhof, Deponie | H97: Akvaryumkies | I97: Her gün 1 m³'e kadar saf çakılı Hannover bölgesindeki geri dönüşüm merkezlerinde veya atık depolama sahalarında ücretsiz olarak imha edebilirsiniz. Lütfen mümkünse çakılın üzerine toprak yapışmadığından emin olun. | K97: Geri dönüştürülebilir malzeme | L97: Geri dönüşüm merkezi, depolama sahası | M97: Aquariumkies | N97: You can dispose of up to 1m³ of pure gravel every day free of charge at the recycling centers or landfills in the Hanover region. Please ensure that no soil sticks to the gravel. | P97: recyclable material | Q97: recycling center, landfill
A98: 0et5Oi9iaHRnXTP6W2Lh | C98: Arbeitshandschuhe (Silikon, Nitril, Latex, Leder, Stoff, etc.) | F98: Restabfall | G98: Restabfalltonne | H98: İş eldivenleri (silikon, nitril, lateks, deri, kumaş vb.) | K98: Yeniden düşme | L98: Yeniden yerleştirme | M98: Work gloves (silicone, nitrile, latex, leather, fabric, etc.) | P98: Restabfall | Q98: Restabfalltonne
A99: PgNVvJ7O3BF42knfM5uN | B99: https://storage.googleapis.com/easy-recycle-app.firebasestorage.app/images/119.jpg | C99: Arbeitsplatte (Küche) | D99: (max. 2,20 m x 1,50 m x 0,75 m) | F99: Sperrabfall | G99: Wertstoffhof, Sperrabfallabholung | H99: Tezgah (mutfak) | I99: (maks. 2,20 m x 1,50 m x 0,75 m) | K99: Sperrabfall | L99: Geri dönüşüm merkezi, hacimli atık toplama | M99: worktop (kitchen) | N99: (max. 2,20 m x 1,50 m x 0,75 m) | P99: Sperrabfall | Q99: recycling center, bulky waste collection
A100: o9NDMvwaFpuLi15Q7izl | C100: Armatur | F100: Altmetall, Sperrabfall | G100: Wertstoffhof, Sperrabfallabholung | H100: Armatür | K100: Demir dışı metaller, atık malzemeler | L100: Geri dönüşüm merkezi, hacimli atık toplama | M100: Armature | P100: Non-ferrous metals, waste materials | Q100: recycling center, bulky waste collection
...

Sheet Hannover
A1: title | B1: categories | C1: disposal | D1: descriptions | E1: desc2 | F1: category2 | G1: disp2 | H1: desc_test | I1: cat_test | J1: disp_test | K1: status
A2: Abbeizmittel | B2: Sonderabfall | C2: Wertstoffhof,Deponie Hannover - Sonderabfallannahmestelle | D2: Bis zu 30kg (Gesamtmenge/ haushaltsübliche Mengen) Ihrer gefährlichen Abfälle, können Sie täglich kostenlos auf allen Wertstoffhöfen abgeben. Auf den Wertstoffhöfen der Region werden Sonderabfälle in Gebinden bis zu einer Größe von max. 10 Litern entgegengenommen. Größere Mengen oder Gebinde können kostenpflichtig an der Sonderannahmestelle auf der Deponie Hannover Lahe abgeben. Gebinde über 10 Liter sind ebenfalls an der Deponie in Hannover anzuliefern.,Bitte beachten Sie die Mengenbegrenzung der einzelnen Abfälle, auf der Preisliste für Sonderabfall.,Bitte achten Sie bei dem Transport darauf, die Gebinde gut zu kennzeichnen und auf keinen Fall mit anderen Flüssigkeiten zu vermischen. Am sichersten transportieren Sie Sonderabfälle nur dicht verschlossen in den originalen Behältern (Gebinden) sowie aufrechtstehend (z.B. in einer Wanne, die Behälter aufrecht hält).,Wichtig: Nutzen Sie bitte die Abgabezeiten für Gewerbekunden (Mo. bis Do. von 7.00 – 14.00 Uhr und Fr. von 7.00 – 12.00 Uhr), wenn Sie größere Mengen an Sonderabfällen abgeben wollen.,Sachstand 19.07.2023 | E2: =VLOOKUP(A2,All!$C$2:$D$2424,2,FALSE) -> Bis zu 30 Kg (Gesamtmenge/ haushaltsübliche Mengen) Ihrer gefährlichen Abfälle täglich können Sie kostenlos auf den Wertstoffhöfen der Region Hannover oder der Deponie Hannover im Sonderabfallzwischenlager abgeben. Größere Mengen können Sie kostenpflichtig an der Sonderannahmestelle auf der Deponie Hannover abgeben. Bitte beachten Sie hierzu die Preisliste für Sonderabfall. Bitte achten Sie bei dem Transport darauf, die Gebinde gut zu kennzeichnen und auf keinen Fall mit anderen Flüssigkeiten zu vermischen. Am sichersten transportieren Sie Sonderabfälle nur dicht verschlossen in den originalen Behältern (Gebinden) sowie aufrecht stehend (z.B in einer Wanne, die Behälter aufrecht hält). | F2: =VLOOKUP(A2,All!$C$2:$F$2424,4,FALSE) -> Sonderabfall | G2: =VLOOKUP(A2,All!$C$2:$G$2424,5,FALSE) -> Wertstoffhof, Deponie | H2: =IF(D2=E2,"ok","no") -> no | I2: =IF(B2=F2,"ok","no") -> ok | J2: =IF(C2=G2,"ok","no") -> no
A3: Abdeckfolien | B3: Leichtverpackungen | C3: Wertstoffhof,Gelbe Tonne | D3: Abdeckfolien aus Kunststoff sind aus Polyethylen (PE). Saubere PE-Folien können wiederverwertet werden. Kleine Mengen nehmen die Wertstoffhöfe im Wertstoffsack an., , Größere Mengen aus Gewerbe oder Industrie werden ebenfalls von aha in Containern gesammelt. Wenden Sie sich an den Gewerbekundenservice von aha. | E3: =VLOOKUP(A3,All!$C$2:$D$2424,2,FALSE) -> Abdeckfolien aus Kunststoff sind aus Polyethylen (PE). Saubere PE-Folien können wiederverwertet werden. Kleine Mengen nehmen die Wertstoffhöfe im Wertstoffsack an. Größere Mengen aus Gewerbe oder Industrie werden ebenfalls von aha in Containern gesammelt. Wenden Sie sich an den Gewerbekundenservice von aha. | F3: =VLOOKUP(A3,All!$C$2:$F$2424,4,FALSE) -> Leichtverpackungen | G3: =VLOOKUP(A3,All!$C$2:$G$2424,5,FALSE) -> Wertstoffhof, Gelber Sack | H3: =IF(D3=E3,"ok","no") -> no | I3: =IF(B3=F3,"ok","no") -> ok | J3: =IF(C3=G3,"ok","no") -> no
A4: Abflussreiniger/Rohrreiniger | B4: Sonderabfall | C4: Wertstoffhof,Deponie Hannover - Sonderabfallannahmestelle | D4: Bis zu 30kg (Gesamtmenge/ haushaltsübliche Mengen) Ihrer gefährlichen Abfälle, können Sie täglich kostenlos auf allen Wertstoffhöfen abgeben. Auf den Wertstoffhöfen der Region werden Sonderabfälle in Gebinden bis zu einer Größe von max. 10 Litern entgegengenommen. Größere Mengen oder Gebinde können kostenpflichtig an der Sonderannahmestelle auf der Deponie Hannover Lahe abgeben. Gebinde über 10 Liter sind ebenfalls an der Deponie in Hannover anzuliefern.,Bitte beachten Sie die Mengenbegrenzung der einzelnen Abfälle, auf der Preisliste für Sonderabfall.,Bitte achten Sie bei dem Transport darauf, die Gebinde gut zu kennzeichnen und auf keinen Fall mit anderen Flüssigkeiten zu vermischen. Am sichersten transportieren Sie Sonderabfälle nur dicht verschlossen in den originalen Behältern (Gebinden) sowie aufrechtstehend (z.B. in einer Wanne, die Behälter aufrecht hält).,Wichtig: Nutzen Sie bitte die Abgabezeiten für Gewerbekunden (Mo. bis Do. von 7.00 – 14.00 Uhr und Fr. von 7.00 – 12.00 Uhr), wenn Sie größere Mengen an Sonderabfällen abgeben wollen.,Sachstand 19.07.2023 | E4: =VLOOKUP(A4,All!$C$2:$D$2424,2,FALSE) -> #N/A | F4: =VLOOKUP(A4,All!$C$2:$F$2424,4,FALSE) -> #N/A | G4: =VLOOKUP(A4,All!$C$2:$G$2424,5,FALSE) -> #N/A | H4: =IF(D4=E4,"ok","no") -> #N/A | I4: =IF(B4=F4,"ok","no") -> #N/A | J4: =IF(C4=G4,"ok","no") -> #N/A
A5: Abscheideranlage | B5: Sonderabfall | C5: Der Zweckverband Abfallwirtschaft Region Hannover (aha) | D5: aha entsorgt in der Region Hannover die Inhalte von Benzin- und Ölabscheidern und von Sand- und Schlammfängen. Im Auftrag von aha führt die Stadtentwässerung Hannover die Reinigung von Abscheideranlagen regionsweit aus., , Ansprechpartner bei der Stadtentwässerung Hannover sind Herr Münder und Herr Wagner, Tel: 0511 - 168 - 47440., , Bei Abwesenheit nimmt ein Anrufbeantworter die Anfragen auf., , , , Störungsmeldestelle der Stadtentwässerung, Tel: 0511 - 168 - 47377 tagsüber besetzt, oder Tel: 0511 - 168 - 47333, 24 Std. besetzt. | E5: =VLOOKUP(A5,All!$C$2:$D$2424,2,FALSE) -> aha entsorgt in der Region Hannover die Inhalte von Benzin- und Ölabscheidern und von Sand- und Schlammfängen. Im Auftrag von aha führt die Stadtentwässerung Hannover die Reinigung von Abscheideranlagen regionsweit aus. Ansprechpartner bei der Stadtentwässerung Hannover sind Herr Münder und Herr Wagner, Tel: 0511 - 168 - 47440. Bei Abwesenheit nimmt ein Anrufbeantworter die Anfragen auf. Störungsmeldestelle der Stadtentwässerung, Tel: 0511 - 168 - 47377 tagsüber besetzt, oder Tel: 0511 - 168 - 47333, 24 Std. besetzt. | F5: =VLOOKUP(A5,All!$C$2:$F$2424,4,FALSE) -> Sonderabfall | G5: =VLOOKUP(A5,All!$C$2:$G$2424,5,FALSE) -> Der Zweckverband Abfallwirtschaft Region Hannover (aha) | H5: =IF(D5=E5,"ok","no") -> no | I5: =IF(B5=F5,"ok","no") -> ok | J5: =IF(C5=G5,"ok","no") -> ok
A6: Abtönfarbe | B6: Sonderabfall,Restabfall,Wertstoff | C6: Wertstoffhof,Deponie Hannover - Sonderabfallannahmestelle | D6: Binderfarben sind wasserlöslich und zählen nicht zu den gefährlichen Abfällen, verursachen uneingedickt allerding böse Flecken. Eingetrocknete oder eingedickte (mit Sand, Gips oder Sägespäne vermischte Binderfarbe) können dem Restabfall über die Restabfalltonne zugeführt werden.,Flüssige Binderfarben geben Sie bitte an den Wertstoffhöfen der Region Hannover oder der Deponie Hannover im Sonderabfallzwischenlager ab.,Sachstand 07.05.2024 | E6: =VLOOKUP(A6,All!$C$2:$D$2424,2,FALSE) -> #N/A | F6: =VLOOKUP(A6,All!$C$2:$F$2424,4,FALSE) -> #N/A | G6: =VLOOKUP(A6,All!$C$2:$G$2424,5,FALSE) -> #N/A | H6: =IF(D6=E6,"ok","no") -> #N/A | I6: =IF(B6=F6,"ok","no") -> #N/A | J6: =IF(C6=G6,"ok","no") -> #N/A
A7: Aceton | B7: Sonderabfall | C7: Wertstoffhof,Deponie Hannover - Sonderabfallannahmestelle | D7: Bis zu 30kg (Gesamtmenge/ haushaltsübliche Mengen) Ihrer gefährlichen Abfälle, können Sie täglich kostenlos auf allen Wertstoffhöfen abgeben. Auf den Wertstoffhöfen der Region werden Sonderabfälle in Gebinden bis zu einer Größe von max. 10 Litern entgegengenommen. Größere Mengen oder Gebinde können kostenpflichtig an der Sonderannahmestelle auf der Deponie Hannover Lahe abgeben. Gebinde über 10 Liter sind ebenfalls an der Deponie in Hannover anzuliefern.,Bitte beachten Sie die Mengenbegrenzung der einzelnen Abfälle, auf der Preisliste für Sonderabfall.,Bitte achten Sie bei dem Transport darauf, die Gebinde gut zu kennzeichnen und auf keinen Fall mit anderen Flüssigkeiten zu vermischen. Am sichersten transportieren Sie Sonderabfälle nur dicht verschlossen in den originalen Behältern (Gebinden) sowie aufrechtstehend (z.B. in einer Wanne, die Behälter aufrecht hält).,Wichtig: Nutzen Sie bitte die Abgabezeiten für Gewerbekunden (Mo. bis Do. von 7.00 – 14.00 Uhr und Fr. von 7.00 – 12.00 Uhr), wenn Sie größere Mengen an Sonderabfällen abgeben wollen.,Sachstand 19.07.2023 | E7: =VLOOKUP(A7,All!$C$2:$D$2424,2,FALSE) -> Bis zu 30 Kg (Gesamtmenge/ haushaltsübliche Mengen) Ihrer gefährlichen Abfälle täglich können Sie kostenlos auf den Wertstoffhöfen der Region Hannover oder der Deponie Hannover im Sonderabfallzwischenlager abgeben. Größere Mengen können Sie kostenpflichtig an der Sonderannahmestelle auf der Deponie Hannover abgeben. Bitte beachten Sie hierzu die Preisliste für Sonderabfall. Bitte achten Sie bei dem Transport darauf, die Gebinde gut zu kennzeichnen und auf keinen Fall mit anderen Flüssigkeiten zu vermischen. Am sichersten transportieren Sie Sonderabfälle nur dicht verschlossen in den originalen Behältern (Gebinden) sowie aufrecht stehend (z.B in einer Wanne, die Behälter aufrecht hält). | F7: =VLOOKUP(A7,All!$C$2:$F$2424,4,FALSE) -> Sonderabfall | G7: =VLOOKUP(A7,All!$C$2:$G$2424,5,FALSE) -> Wertstoffhof, Deponie | H7: =IF(D7=E7,"ok","no") -> no | I7: =IF(B7=F7,"ok","no") -> ok | J7: =IF(C7=G7,"ok","no") -> no
A8: Acryl/ Silikon | B8: Sonderabfall | C8: Wertstoffhof,Deponie Hannover - Sonderabfallannahmestelle | D8: Bis zu 30kg (Gesamtmenge/ haushaltsübliche Mengen) Ihrer gefährlichen Abfälle, können Sie täglich kostenlos auf allen Wertstoffhöfen abgeben. Auf den Wertstoffhöfen der Region werden Sonderabfälle in Gebinden bis zu einer Größe von max. 10 Litern entgegengenommen. Größere Mengen oder Gebinde können kostenpflichtig an der Sonderannahmestelle auf der Deponie Hannover Lahe abgeben. Gebinde über 10 Liter sind ebenfalls an der Deponie in Hannover anzuliefern.,Bitte beachten Sie die Mengenbegrenzung der einzelnen Abfälle, auf der Preisliste für Sonderabfall.,Bitte achten Sie bei dem Transport darauf, die Gebinde gut zu kennzeichnen und auf keinen Fall mit anderen Flüssigkeiten zu vermischen. Am sichersten transportieren Sie Sonderabfälle nur dicht verschlossen in den originalen Behältern (Gebinden) sowie aufrechtstehend (z.B. in einer Wanne, die Behälter aufrecht hält).,Wichtig: Nutzen Sie bitte die Abgabezeiten für Gewerbekunden (Mo. bis Do. von 7.00 – 14.00 Uhr und Fr. von 7.00 – 12.00 Uhr), wenn Sie größere Mengen an Sonderabfällen abgeben wollen.,Sachstand 22.04.2024 | E8: =VLOOKUP(A8,All!$C$2:$D$2424,2,FALSE) -> #N/A | F8: =VLOOKUP(A8,All!$C$2:$F$2424,4,FALSE) -> #N/A | G8: =VLOOKUP(A8,All!$C$2:$G$2424,5,FALSE) -> #N/A | H8: =IF(D8=E8,"ok","no") -> #N/A | I8: =IF(B8=F8,"ok","no") -> #N/A | J8: =IF(C8=G8,"ok","no") -> #N/A
A9: Adventskranz | D9: Adventskränze müssen für die Entsorgung auf dem Komposthaufen oder in der Bioabfalltonne auseinandergenommen werden (das heißt Drahtgeflechte, Kerzen/ Kerzenhalter und alle Dekoration müssen entfernt werden.) Ganze Adventskränze können über die Restabfalltonne entsorgt werden.,Sachstand: 08.10.2024 | E9: =VLOOKUP(A9,All!$C$2:$D$2424,2,FALSE) -> #N/A | F9: =VLOOKUP(A9,All!$C$2:$F$2424,4,FALSE) -> #N/A | G9: =VLOOKUP(A9,All!$C$2:$G$2424,5,FALSE) -> #N/A | H9: =IF(D9=E9,"ok","no") -> #N/A | I9: =IF(B9=F9,"ok","no") -> #N/A | J9: =IF(C9=G9,"ok","no") -> #N/A
A10: Akkus | B10: Sonderabfall | C10: Wertstoffhof,Deponie Hannover - Sonderabfallannahmestelle | D10: aha nimmt Gerätebatterien, z. B. aus Taschenlampen, Uhren, Radios usw. an. Bis zu 30 kg Ihrer gefährlichen Abfälle täglich können Sie kostenlos auf den Wertstoffhöfen der Region Hannover oder der Deponie Hannover im Sonderabfallzwischenlager abgeben.,Ausgediente Akkus von E-Bikes und E-Scootern gehören zu laut §8 Batteriegesetz zu den Industriebatterien. Industriebatterien werden von aha nicht angenommen. Bitte geben Sie diese an den Fachhandel zurück.,Die einzige Ausnahme von dieser Regel stellen Starterbatterien auf Bleibasis von LKWs und PKWs sowie Motorrädern dar. | E10: =VLOOKUP(A10,All!$C$2:$D$2424,2,FALSE) -> #N/A | F10: =VLOOKUP(A10,All!$C$2:$F$2424,4,FALSE) -> #N/A | G10: =VLOOKUP(A10,All!$C$2:$G$2424,5,FALSE) -> #N/A | H10: =IF(D10=E10,"ok","no") -> #N/A | I10: =IF(B10=F10,"ok","no") -> #N/A | J10: =IF(C10=G10,"ok","no") -> #N/A
A11: Aktenordner | B11: Restabfall | C11: Restabfalltonne | D11: Alte Akten können (soweit es der Datenschutz es erfordert) durch spezielle Aktenvernichtungsfirmen entsorgt bzw. der Verwertung zugeführt werden. Aktendeckel aus Papier/Karton (unbeschichtet) gehören nur ohne Metallinlett in die Papiersammlung.,Komplette Ordner ohne Inhalt gehören in den Restabfallbehälter.,Sachstand:10.05.2024 | E11: =VLOOKUP(A11,All!$C$2:$D$2424,2,FALSE) -> #N/A | F11: =VLOOKUP(A11,All!$C$2:$F$2424,4,FALSE) -> #N/A | G11: =VLOOKUP(A11,All!$C$2:$G$2424,5,FALSE) -> #N/A | H11: =IF(D11=E11,"ok","no") -> #N/A | I11: =IF(B11=F11,"ok","no") -> #N/A | J11: =IF(C11=G11,"ok","no") -> #N/A
A12: Akustikpaneele | C12: Wertstoffhof,Deponie | D12: Bis zu 1m³ an Akustikpaneelen, die zur Schalldämmung verwendet werden, können kostenfrei auf den Wertstoffhöfen und Deponien über den Sperrabfallcontainer entsorgt werden. Größere Mengen werden kostenpflichtig auf den drei Regionsdeponien entgegengenommen.,5 m³ an Akustikpaneelen können Sie ebenfalls als Sperrabfall kostenlos direkt vor Ihrer Haustür abholen lassen. Dabei sollten die Gegenstände eine Länge von 2 m und ein Gewicht von max. 75 kg nicht überschreiten. Bitte vereinbaren Sie herfür einen Termin - online oder telefonisch.,Akustikplatten hingegen können leider weder auf den Deponien noch den Wertstoffhöfen entgegengenommen werden, da diese HBCD belastet sind. Ohne eine entsprechende Analyse kann allerdings nicht festgestellt werden, ob das Material belastet ist oder nicht.,Sachstand: 07.05.2024 | E12: =VLOOKUP(A12,All!$C$2:$D$2424,2,FALSE) -> #N/A | F12: =VLOOKUP(A12,All!$C$2:$F$2424,4,FALSE) -> #N/A | G12: =VLOOKUP(A12,All!$C$2:$G$2424,5,FALSE) -> #N/A | H12: =IF(D12=E12,"ok","no") -> #N/A | I12: =IF(B12=F12,"ok","no") -> #N/A | J12: =IF(C12=G12,"ok","no") -> #N/A
A13: Akustikplatten | D13: Akustikplatten werden weder auf den Deponien der Region noch auf den Wertstoffhöfen entgegengenommen, da diese oft HBCD belastet sind und diese Belastung ohne entsprechende Analyse nicht zu erkennen ist.,Bitte wenden Sie sich für die Entsorgung dieser an eine externe Firma aus dem Branchenbuch/-verzeichnis oder dem Internet.,Sachstand: 07.05.2024 | E13: =VLOOKUP(A13,All!$C$2:$D$2424,2,FALSE) -> #N/A | F13: =VLOOKUP(A13,All!$C$2:$F$2424,4,FALSE) -> #N/A | G13: =VLOOKUP(A13,All!$C$2:$G$2424,5,FALSE) -> #N/A | H13: =IF(D13=E13,"ok","no") -> #N/A | I13: =IF(B13=F13,"ok","no") -> #N/A | J13: =IF(C13=G13,"ok","no") -> #N/A
A14: Alleskleber | B14: Sonderabfall | C14: Wertstoffhof,Deponie Hannover - Sonderabfallannahmestelle | D14: Klebstoffe gehören zu den gefährlichen Abfällen (Sonderabfall). Bis zu 30 Kg (Gesamtmenge/ haushaltsübliche Mengen) Ihrer gefährlichen Abfälle täglich können Sie kostenlos auf den Wertstoffhöfen der Region Hannover oder der Deponie Hannover im Sonderabfallzwischenlager abgeben. Größere Mengen können Sie kostenpflichtig an der Sonderannahmestelle auf der Deponie Hannover abgeben. Bitte beachten Sie hierzu die Preisliste für Sonderabfall.,Bitte achten Sie bei dem Transport darauf, die Gebinde gut zu kennzeichnen und auf keinen Fall mit anderen Flüssigkeiten zu vermischen. Am sichersten transportieren Sie Sonderabfälle nur dicht verschlossen in den originalen Behältern (Gebinden) sowie aufrecht stehend (z.B in einer Wanne, die Behälter aufrecht hält).,Natürliche Klebstoffe, die aus pflanzlichen oder tierischen Produkten hergestellt werden, können über den Restabfall entsorgt werden. | E14: =VLOOKUP(A14,All!$C$2:$D$2424,2,FALSE) -> Klebstoffe gehören zu den gefährlichen Abfällen (Sonderabfall). Bis zu 30 Kg (Gesamtmenge/ haushaltsübliche Mengen) Ihrer gefährlichen Abfälle täglich können Sie kostenlos auf den Wertstoffhöfen der Region Hannover oder der Deponie Hannover im Sonderabfallzwischenlager abgeben. Größere Mengen können Sie kostenpflichtig an der Sonderannahmestelle auf der Deponie Hannover abgeben. Bitte beachten Sie hierzu die Preisliste für Sonderabfall. Bitte achten Sie bei dem Transport darauf, die Gebinde gut zu kennzeichnen und auf keinen Fall mit anderen Flüssigkeiten zu vermischen. Am sichersten transportieren Sie Sonderabfälle nur dicht verschlossen in den originalen Behältern (Gebinden) sowie aufrecht stehend (z.B in einer Wanne, die Behälter aufrecht hält). Natürliche Klebstoffe, die aus pflanzlichen oder tierischen Produkten hergestellt werden, können über den Restabfall entsorgt werden. | F14: =VLOOKUP(A14,All!$C$2:$F$2424,4,FALSE) -> Sonderabfall | G14: =VLOOKUP(A14,All!$C$2:$G$2424,5,FALSE) -> Wertstoffhof, Deponie | H14: =IF(D14=E14,"ok","no") -> no | I14: =IF(B14=F14,"ok","no") -> ok | J14: =IF(C14=G14,"ok","no") -> no
A15: Allzweckreiniger | B15: Sonderabfall | C15: Wertstoffhof,Deponie Hannover - Sonderabfallannahmestelle | D15: Bis zu 30kg (Gesamtmenge/ haushaltsübliche Mengen) Ihrer gefährlichen Abfälle, können Sie täglich kostenlos auf allen Wertstoffhöfen abgeben. Auf den Wertstoffhöfen der Region werden Sonderabfälle in Gebinden bis zu einer Größe von max. 10 Litern entgegengenommen. Größere Mengen oder Gebinde können kostenpflichtig an der Sonderannahmestelle auf der Deponie Hannover Lahe abgeben. Gebinde über 10 Liter sind ebenfalls an der Deponie in Hannover anzuliefern.,Bitte beachten Sie die Mengenbegrenzung der einzelnen Abfälle, auf der Preisliste für Sonderabfall.,Bitte achten Sie bei dem Transport darauf, die Gebinde gut zu kennzeichnen und auf keinen Fall mit anderen Flüssigkeiten zu vermischen. Am sichersten transportieren Sie Sonderabfälle nur dicht verschlossen in den originalen Behältern (Gebinden) sowie aufrechtstehend (z.B. in einer Wanne, die Behälter aufrecht hält).,Wichtig: Nutzen Sie bitte die Abgabezeiten für Gewerbekunden (Mo. bis Do. von 7.00 – 14.00 Uhr und Fr. von 7.00 – 12.00 Uhr), wenn Sie größere Mengen an Sonderabfällen abgeben wollen.,Sachstand 19.07.2023 | E15: =VLOOKUP(A15,All!$C$2:$D$2424,2,FALSE) -> Bis zu 30 Kg (Gesamtmenge/ haushaltsübliche Mengen) Ihrer gefährlichen Abfälle täglich können Sie kostenlos auf den Wertstoffhöfen der Region Hannover oder der Deponie Hannover im Sonderabfallzwischenlager abgeben. Größere Mengen können Sie kostenpflichtig an der Sonderannahmestelle auf der Deponie Hannover abgeben. Bitte beachten Sie hierzu die Preisliste für Sonderabfall. Bitte achten Sie bei dem Transport darauf, die Gebinde gut zu kennzeichnen und auf keinen Fall mit anderen Flüssigkeiten zu vermischen. Am sichersten transportieren Sie Sonderabfälle nur dicht verschlossen in den originalen Behältern (Gebinden) sowie aufrecht stehend (z.B in einer Wanne, die Behälter aufrecht hält). | F15: =VLOOKUP(A15,All!$C$2:$F$2424,4,FALSE) -> Sonderabfall | G15: =VLOOKUP(A15,All!$C$2:$G$2424,5,FALSE) -> Wertstoffhof, Deponie | H15: =IF(D15=E15,"ok","no") -> no | I15: =IF(B15=F15,"ok","no") -> ok | J15: =IF(C15=G15,"ok","no") -> no
A16: Altakten | D16: Alte Akten können (soweit es der Datenschutz erfordert) durch spezielle Aktenvernichtungsfirmen entsorgt bzw. verwertet werden. Aktendeckel aus Papier/Karton gehören - wenn sie unbeschichtet sind und das Metallinlett entfernt wurden - in die Papiersammlung.,Komplette Ordner können über den Restabfallbehälter entsorgt werden. | E16: =VLOOKUP(A16,All!$C$2:$D$2424,2,FALSE) -> #N/A | F16: =VLOOKUP(A16,All!$C$2:$F$2424,4,FALSE) -> #N/A | G16: =VLOOKUP(A16,All!$C$2:$G$2424,5,FALSE) -> #N/A | H16: =IF(D16=E16,"ok","no") -> #N/A | I16: =IF(B16=F16,"ok","no") -> #N/A | J16: =IF(C16=G16,"ok","no") -> #N/A
A17: Altauto | B17: Altfahrzeug | C17: Altfahrzeugverwertung | D17: Altfahrzeuge, Fahrzeugwracks, und Fahrzeugteile werden von zertifizierten Verwertungsbetrieben angenommen und einer Verwertung zugeführt (siehe www.gelbeseiten.de). Sie werden nicht an den Wertstoffhöfen von aha angenommen; auch bei der Sperrabfallsammlung werden sie nicht mitgenommen.,In zertifizierten Verwertungsbetrieben wird Ihnen ein Verwertungsnachweis für Ihr Altfahrzeug ausgehändigt; verlangen Sie diesen unbedingt!, In den Fachbetrieben werden aus diesen Fahrzeugen die Betriebsflüssigkeiten entfernt und einer fachgerechten Aufbereitung (z.B. Öle aller Art) oder Entsorgung zugeführt. Zusätzlich werden aus den Fahrzeugen die weiter einsetzbaren Ersatzteile demontiert und dem Markt zur weiteren Nutzung als kostengünstige Ersatzteile erhalten. Kabel, Metalle u.a. werden der Wiederverwertung zugeführt. Der nicht mehr nutzbare Rest des Fahrzeuges wird ordnungsgemäß entsorgt.,Über ,können Sie Fahrzeuge ohne Zulassung oder Fahrzeugwracks, die im öffentlichen Straßenraum stehen, melden.,Im Umland wenden Sie sich bitte an die entsprechende Stadt- oder Gemeindeverwaltung, bzw. an die Region Hannover.,Sachstand: 08.05.2024 | E17: =VLOOKUP(A17,All!$C$2:$D$2424,2,FALSE) -> Altfahrzeuge, Fahrzeugwracks, und Autoteile werden von zertifizierten Verwertungsbetrieben angenommen und einer Verwertung zugeführt (siehe ,). Sie werden nicht an den Wertstoffhöfen von aha angenommen; auch bei der Sperrabfallsammlung werden sie nicht mitgenommen. In zertifizierten Verwertungsbetrieben wird Ihnen ein Verwertungsnachweis für Ihr Altfahrzeug ausgehändigt; verlangen Sie diesen unbedingt!, In den Fachbetrieben werden aus diesen Fahrzeuge die Betriebsflüssigkeiten entfernt und einer fachgerechten Aufbereitung (z.B. Öle aller Art) oder Entsorgung zugeführt. Zusätzlich werden aus den Fahrzeugen die weiter einsetzbaren Ersatzteile demontiert und dem Markt zur weiteren Nutzung als kostengünstige Ersatzteile erhalten. Kabel, Metalle u.a. werden der Wiederverwertung zugeführt. Der nicht mehr nutzbare Rest des Fahrzeuges wird ordnungsgemäß entsorgt. Im Umland wenden Sie sich bitte an die entsprechende Stadt- oder Gemeindeverwaltung, bzw. an die Region Hannover. | F17: =VLOOKUP(A17,All!$C$2:$F$2424,4,FALSE) -> Altfahrzeug | G17: =VLOOKUP(A17,All!$C$2:$G$2424,5,FALSE) -> Altfahrzeugverwertung | H17: =IF(D17=E17,"ok","no") -> no | I17: =IF(B17=F17,"ok","no") -> ok | J17: =IF(C17=G17,"ok","no") -> ok
A18: Altfette/Speisefette/Fette | B18: Restabfall | C18: Restabfalltonne | D18: Erkaltete Fette/Öle sind als Restabfall zu entsorgen. Auch in kleinen Mengen gehören Fette und Öle nicht in den Abfluss. Größere Mengen, z. B. aus der Gastronomie, müssen über spezielle Entsorgungsunternehmen entsorgt werden oder wenden Sie sich an unseren Gewerbekundenservice., | E18: =VLOOKUP(A18,All!$C$2:$D$2424,2,FALSE) -> #N/A | F18: =VLOOKUP(A18,All!$C$2:$F$2424,4,FALSE) -> #N/A | G18: =VLOOKUP(A18,All!$C$2:$G$2424,5,FALSE) -> #N/A | H18: =IF(D18=E18,"ok","no") -> #N/A | I18: =IF(B18=F18,"ok","no") -> #N/A | J18: =IF(C18=G18,"ok","no") -> #N/A
A19: Altholz | C19: Wertstoffhof | D19: d.h. Holzabfälle ohne Störstoffe (keine Metalle, Kunststoffe, Glas), keine Holzabfälle mit schädlichen Verunreinigungen,und,z.B. Bahnschwellen, Leitungsmasten, Jägerzäune, Fenster, Außentüren und sonstige Hölzer aus dem Außenbereich (Annahme nur auf der Depoie Hannover in Lahe),Bis zu 1 m³ (Gesamtmenge/ haushaltsübliche Mengen) Ihrer Holzabfälle können Sie täglich kostenlos auf den Wertstoffhöfen der Region Hannover abgeben. Größere Mengen können Sie kostenpflichtig an den Deponien der Region Hannover abgeben. Bitte beachten Sie hierzu die Preisliste für die Deponieanlieferung. Die Annahmebedingungen unserer Deponien und Wertstoffhöfe finden Sie hier (,) und hier (,).,Verdreckte Holzabfälle aus Hühnerställen, Hühner-/ oder Taubenverschlägen werden auf Grund ihrer Verschmutzung durch Tierfäkalien weder auf den Wertstoffhöfen noch auf den drei Regionsdeponien angenommen. Bitte wenden Sie sich für die Entsorgung solcher Materialien an eine Fachfirma.,Sachstand: 13.03.2024, | E19: =VLOOKUP(A19,All!$C$2:$D$2424,2,FALSE) -> #N/A | F19: =VLOOKUP(A19,All!$C$2:$F$2424,4,FALSE) -> #N/A | G19: =VLOOKUP(A19,All!$C$2:$G$2424,5,FALSE) -> #N/A | H19: =IF(D19=E19,"ok","no") -> #N/A | I19: =IF(B19=F19,"ok","no") -> #N/A | J19: =IF(C19=G19,"ok","no") -> #N/A
A20: Altholz, gefährlicher Abfall | B20: Holzabfall, Sonderabfall | C20: Deponie Hannover Lahe | D20: Hölzer wie z. B. Bahnschwellen, Jägerzäune, Pfähle, Masten sind durch umwelt- und gesundheitsschädigende Holzschutzmittel belastet., , Aus Privathaushalten erfolgt die Annahme an der Deponie Hannover in Lahe bis zur Menge von 1 m³ kostenlos, größere Mengen nur gegen Gebühr., , Das kontaminierte Altholz wird in einem separaten Behälter gesammelt und einer gesonderten Entsorgung zugeführt., , , Kontaminiertes Altholz aus Gewerbebetrieben wird an der Deponie Hannover gebührenpflichtig in einem separaten Behälter angenommen. | E20: =VLOOKUP(A20,All!$C$2:$D$2424,2,FALSE) -> Hölzer wie z. B. Bahnschwellen, Jägerzäune, Pfähle, Masten sind durch umwelt- und gesundheitsschädigende Holzschutzmittel belastet. Aus Privathaushalten erfolgt die Annahme an der Deponie Hannover in Lahe bis zur Menge von 1 m³ kostenlos, größere Mengen nur gegen Gebühr. Das kontaminierte Altholz wird in einem separaten Behälter gesammelt und einer gesonderten Entsorgung zugeführt. Kontaminiertes Altholz aus Gewerbebetrieben wird an der Deponie Hannover gebührenpflichtig in einem separaten Behälter angenommen. | F20: =VLOOKUP(A20,All!$C$2:$F$2424,4,FALSE) -> Holzabfall, Sonderabfall | G20: =VLOOKUP(A20,All!$C$2:$G$2424,5,FALSE) -> Deponie | H20: =IF(D20=E20,"ok","no") -> no | I20: =IF(B20=F20,"ok","no") -> ok | J20: =IF(C20=G20,"ok","no") -> no
A21: Altholz, ungefährlicher Abfall | B21: Sperrabfall | C21: Wertstoffhof,Sperrabfallabholung | D21: Ungefährliche Abfallhölzer sind unbehandelte Hölzer, beispielsweise Voll- und Massivhölzer, Möbel, Dielen, Spanplatten, Türen aus dem Innenbereich und Holzverpackungen., Altholz wird in Kleinmengen aus Privathaushalten auf den Wertstoffhöfen angenommen (bis 1 m³ pro Tag). Größere Mengen und gewerbliche Abfälle sind kostenpflichtig an den Deponien anzuliefern., Bis zur Menge von 5 m³ holt aha auch kostenlos (größer 5 m³ gegen Gebühr) vor Ihrem Grundstück ab. Melden Sie Ihren Sperrmüll einfach , an oder vereinbaren Sie telefonisch einen Termin beim aha-Service, Tel.: 0800 - 999 11 99. | E21: =VLOOKUP(A21,All!$C$2:$D$2424,2,FALSE) -> Ungefährliche Abfallhölzer sind unbehandelte Hölzer, beispielsweise Voll- und Massivhölzer, Möbel, Dielen, Spanplatten, Türen aus dem Innenbereich und Holzverpackungen. Altholz wird in Kleinmengen aus Privathaushalten auf den Wertstoffhöfen angenommen (bis 1 m³ pro Tag). Größere Mengen und gewerbliche Abfälle sind kostenpflichtig an den Deponien anzuliefern. Bis zur Menge von 5 m³ holt aha auch kostenlos (größer 5 m³ gegen Gebühr) vor Ihrem Grundstück ab. Melden Sie Ihren Sperrmüll einfach , an oder vereinbaren Sie telefonisch einen Termin beim aha-Service, Tel.: 0800 - 999 11 99. | F21: =VLOOKUP(A21,All!$C$2:$F$2424,4,FALSE) -> Sperrabfall | G21: =VLOOKUP(A21,All!$C$2:$G$2424,5,FALSE) -> Wertstoffhof, Sperrabfallabholung | H21: =IF(D21=E21,"ok","no") -> no | I21: =IF(B21=F21,"ok","no") -> ok | J21: =IF(C21=G21,"ok","no") -> no
A22: Altkleider | B22: Alttextilien | C22: Wertstoffhof,Wertstoffinsel | D22: Zur Entsorgung Ihrer Textilien und Schuhe ( Kleidungsstücke wie Hosen, Blusen und Mäntel, Bettwäsche, Federbetten usw.) finden Sie Sammelcontainer an allen Wertstoffhöfen, den Deponien, auf öffentlichen Plätzen (Wertstoffinseln) sowie bei vielen Supermärkten., , ,Sachstand:15.05.2024, | E22: =VLOOKUP(A22,All!$C$2:$D$2424,2,FALSE) -> Zur Entsorgung Ihrer Textilien und Schuhe ( Kleidungsstücke wie Hosen, Blusen und Mäntel, Bettwäsche, Federbetten usw.) finden Sie Sammelcontainer an allen Wertstoffhöfen, den Deponien, auf öffentlichen Plätzen (Wertstoffinseln) sowie bei vielen Supermärkten. | F22: =VLOOKUP(A22,All!$C$2:$F$2424,4,FALSE) -> Alttextilien | G22: =VLOOKUP(A22,All!$C$2:$G$2424,5,FALSE) -> Wertstoffhof, Wertstoffinsel | H22: =IF(D22=E22,"ok","no") -> no | I22: =IF(B22=F22,"ok","no") -> ok | J22: =IF(C22=G22,"ok","no") -> no
A23: Altöl | B23: Sonderabfall | C23: Deponie Hannover - Sonderabfallannahmestelle | D23: Altöle gehören zur Gruppe der Sonderabfälle (gefährlicher Abfall). Bei Altölen besteht eine gesetzliche Rücknahmepflicht für den Handel. Die Entsorgung von den Altölen hat aus diesem Grund über den Handel zu erfolgen. Wichtig hierfür ist die Vorlage eines Kaufbeleges. Auf Grund dessen kann eine entsprechende Menge Altöl zurückgegeben werden.,Sollte der Kaufbeleg nicht mehr vorliegen, so kann in Ausnahmefällen eine Entsorgung von 30 kg (haushaltsübliche Menge/Gesamtmenge) über die Sonderabfallannahme auf der Deponie Hannover erfolgen. Altöle werden nicht auf den Wertstoffhöfen angenommen. | E23: =VLOOKUP(A23,All!$C$2:$D$2424,2,FALSE) -> Altöle gehören zur Gruppe der Sonderabfälle (gefährlicher Abfall). Bei Altölen besteht eine gesetzliche Rücknahmepflicht für den Handel. Die Entsorgung von den Altölen hat aus diesem Grund über den Handel zu erfolgen. Wichtig hierfür ist die Vorlage eines Kaufbeleges. Auf Grund dessen kann eine entsprechende Menge Altöl zurückgegeben werden. Sollte der Kaufbeleg nicht mehr vorliegen, so kann in Ausnahmefällen eine Entsorgung von 30 kg (haushaltsübliche Menge/Gesamtmenge) über die Sonderabfallannahme auf der Deponie Hannover erfolgen. Altöle werden nicht auf den Wertstoffhöfen angenommen. | F23: =VLOOKUP(A23,All!$C$2:$F$2424,4,FALSE) -> Sonderabfall | G23: =VLOOKUP(A23,All!$C$2:$G$2424,5,FALSE) -> Deponie | H23: =IF(D23=E23,"ok","no") -> no | I23: =IF(B23=F23,"ok","no") -> ok | J23: =IF(C23=G23,"ok","no") -> no
A24: Alufolie | D24: Da es sich bei der Alufolie nicht um eine lizenzierten Verkaufsverpackung hadelt, gehört Alufolie über den Restabfall entsorgt.,Joghurtdeckel und Sahnebecherdeckel sowie Aluschalen von z.B. Teelichter können über die Wertstofftonne entsorgt werden.,Sachstand: 08.10.2024 | E24: =VLOOKUP(A24,All!$C$2:$D$2424,2,FALSE) -> #N/A | F24: =VLOOKUP(A24,All!$C$2:$F$2424,4,FALSE) -> #N/A | G24: =VLOOKUP(A24,All!$C$2:$G$2424,5,FALSE) -> #N/A | H24: =IF(D24=E24,"ok","no") -> #N/A | I24: =IF(B24=F24,"ok","no") -> #N/A | J24: =IF(C24=G24,"ok","no") -> #N/A
A25: Aluminium | B25: Altmetall | C25: Wertstoffhof,Gelbe Tonne | D25: Aluminiumdeckel von Joghurt- und Sahnebechern oder auch die Aluschalen der Teelichter können gesammelt und über die Wertstoffsammlung in der Wertstofftonne verwertet werden. Größere Aluminiumteile können beim Schrotthandel oder kostenfrei bei den Wertstoffhöfen abgegeben werden.,Sachstand:10.05.2024 | E25: =VLOOKUP(A25,All!$C$2:$D$2424,2,FALSE) -> 0 | F25: =VLOOKUP(A25,All!$C$2:$F$2424,4,FALSE) -> Altmetall | G25: =VLOOKUP(A25,All!$C$2:$G$2424,5,FALSE) -> Wertstoffhof | H25: =IF(D25=E25,"ok","no") -> no | I25: =IF(B25=F25,"ok","no") -> ok | J25: =IF(C25=G25,"ok","no") -> no
A26: Ambrosia | B26: giftigen oder invasiven Pflanzen | C26: Wertstoffhof,Deponie | D26: Bitte verpacken Sie die giftigen Pflanzen gut und gesondert von anderen Materialien.,Bis zu 1 m³ (Gesamtmenge/ haushaltsübliche Mengen) Ihrer giftigen oder invasiven Pflanzen täglich können Sie kostenlos auf den Wertstoffhöfen der Region Hannover (im Sperrabfall) abgeben. Größere Mengen können Sie kostenpflichtig an den Deponien der Region Hannover abgeben. Bitte beachten Sie hierzu die Preisliste für die Deponieanlieferung unter folgendem Link: , finden Sie die Annahmebedingungen unserer Wertstoffhofe, , die der Deponien. | E26: =VLOOKUP(A26,All!$C$2:$D$2424,2,FALSE) -> Bitte verpacken Sie die giftigen Pflanzen gut und gesondert von anderen Materialien. Bis zu 1 m³ (Gesamtmenge/ haushaltsübliche Mengen) Ihrer giftigen oder invasiven Pflanzen täglich können Sie kostenlos auf den Wertstoffhöfen der Region Hannover (im Sperrabfall) abgeben. Größere Mengen können Sie kostenpflichtig an den Deponien der Region Hannover abgeben. Bitte beachten Sie hierzu die Preisliste für die Deponieanlieferung. finden Sie die Annahmebedingungen unserer Wertstoffhofe, die der Deponien. | F26: =VLOOKUP(A26,All!$C$2:$F$2424,4,FALSE) -> giftigen oder invasiven Pflanzen | G26: =VLOOKUP(A26,All!$C$2:$G$2424,5,FALSE) -> Wertstoffhof, Deponie | H26: =IF(D26=E26,"ok","no") -> no | I26: =IF(B26=F26,"ok","no") -> ok | J26: =IF(C26=G26,"ok","no") -> no
A27: Ameisengift | B27: Sonderabfall | C27: Wertstoffhof,Deponie Hannover - Sonderabfallannahmestelle | D27: Bis zu 30kg (Gesamtmenge/ haushaltsübliche Mengen) Ihrer gefährlichen Abfälle, können Sie täglich kostenlos auf allen Wertstoffhöfen abgeben. Auf den Wertstoffhöfen der Region werden Sonderabfälle in Gebinden bis zu einer Größe von max. 10 Litern entgegengenommen. Größere Mengen oder Gebinde können kostenpflichtig an der Sonderannahmestelle auf der Deponie Hannover Lahe abgeben. Gebinde über 10 Liter sind ebenfalls an der Deponie in Hannover anzuliefern.,Bitte beachten Sie die Mengenbegrenzung der einzelnen Abfälle, auf der Preisliste für Sonderabfall.,Bitte achten Sie bei dem Transport darauf, die Gebinde gut zu kennzeichnen und auf keinen Fall mit anderen Flüssigkeiten zu vermischen. Am sichersten transportieren Sie Sonderabfälle nur dicht verschlossen in den originalen Behältern (Gebinden) sowie aufrechtstehend (z.B. in einer Wanne, die Behälter aufrecht hält).,Wichtig: Nutzen Sie bitte die Abgabezeiten für Gewerbekunden (Mo. bis Do. von 7.00 – 14.00 Uhr und Fr. von 7.00 – 12.00 Uhr), wenn Sie größere Mengen an Sonderabfällen abgeben wollen.,Sachstand 19.07.2023 | E27: =VLOOKUP(A27,All!$C$2:$D$2424,2,FALSE) -> Bis zu 30 Kg (Gesamtmenge/ haushaltsübliche Mengen) Ihrer gefährlichen Abfälle täglich können Sie kostenlos auf den Wertstoffhöfen der Region Hannover oder der Deponie Hannover im Sonderabfallzwischenlager abgeben. Größere Mengen können Sie kostenpflichtig an der Sonderannahmestelle auf der Deponie Hannover abgeben. Bitte beachten Sie hierzu die Preisliste für Sonderabfall. Bitte achten Sie bei dem Transport darauf, die Gebinde gut zu kennzeichnen und auf keinen Fall mit anderen Flüssigkeiten zu vermischen. Am sichersten transportieren Sie Sonderabfälle nur dicht verschlossen in den originalen Behältern (Gebinden) sowie aufrecht stehend (z.B in einer Wanne, die Behälter aufrecht hält). | F27: =VLOOKUP(A27,All!$C$2:$F$2424,4,FALSE) -> Sonderabfall | G27: =VLOOKUP(A27,All!$C$2:$G$2424,5,FALSE) -> Wertstoffhof, Deponie | H27: =IF(D27=E27,"ok","no") -> no | I27: =IF(B27=F27,"ok","no") -> ok | J27: =IF(C27=G27,"ok","no") -> no
A28: Ammoniak | B28: Sonderabfall | C28: Wertstoffhof,Deponie Hannover - Sonderabfallannahmestelle | D28: Bis zu 30kg (Gesamtmenge/ haushaltsübliche Mengen) Ihrer gefährlichen Abfälle, können Sie täglich kostenlos auf allen Wertstoffhöfen abgeben. Auf den Wertstoffhöfen der Region werden Sonderabfälle in Gebinden bis zu einer Größe von max. 10 Litern entgegengenommen. Größere Mengen oder Gebinde können kostenpflichtig an der Sonderannahmestelle auf der Deponie Hannover Lahe abgeben. Gebinde über 10 Liter sind ebenfalls an der Deponie in Hannover anzuliefern.,Bitte beachten Sie die Mengenbegrenzung der einzelnen Abfälle, auf der Preisliste für Sonderabfall.,Bitte achten Sie bei dem Transport darauf, die Gebinde gut zu kennzeichnen und auf keinen Fall mit anderen Flüssigkeiten zu vermischen. Am sichersten transportieren Sie Sonderabfälle nur dicht verschlossen in den originalen Behältern (Gebinden) sowie aufrechtstehend (z.B. in einer Wanne, die Behälter aufrecht hält).,Wichtig: Nutzen Sie bitte die Abgabezeiten für Gewerbekunden (Mo. bis Do. von 7.00 – 14.00 Uhr und Fr. von 7.00 – 12.00 Uhr), wenn Sie größere Mengen an Sonderabfällen abgeben wollen.,Sachstand 19.07.2023 | E28: =VLOOKUP(A28,All!$C$2:$D$2424,2,FALSE) -> Bis zu 30 Kg (Gesamtmenge/ haushaltsübliche Mengen) Ihrer gefährlichen Abfälle täglich können Sie kostenlos auf den Wertstoffhöfen der Region Hannover oder der Deponie Hannover im Sonderabfallzwischenlager abgeben. Größere Mengen können Sie kostenpflichtig an der Sonderannahmestelle auf der Deponie Hannover abgeben. Bitte beachten Sie hierzu die Preisliste für Sonderabfall. Bitte achten Sie bei dem Transport darauf, die Gebinde gut zu kennzeichnen und auf keinen Fall mit anderen Flüssigkeiten zu vermischen. Am sichersten transportieren Sie Sonderabfälle nur dicht verschlossen in den originalen Behältern (Gebinden) sowie aufrecht stehend (z.B in einer Wanne, die Behälter aufrecht hält). | F28: =VLOOKUP(A28,All!$C$2:$F$2424,4,FALSE) -> Sonderabfall | G28: =VLOOKUP(A28,All!$C$2:$G$2424,5,FALSE) -> Wertstoffhof, Deponie | H28: =IF(D28=E28,"ok","no") -> no | I28: =IF(B28=F28,"ok","no") -> ok | J28: =IF(C28=G28,"ok","no") -> no
A29: Angel | C29: Wertstoffhof,Restabfalltonne,Sperrabfallabholung | D29: Angeln aus Fieberglas können kostenfrei auf den Wertstoffhöfen der Region Hannover über den Sperrabfallcontainer entsorgt werden. Bitte entsorgen Sie Zubehörteile wie Rollen oder ähnliches über den Metallcontainer.,Angeln, die sich zusammenschieben lassen, könnten über die Restabfalltonne entsorgt werden.,Sachstand: 10.05.2024 | E29: =VLOOKUP(A29,All!$C$2:$D$2424,2,FALSE) -> #N/A | F29: =VLOOKUP(A29,All!$C$2:$F$2424,4,FALSE) -> #N/A | G29: =VLOOKUP(A29,All!$C$2:$G$2424,5,FALSE) -> #N/A | H29: =IF(D29=E29,"ok","no") -> #N/A | I29: =IF(B29=F29,"ok","no") -> #N/A | J29: =IF(C29=G29,"ok","no") -> #N/A
A30: Anstreichfarbe | B30: Sonderabfall | C30: Wertstoffhof,Deponie Hannover - Sonderabfallannahmestelle | D30: Bis zu 30kg (Gesamtmenge/ haushaltsübliche Mengen) Ihrer gefährlichen Abfälle, können Sie täglich kostenlos auf allen Wertstoffhöfen abgeben. Auf den Wertstoffhöfen der Region werden Sonderabfälle in Gebinden bis zu einer Größe von max. 10 Litern entgegengenommen. Größere Mengen oder Gebinde können kostenpflichtig an der Sonderannahmestelle auf der Deponie Hannover Lahe abgeben. Gebinde über 10 Liter sind ebenfalls an der Deponie in Hannover anzuliefern.,Bitte beachten Sie die Mengenbegrenzung der einzelnen Abfälle, auf der Preisliste für Sonderabfall.,Bitte achten Sie bei dem Transport darauf, die Gebinde gut zu kennzeichnen und auf keinen Fall mit anderen Flüssigkeiten zu vermischen. Am sichersten transportieren Sie Sonderabfälle nur dicht verschlossen in den originalen Behältern (Gebinden) sowie aufrechtstehend (z.B. in einer Wanne, die Behälter aufrecht hält).,Wichtig: Nutzen Sie bitte die Abgabezeiten für Gewerbekunden (Mo. bis Do. von 7.00 – 14.00 Uhr und Fr. von 7.00 – 12.00 Uhr), wenn Sie größere Mengen an Sonderabfällen abgeben wollen.,Sachstand 19.07.2023 | E30: =VLOOKUP(A30,All!$C$2:$D$2424,2,FALSE) -> Bis zu 30 Kg (Gesamtmenge/ haushaltsübliche Mengen) Ihrer gefährlichen Abfälle täglich können Sie kostenlos auf den Wertstoffhöfen der Region Hannover oder der Deponie Hannover im Sonderabfallzwischenlager abgeben. Größere Mengen können Sie kostenpflichtig an der Sonderannahmestelle auf der Deponie Hannover abgeben. Bitte beachten Sie hierzu die Preisliste für Sonderabfall. Bitte achten Sie bei dem Transport darauf, die Gebinde gut zu kennzeichnen und auf keinen Fall mit anderen Flüssigkeiten zu vermischen. Am sichersten transportieren Sie Sonderabfälle nur dicht verschlossen in den originalen Behältern (Gebinden) sowie aufrecht stehend (z.B in einer Wanne, die Behälter aufrecht hält). | F30: =VLOOKUP(A30,All!$C$2:$F$2424,4,FALSE) -> Sonderabfall | G30: =VLOOKUP(A30,All!$C$2:$G$2424,5,FALSE) -> Wertstoffhof, Deponie | H30: =IF(D30=E30,"ok","no") -> no | I30: =IF(B30=F30,"ok","no") -> ok | J30: =IF(C30=G30,"ok","no") -> no
A31: Aquarium (leer) | B31: Wertstoff,Sperrabfall | C31: Wertstoffhof,Deponie | D31: Leere Aquarien können auf den Wertstoffhöfen und Deponien kostenfrei über die Sperrabfallcontainer entsorgt werden. Bitte erkundigen Sie sich vor der Entsorgung bei dem jeweilig zuständigen Personal in welchen Container das Aquarium entsorgt werden darf, da sonst eine zu hohe Verletzungsgefahr besteht. Wichtig: Leere Aquarien werden nicht bei der kostenfreien Sperrabfuhr mitgenommen.,Sachstand: 10.05.2024 | E31: =VLOOKUP(A31,All!$C$2:$D$2424,2,FALSE) -> #N/A | F31: =VLOOKUP(A31,All!$C$2:$F$2424,4,FALSE) -> #N/A | G31: =VLOOKUP(A31,All!$C$2:$G$2424,5,FALSE) -> #N/A | H31: =IF(D31=E31,"ok","no") -> #N/A | I31: =IF(B31=F31,"ok","no") -> #N/A | J31: =IF(C31=G31,"ok","no") -> #N/A
A32: Aquariumkies | B32: Wertstoff | C32: Wertstoffhof,Deponie | D32: Bis zu 1m ³ reinen Kies können Sie täglich auf den Wertstoffhöfen oder den Deponien der Region Hannover kostenlos entsorgen. Bitte beachten Sie, dass möglichst keine Erde an dem Kies haftet.,Sachstand: 03.05.2024 | E32: =VLOOKUP(A32,All!$C$2:$D$2424,2,FALSE) -> Bis zu 1m ³ reinen Kies können Sie täglich auf den Wertstoffhöfen oder den Deponien der Region Hannover kostenlos entsorgen. Bitte beachten Sie, dass möglichst keine Erde an dem Kies haftet. | F32: =VLOOKUP(A32,All!$C$2:$F$2424,4,FALSE) -> Wertstoff | G32: =VLOOKUP(A32,All!$C$2:$G$2424,5,FALSE) -> Wertstoffhof, Deponie | H32: =IF(D32=E32,"ok","no") -> no | I32: =IF(B32=F32,"ok","no") -> ok | J32: =IF(C32=G32,"ok","no") -> no
A33: Asbestzement | B33: Sonderabfall | C33: Deponie Hannover - Sonderabfallannahmestelle | D33: Asbestzementabfälle zählen zur Gruppe der gefährlichen Abfälle (Sonderabfall). Bis zu 16 kg luftdicht verpacktes Asbest wird auf der Deponie Hannover gebührenfrei entgegengenommen. Bitte melden Sie Ihre Anlieferung unbedingt vorher telefonisch an: 0511 9911- 678 29 oder 0511 9911- 479 61.,Belastete Fußbodenplatten oder -belägen müssen ebenfalls luftdicht verpackt angeliefert werden, bis zu 16 kg an Asbestbelasteten Fußbodenbelägen aus Privathaushalten werden kostenlos nach Anmeldung auf der Deponie Lahe entgegengenommen.,Hinweise zur Entsorgung und eine Gebührenübersicht finden Sie auf unserem | E33: =VLOOKUP(A33,All!$C$2:$D$2424,2,FALSE) -> Asbestzementabfälle zählen zur Gruppe der gefährlichen Abfälle (Sonderabfall). Bis zu 16 kg luftdicht verpacktes Asbest wird auf der Deponie Hannover gebührenfrei entgegengenommen. Bitte melden Sie Ihre Anlieferung unbedingt vorher telefonisch an: 0511 9911- 678 29. Hinweise zur Entsorgung und eine Gebührenübersicht finden Sie auf unserem | F33: =VLOOKUP(A33,All!$C$2:$F$2424,4,FALSE) -> Sonderabfall | G33: =VLOOKUP(A33,All!$C$2:$G$2424,5,FALSE) -> Deponie | H33: =IF(D33=E33,"ok","no") -> no | I33: =IF(B33=F33,"ok","no") -> ok | J33: =IF(C33=G33,"ok","no") -> no
A34: Asche | B34: Restabfall | C34: Restabfalltonne | D34: Holz-, Stein- und Braunkohlen- sowie Grillkohlenaschen gehören in den Restabfallbehälter, wenn sie vollständig ausgekühlt ist. Asche ist meistens belastet und darf daher weder auf den Kompost, noch in die Bio-Tonne gegeben werden.,Sachstand: 08.10.2024 | E34: =VLOOKUP(A34,All!$C$2:$D$2424,2,FALSE) -> Holz-, Stein- und Braunkohlen- sowie Grillkohlenaschen gehören in den Restabfall. Sie sind meist belastet und dürfen weder auf den Kompost noch in die Bio-Tonne oder in den Biosack gegeben werden. | F34: =VLOOKUP(A34,All!$C$2:$F$2424,4,FALSE) -> Restabfall | G34: =VLOOKUP(A34,All!$C$2:$G$2424,5,FALSE) -> Restabfalltonne | H34: =IF(D34=E34,"ok","no") -> no | I34: =IF(B34=F34,"ok","no") -> ok | J34: =IF(C34=G34,"ok","no") -> ok
A35: Asphalt | B35: Andere | C35: Entsorgungsbetriebe aus den Gelben Seiten | D35: Asphalt, Teer oder Straßenaufbruch werden weder auf den Deponien noch den Wertstoffhöfen von aha entgegengenommen. Bitte wenden Sie sich für die Entsorgung von Asphalt an einen externen Entsorger aus dem Branchenbuch/-verzeichnis oder dem Internet.,Sachstand:10.05.2024 | E35: =VLOOKUP(A35,All!$C$2:$D$2424,2,FALSE) -> Leider nicht bei aha. ,Asphalt, Teer oder Straßenaufbruch werden nicht angenommen. Bitte wenden Sie sich an andere Entsorgungsbetriebe aus den Gelben Seiten. | F35: =VLOOKUP(A35,All!$C$2:$F$2424,4,FALSE) -> Andere | G35: =VLOOKUP(A35,All!$C$2:$G$2424,5,FALSE) -> Entsorgungsbetriebe aus den Gelben Seiten | H35: =IF(D35=E35,"ok","no") -> no | I35: =IF(B35=F35,"ok","no") -> ok | J35: =IF(C35=G35,"ok","no") -> ok
A36: Äste, dicke | B36: Grüngut | C36: Deponie | D36: Bis zu 1m ³ Ihrer Rodungsmaterialen wie Wurzelballen, Stammhölzer oder Stubben (mit einem Durchmesser über 15cm) können kostenlos auf den drei Deponien der Region Hannover abgegeben werden. Eine Annahme von Rodungsmaterialien auf den Wertstoffhöfen ist nicht möglich. Kleineres Wurzelmaterial können Sie über die kostenlose Grünabfallabgabestelle auf den Deponien entsorgen. Sollten Sie einmal eine größere Menge an Wurzelballen als 1 m³ entsorgen wollen, können Sie diese kostenpflichtig auf unseren Deponien anliefern. | E36: =VLOOKUP(A36,All!$C$2:$D$2424,2,FALSE) -> Bis zu 1m ³ Ihrer Rodungsmaterialen wie Wurzelballen, Stammhölzer oder Stubben (mit einem Umfang über 15cm) können kostenlos auf den drei Deponien der Region Hannover abgegeben werden. Eine Annahme von Rodungsmaterialien auf den Wertstoffhöfen ist nicht möglich. Kleineres Wurzelmaterial können Sie über die kostenlose Grünabfallabgabestelle auf den Deponien entsorgen. Sollten Sie einmal eine größere Menge an Wurzelballen als 1 m³ entsorgen wollen, können Sie diese kostenpflichtig auf unseren Deponien anliefern. | F36: =VLOOKUP(A36,All!$C$2:$F$2424,4,FALSE) -> Grüngut | G36: =VLOOKUP(A36,All!$C$2:$G$2424,5,FALSE) -> Deponie | H36: =IF(D36=E36,"ok","no") -> no | I36: =IF(B36=F36,"ok","no") -> ok | J36: =IF(C36=G36,"ok","no") -> ok
A37: Ätznatron | B37: Sonderabfall | C37: Wertstoffhof,Deponie Hannover - Sonderabfallannahmestelle | D37: Bis zu 30kg (Gesamtmenge/ haushaltsübliche Mengen) Ihrer gefährlichen Abfälle, können Sie täglich kostenlos auf allen Wertstoffhöfen abgeben. Auf den Wertstoffhöfen der Region werden Sonderabfälle in Gebinden bis zu einer Größe von max. 10 Litern entgegengenommen. Größere Mengen oder Gebinde können kostenpflichtig an der Sonderannahmestelle auf der Deponie Hannover Lahe abgeben. Gebinde über 10 Liter sind ebenfalls an der Deponie in Hannover anzuliefern.,Bitte beachten Sie die Mengenbegrenzung der einzelnen Abfälle, auf der Preisliste für Sonderabfall.,Bitte achten Sie bei dem Transport darauf, die Gebinde gut zu kennzeichnen und auf keinen Fall mit anderen Flüssigkeiten zu vermischen. Am sichersten transportieren Sie Sonderabfälle nur dicht verschlossen in den originalen Behältern (Gebinden) sowie aufrechtstehend (z.B. in einer Wanne, die Behälter aufrecht hält).,Wichtig: Nutzen Sie bitte die Abgabezeiten für Gewerbekunden (Mo. bis Do. von 7.00 – 14.00 Uhr und Fr. von 7.00 – 12.00 Uhr), wenn Sie größere Mengen an Sonderabfällen abgeben wollen.,Sachstand 19.07.2023 | E37: =VLOOKUP(A37,All!$C$2:$D$2424,2,FALSE) -> Bis zu 30 Kg (Gesamtmenge/ haushaltsübliche Mengen) Ihrer gefährlichen Abfälle täglich können Sie kostenlos auf den Wertstoffhöfen der Region Hannover oder der Deponie Hannover im Sonderabfallzwischenlager abgeben. Größere Mengen können Sie kostenpflichtig an der Sonderannahmestelle auf der Deponie Hannover abgeben. Bitte beachten Sie hierzu die Preisliste für Sonderabfall. Bitte achten Sie bei dem Transport darauf, die Gebinde gut zu kennzeichnen und auf keinen Fall mit anderen Flüssigkeiten zu vermischen. Am sichersten transportieren Sie Sonderabfälle nur dicht verschlossen in den originalen Behältern (Gebinden) sowie aufrecht stehend (z.B in einer Wanne, die Behälter aufrecht hält). | F37: =VLOOKUP(A37,All!$C$2:$F$2424,4,FALSE) -> Sonderabfall | G37: =VLOOKUP(A37,All!$C$2:$G$2424,5,FALSE) -> Wertstoffhof, Deponie | H37: =IF(D37=E37,"ok","no") -> no | I37: =IF(B37=F37,"ok","no") -> ok | J37: =IF(C37=G37,"ok","no") -> no
A38: Auftausalz | B38: Sonderabfall | C38: Wertstoffhof,Deponie Hannover - Sonderabfallannahmestelle | D38: Bis zu 30kg (Gesamtmenge/ haushaltsübliche Mengen) Ihrer gefährlichen Abfälle, können Sie täglich kostenlos auf allen Wertstoffhöfen abgeben. Auf den Wertstoffhöfen der Region werden Sonderabfälle in Gebinden bis zu einer Größe von max. 10 Litern entgegengenommen. Größere Mengen oder Gebinde können kostenpflichtig an der Sonderannahmestelle auf der Deponie Hannover Lahe abgeben. Gebinde über 10 Liter sind ebenfalls an der Deponie in Hannover anzuliefern.,Bitte beachten Sie die Mengenbegrenzung der einzelnen Abfälle, auf der Preisliste für Sonderabfall.,Bitte achten Sie bei dem Transport darauf, die Gebinde gut zu kennzeichnen und auf keinen Fall mit anderen Flüssigkeiten zu vermischen. Am sichersten transportieren Sie Sonderabfälle nur dicht verschlossen in den originalen Behältern (Gebinden) sowie aufrechtstehend (z.B. in einer Wanne, die Behälter aufrecht hält).,Wichtig: Nutzen Sie bitte die Abgabezeiten für Gewerbekunden (Mo. bis Do. von 7.00 – 14.00 Uhr und Fr. von 7.00 – 12.00 Uhr), wenn Sie größere Mengen an Sonderabfällen abgeben wollen.,Sachstand 19.07.2023 | E38: =VLOOKUP(A38,All!$C$2:$D$2424,2,FALSE) -> Bis zu 30 Kg (Gesamtmenge/ haushaltsübliche Mengen) Ihrer gefährlichen Abfälle täglich können Sie kostenlos auf den Wertstoffhöfen der Region Hannover oder der Deponie Hannover im Sonderabfallzwischenlager abgeben. Größere Mengen können Sie kostenpflichtig an der Sonderannahmestelle auf der Deponie Hannover abgeben. Bitte beachten Sie hierzu die Preisliste für Sonderabfall. Bitte achten Sie bei dem Transport darauf, die Gebinde gut zu kennzeichnen und auf keinen Fall mit anderen Flüssigkeiten zu vermischen. Am sichersten transportieren Sie Sonderabfälle nur dicht verschlossen in den originalen Behältern (Gebinden) sowie aufrecht stehend (z.B in einer Wanne, die Behälter aufrecht hält). | F38: =VLOOKUP(A38,All!$C$2:$F$2424,4,FALSE) -> Sonderabfall | G38: =VLOOKUP(A38,All!$C$2:$G$2424,5,FALSE) -> Wertstoffhof, Deponie | H38: =IF(D38=E38,"ok","no") -> no | I38: =IF(B38=F38,"ok","no") -> ok | J38: =IF(C38=G38,"ok","no") -> no
A39: Autobatterie | B39: Sonderabfall | C39: Wertstoffhof,Deponie Hannover - Sonderabfallannahmestelle | D39: Autobatterien zählen auf Grund Ihrer Bestandteile zu den gefährlichen Abfällen (Sonderabfall). Fachhändler, Autoverwertungsbetriebe, Tankstellen sowie Schrotthändler nehmen Autobatterien zurück. Sie können Ihre Autobatterie auch kostenlos auf den Wertstoffhöfen der Region Hannover oder der Deponie Hannover im Sonderabfallzwischenlager abgeben.,Sachstand:10.05.2024 | E39: =VLOOKUP(A39,All!$C$2:$D$2424,2,FALSE) -> Autobatterien zählen auf Grund Ihrer Bestandteile zu den gefährlichen Abfällen (Sonderabfall). Fachhändler, Autoverwertungsbetriebe, Tankstellen sowie Schrotthändler nehmen Autobatterien zurück. Sie können Ihre Autobatterie auch kostenlos auf den Wertstoffhöfen der Region Hannover oder der Deponie Hannover im Sonderabfallzwischenlager abgeben. | F39: =VLOOKUP(A39,All!$C$2:$F$2424,4,FALSE) -> Sonderabfall | G39: =VLOOKUP(A39,All!$C$2:$G$2424,5,FALSE) -> Wertstoffhof, Deponie, Händler | H39: =IF(D39=E39,"ok","no") -> no | I39: =IF(B39=F39,"ok","no") -> ok | J39: =IF(C39=G39,"ok","no") -> no
A40: Autoteile | D40: Altfahrzeuge, Fahrzeugwracks, und Fahrzeugteile werden von zertifizierten Verwertungsbetrieben angenommen und einer Verwertung zugeführt (siehe www.gelbeseiten.de). Sie werden nicht an den Wertstoffhöfen von aha angenommen; auch bei der Sperrabfallsammlung werden sie nicht mitgenommen.,In zertifizierten Verwertungsbetrieben wird Ihnen ein Verwertungsnachweis für Ihr Altfahrzeug ausgehändigt; verlangen Sie diesen unbedingt!, In den Fachbetrieben werden aus diesen Fahrzeugen die Betriebsflüssigkeiten entfernt und einer fachgerechten Aufbereitung (z.B. Öle aller Art) oder Entsorgung zugeführt. Zusätzlich werden aus den Fahrzeugen die weiter einsetzbaren Ersatzteile demontiert und dem Markt zur weiteren Nutzung als kostengünstige Ersatzteile erhalten. Kabel, Metalle u.a. werden der Wiederverwertung zugeführt. Der nicht mehr nutzbare Rest des Fahrzeuges wird ordnungsgemäß entsorgt.,Über ,können Sie Fahrzeuge ohne Zulassung oder Fahrzeugwracks, die im öffentlichen Straßenraum stehen, melden.,Im Umland wenden Sie sich bitte an die entsprechende Stadt- oder Gemeindeverwaltung, bzw. an die Region Hannover.,Sachstand: 08.05.2024 | E40: =VLOOKUP(A40,All!$C$2:$D$2424,2,FALSE) -> #N/A | F40: =VLOOKUP(A40,All!$C$2:$F$2424,4,FALSE) -> #N/A | G40: =VLOOKUP(A40,All!$C$2:$G$2424,5,FALSE) -> #N/A | H40: =IF(D40=E40,"ok","no") -> #N/A | I40: =IF(B40=F40,"ok","no") -> #N/A | J40: =IF(C40=G40,"ok","no") -> #N/A
A41: Babybadewanne | B41: Wertstoff | C41: Wertstoffhof | D41: Babybadewannen können kostenfrei auf den Wertstoffhöfen und Deponien der Region Hannover entsorgt werden. Bitte entsorgen Sie die Wanne im PE/PP-Container (Polyethylen/Polypropylen).,Sachstand:10.05.2024 | E41: =VLOOKUP(A41,All!$C$2:$D$2424,2,FALSE) -> Eine Babybadewanne wird auf den Wertstoffhöfen angenommen, bitte entsorgen Sie die Wanne im PE/PP-Container (Polyethylen/Polypropylen). | F41: =VLOOKUP(A41,All!$C$2:$F$2424,4,FALSE) -> Wertstoff | G41: =VLOOKUP(A41,All!$C$2:$G$2424,5,FALSE) -> Wertstoffhof | H41: =IF(D41=E41,"ok","no") -> no | I41: =IF(B41=F41,"ok","no") -> ok | J41: =IF(C41=G41,"ok","no") -> ok
A42: Backofenreiniger | B42: Sonderabfall | C42: Wertstoffhof,Deponie Hannover - Sonderabfallannahmestelle | D42: Bis zu 30kg (Gesamtmenge/ haushaltsübliche Mengen) Ihrer gefährlichen Abfälle, können Sie täglich kostenlos auf allen Wertstoffhöfen abgeben. Auf den Wertstoffhöfen der Region werden Sonderabfälle in Gebinden bis zu einer Größe von max. 10 Litern entgegengenommen. Größere Mengen oder Gebinde können kostenpflichtig an der Sonderannahmestelle auf der Deponie Hannover Lahe abgeben. Gebinde über 10 Liter sind ebenfalls an der Deponie in Hannover anzuliefern.,Bitte beachten Sie die Mengenbegrenzung der einzelnen Abfälle, auf der Preisliste für Sonderabfall.,Bitte achten Sie bei dem Transport darauf, die Gebinde gut zu kennzeichnen und auf keinen Fall mit anderen Flüssigkeiten zu vermischen. Am sichersten transportieren Sie Sonderabfälle nur dicht verschlossen in den originalen Behältern (Gebinden) sowie aufrechtstehend (z.B. in einer Wanne, die Behälter aufrecht hält).,Wichtig: Nutzen Sie bitte die Abgabezeiten für Gewerbekunden (Mo. bis Do. von 7.00 – 14.00 Uhr und Fr. von 7.00 – 12.00 Uhr), wenn Sie größere Mengen an Sonderabfällen abgeben wollen.,Sachstand 19.07.2023 | E42: =VLOOKUP(A42,All!$C$2:$D$2424,2,FALSE) -> Bis zu 30 Kg (Gesamtmenge/ haushaltsübliche Mengen) Ihrer gefährlichen Abfälle täglich können Sie kostenlos auf den Wertstoffhöfen der Region Hannover oder der Deponie Hannover im Sonderabfallzwischenlager abgeben. Größere Mengen können Sie kostenpflichtig an der Sonderannahmestelle auf der Deponie Hannover abgeben. Bitte beachten Sie hierzu die Preisliste für Sonderabfall. Bitte achten Sie bei dem Transport darauf, die Gebinde gut zu kennzeichnen und auf keinen Fall mit anderen Flüssigkeiten zu vermischen. Am sichersten transportieren Sie Sonderabfälle nur dicht verschlossen in den originalen Behältern (Gebinden) sowie aufrecht stehend (z.B in einer Wanne, die Behälter aufrecht hält). | F42: =VLOOKUP(A42,All!$C$2:$F$2424,4,FALSE) -> Sonderabfall | G42: =VLOOKUP(A42,All!$C$2:$G$2424,5,FALSE) -> Wertstoffhof, Deponie | H42: =IF(D42=E42,"ok","no") -> no | I42: =IF(B42=F42,"ok","no") -> ok | J42: =IF(C42=G42,"ok","no") -> no
A43: Backwaren | B43: Restabfall | C43: Restabfalltonne | D43: Backwaren aus Haushalten werden als Essensreste in der Restabfalltonne entsorgt., Backwaren aus Gewerbebetrieben sind Speisereste, die verwertet werden. Informationen erhalten Sie beim aha-Gewerbekundenservice unter folgendem Link: ,Sachstand: 03.05.2024 | E43: =VLOOKUP(A43,All!$C$2:$D$2424,2,FALSE) -> Backwaren aus Haushalten werden als Essensreste im Restabfall entsorgt. Backwaren aus Gewerbebetrieben sind Speisereste, die verwertet werden. Informationen erhalten Sie beim aha-Gewerbekundenservice. | F43: =VLOOKUP(A43,All!$C$2:$F$2424,4,FALSE) -> Restabfall | G43: =VLOOKUP(A43,All!$C$2:$G$2424,5,FALSE) -> Restabfalltonne | H43: =IF(D43=E43,"ok","no") -> no | I43: =IF(B43=F43,"ok","no") -> ok | J43: =IF(C43=G43,"ok","no") -> ok
A44: Badewanne | B44: Wertstoff | C44: Wertstoffhof | D44: Eine Badewanne aus dem privaten Haushalt wird kostenfrei auf den Wertstoffhöfen und den Deponien der Region Hannover angenommen.,Dusch- und Badewannen können aus unterschiedlichen Materialien gefertigt sein, so dass sie unterschiedlichen Entsorgungswegen auf den Wertstoffhöfen/ Deponien zuzuordnen sind:,Metall (emailliert) -> Schrottcontainer,Keramik -> Bauschuttcontainer,andere Materialien -> Sperrabfallcontainer,Eine Badewanne aus Kunststoff oder Metall, deren Gewicht unter 75 kg beträgt, können kostenfrei bei der Sperrabfallabholung angemeldet werden.,Sachstand:10.05.2024 | E44: =VLOOKUP(A44,All!$C$2:$D$2424,2,FALSE) -> Eine Badewanne aus dem privaten Haushalt wird auf den Wertstoffhöfen angenommen. ,Dusch- und Badewannen können aus unterschiedlichen Materialien gefertigt sein, so dass sie unterschiedlichen Entsorgungswegen an den Wertstoffhöfen zuzuordnen sind:Eine Badewanne aus Kunststoff, deren Gewicht unter 75 kg beträgt, kann bei der Sperrabfallabholung angemeldet werden. | F44: =VLOOKUP(A44,All!$C$2:$F$2424,4,FALSE) -> Wertstoff | G44: =VLOOKUP(A44,All!$C$2:$G$2424,5,FALSE) -> Wertstoffhof, Sperrabfallabholung | H44: =IF(D44=E44,"ok","no") -> no | I44: =IF(B44=F44,"ok","no") -> ok | J44: =IF(C44=G44,"ok","no") -> no
A45: Badreiniger | B45: Sonderabfall | C45: Wertstoffhof,Deponie Hannover - Sonderabfallannahmestelle | D45: Bis zu 30kg (Gesamtmenge/ haushaltsübliche Mengen) Ihrer gefährlichen Abfälle, können Sie täglich kostenlos auf allen Wertstoffhöfen abgeben. Auf den Wertstoffhöfen der Region werden Sonderabfälle in Gebinden bis zu einer Größe von max. 10 Litern entgegengenommen. Größere Mengen oder Gebinde können kostenpflichtig an der Sonderannahmestelle auf der Deponie Hannover Lahe abgeben. Gebinde über 10 Liter sind ebenfalls an der Deponie in Hannover anzuliefern.,Bitte beachten Sie die Mengenbegrenzung der einzelnen Abfälle, auf der Preisliste für Sonderabfall.,Bitte achten Sie bei dem Transport darauf, die Gebinde gut zu kennzeichnen und auf keinen Fall mit anderen Flüssigkeiten zu vermischen. Am sichersten transportieren Sie Sonderabfälle nur dicht verschlossen in den originalen Behältern (Gebinden) sowie aufrechtstehend (z.B. in einer Wanne, die Behälter aufrecht hält).,Wichtig: Nutzen Sie bitte die Abgabezeiten für Gewerbekunden (Mo. bis Do. von 7.00 – 14.00 Uhr und Fr. von 7.00 – 12.00 Uhr), wenn Sie größere Mengen an Sonderabfällen abgeben wollen.,Sachstand 19.07.2023 | E45: =VLOOKUP(A45,All!$C$2:$D$2424,2,FALSE) -> Bis zu 30 Kg (Gesamtmenge/ haushaltsübliche Mengen) Ihrer gefährlichen Abfälle täglich können Sie kostenlos auf den Wertstoffhöfen der Region Hannover oder der Deponie Hannover im Sonderabfallzwischenlager abgeben. Größere Mengen können Sie kostenpflichtig an der Sonderannahmestelle auf der Deponie Hannover abgeben. Bitte beachten Sie hierzu die Preisliste für Sonderabfall. Bitte achten Sie bei dem Transport darauf, die Gebinde gut zu kennzeichnen und auf keinen Fall mit anderen Flüssigkeiten zu vermischen. Am sichersten transportieren Sie Sonderabfälle nur dicht verschlossen in den originalen Behältern (Gebinden) sowie aufrecht stehend (z.B in einer Wanne, die Behälter aufrecht hält). | F45: =VLOOKUP(A45,All!$C$2:$F$2424,4,FALSE) -> Sonderabfall | G45: =VLOOKUP(A45,All!$C$2:$G$2424,5,FALSE) -> Wertstoffhof, Deponie | H45: =IF(D45=E45,"ok","no") -> no | I45: =IF(B45=F45,"ok","no") -> ok | J45: =IF(C45=G45,"ok","no") -> no
A46: Bahnschwellen | B46: Andere | C46: Deponie Hannover Lahe | D46: Hölzer wie z. B. Bahnschwellen, Jägerzäune, Pfähle, Masten sind durch umwelt- und gesundheitsschädigende Holzschutzmittel belastet. Aus Privathaushalten erfolgt die Annahme an der Deponie Hannover in Lahe bis zur Menge von 1 m³ kostenlos, größere Mengen nur gegen Gebühr.,Das kontaminierte Altholz wird in einem separaten Behälter gesammelt und einer gesonderten Entsorgung zugeführt., , , Kontaminiertes Altholz aus Gewerbebetrieben wird an der Deponie Hannover gebührenpflichtig in einem separaten Behälter angenommen. Bitte beachten Sie unsere ,. | E46: =VLOOKUP(A46,All!$C$2:$D$2424,2,FALSE) -> Bis zu 1 m³ (Gesamtmenge/ haushaltsübliche Mengen) ihrer behandelten Holzabfälle täglich können Sie kostenlos auf den Deponien Lahe und Kolenfeld der Region Hannover abgeben. Größere Mengen können Sie ebenfalls kostenpflichtig dort abgeben. Bitte beachten Sie hierzu die Preisliste für die Deponieanlieferung. Die Annahmebedingungen unserer Deponien und Wertstoffhöfe finden Sie , und ,. | F46: =VLOOKUP(A46,All!$C$2:$F$2424,4,FALSE) -> Andere | G46: =VLOOKUP(A46,All!$C$2:$G$2424,5,FALSE) -> Deponie, Deponie | H46: =IF(D46=E46,"ok","no") -> no | I46: =IF(B46=F46,"ok","no") -> ok | J46: =IF(C46=G46,"ok","no") -> no
A47: Bambus | B47: Bioabfall | C47: Wertstoffhof,Biotonne,Biosack,Deponie | D47: Bambus und Schilf aus Privathaushalten kann auf Grund seiner schnellen Ausbreitung und Silicatbelastung nur auf den Wertstoffhöfen oder Deponien (maximale Länge von 150 cm) angeliefert werden. Die landwirtschaftlichen Grüngutannahmestellen nehmen Bambus und Schilf nicht entgegen. Des Weiteren besteht die Möglichkeit der Eigenkompostierung auf dem eigenen Grundstück. Die Annahmebedingungen der einzelnen Annahmestellen sind abhängig von der Art des angelieferten Grüngutes.,Wichtig: Sollte es sich allerding um eine Bambusart handeln, die sich durch unterirdische Sprossen (Rhizome) verbreitet, empfehlen wir den Bambus nicht selbst zu kompostieren oder bei den landwirtschaftlichen Grüngutannahmestellen zu entsorgen. Diese Art Bambus kann über die Biotonne/ Bioabfallsäcke, die drei Kompostwerke bei den Deponien oder die Grüngutcontainer auf den Wertstoffhöfen entsorgt werden. | E47: =VLOOKUP(A47,All!$C$2:$D$2424,2,FALSE) -> Grüngut wird in allen drei Grünabfallkompostwerken von aha zu hochwertigem RAL-gütegesichertem Kompost verarbeitet. Die Annahme erfolgt auf den Wertstoffhöfen, den Deponien und z.T. auch auf den landwirtschaftlichen Grüngutannahmestellen. Bei nachgewiesener Eigenkompostierung kann es auch auf dem eigenen Grundstück verwertet werden. Die Annahmebedingungen sind abhängig von der Art des Grüngutes. Rasenschnitt (nicht auf Grüngutannahmestellen) | F47: =VLOOKUP(A47,All!$C$2:$F$2424,4,FALSE) -> Bioabfall | G47: =VLOOKUP(A47,All!$C$2:$G$2424,5,FALSE) -> Wertstoffhof, Biotonne, Biosack | H47: =IF(D47=E47,"ok","no") -> no | I47: =IF(B47=F47,"ok","no") -> ok | J47: =IF(C47=G47,"ok","no") -> no
A48: Bärenklau | B48: giftigen oder invasiven Pflanzen | C48: Wertstoffhof,Deponie | D48: Bitte verpacken Sie die giftigen Pflanzen gut und gesondert von anderen Materialien.,Bis zu 1 m³ (Gesamtmenge/ haushaltsübliche Mengen) Ihrer giftigen oder invasiven Pflanzen täglich können Sie kostenlos auf den Wertstoffhöfen der Region Hannover (im Sperrabfall) abgeben. Größere Mengen können Sie kostenpflichtig an den Deponien der Region Hannover abgeben. Bitte beachten Sie hierzu die Preisliste für die Deponieanlieferung unter folgendem Link: , finden Sie die Annahmebedingungen unserer Wertstoffhofe, , die der Deponien. | E48: =VLOOKUP(A48,All!$C$2:$D$2424,2,FALSE) -> Bitte verpacken Sie die giftigen Pflanzen gut und gesondert von anderen Materialien. Bis zu 1 m³ (Gesamtmenge/ haushaltsübliche Mengen) Ihrer giftigen oder invasiven Pflanzen täglich können Sie kostenlos auf den Wertstoffhöfen der Region Hannover (im Sperrabfall) abgeben. Größere Mengen können Sie kostenpflichtig an den Deponien der Region Hannover abgeben. Bitte beachten Sie hierzu die Preisliste für die Deponieanlieferung. finden Sie die Annahmebedingungen unserer Wertstoffhofe, die der Deponien. | F48: =VLOOKUP(A48,All!$C$2:$F$2424,4,FALSE) -> giftigen oder invasiven Pflanzen | G48: =VLOOKUP(A48,All!$C$2:$G$2424,5,FALSE) -> Wertstoffhof, Deponie | H48: =IF(D48=E48,"ok","no") -> no | I48: =IF(B48=F48,"ok","no") -> ok | J48: =IF(C48=G48,"ok","no") -> no
A49: Batterien | B49: Sonderabfall | C49: Deponie Hannover - Sonderabfallannahmestelle | D49: aha nimmt Gerätebatterien, z. B. aus Taschenlampen, Uhren, Radios usw. an. Haushaltsübliche Kleinmengen an Batterien können Sie täglich kostenlos auf den Wertstoffhöfen der Region Hannover oder der Deponie Hannover im Sonderabfallzwischenlager abgeben.,Bitte kleben Sie vor der Abgabe die beiden Pole der Batterien mit Klebestreifen ab. Diese Maßnahme verringert die Brandgefahr und Entzündungsgefahr.,Ausgediente Akkus von E-Bikes, E-Scootern und Motorrädern gehören zu laut §8 Batteriegesetz zu den Industriebatterien. Industriebatterien werden von aha nicht angenommen. Bitte geben Sie diese an den Fachhandel zurück.,Die einzige Ausnahme von dieser Regel stellen Starterbatterien auf Bleibasis von LKWs und PKWs sowie Motorrädern dar. | E49: =VLOOKUP(A49,All!$C$2:$D$2424,2,FALSE) -> aha nimmt Gerätebatterien, z. B. aus Taschenlampen, Uhren, Radios usw. an. Bis zu 30 kg Ihrer gefährlichen Abfälle täglich können Sie kostenlos auf den Wertstoffhöfen der Region Hannover oder der Deponie Hannover im Sonderabfallzwischenlager abgeben. Ausgediente Akkus von E-Bikes und E-Scootern gehören zu laut §8 Batteriegesetz zu den Industriebatterien. Industriebatterien werden von aha nicht angenommen. Bitte geben Sie diese an den Fachhandel zurück. Die einzige Ausnahme von dieser Regel stellen Starterbatterien auf Bleibasis von LKWs und PKWs sowie Motorrädern dar. Ausgediente Akkus von E-Bikes, E-Scootern und Motorrädern gehören zu laut §8 Batteriegesetz zu den Industriebatterien. Industriebatterien werden von aha nicht angenommen. Bitte geben Sie diese an den Fachhandel zurück. | F49: =VLOOKUP(A49,All!$C$2:$F$2424,4,FALSE) -> Sonderabfall | G49: =VLOOKUP(A49,All!$C$2:$G$2424,5,FALSE) -> Wertstoffhof, Deponie | H49: =IF(D49=E49,"ok","no") -> no | I49: =IF(B49=F49,"ok","no") -> ok | J49: =IF(C49=G49,"ok","no") -> no
A50: Bau- und Abbruchholz | C50: Wertstoffhof | D50: d.h. Holzabfälle ohne Störstoffe (keine Metalle, Kunststoffe, Glas), keine Holzabfälle mit schädlichen Verunreinigungen,und,z.B. Bahnschwellen, Leitungsmasten, Jägerzäune, Fenster, Außentüren und sonstige Hölzer aus dem Außenbereich (Annahme nur auf der Depoie Hannover in Lahe),Bis zu 1 m³ (Gesamtmenge/ haushaltsübliche Mengen) Ihrer Holzabfälle können Sie täglich kostenlos auf den Wertstoffhöfen der Region Hannover abgeben. Größere Mengen können Sie kostenpflichtig an den Deponien der Region Hannover abgeben. Bitte beachten Sie hierzu die Preisliste für die Deponieanlieferung. Die Annahmebedingungen unserer Deponien und Wertstoffhöfe finden Sie hier (,) und hier (,).,Verdreckte Holzabfälle aus Hühnerställen, Hühner-/ oder Taubenverschlägen werden auf Grund ihrer Verschmutzung durch Tierfäkalien weder auf den Wertstoffhöfen noch auf den drei Regionsdeponien angenommen. Bitte wenden Sie sich für die Entsorgung solcher Materialien an eine Fachfirma.,Sachstand: 13.03.2024, | E50: =VLOOKUP(A50,All!$C$2:$D$2424,2,FALSE) -> #N/A | F50: =VLOOKUP(A50,All!$C$2:$F$2424,4,FALSE) -> #N/A | G50: =VLOOKUP(A50,All!$C$2:$G$2424,5,FALSE) -> #N/A | H50: =IF(D50=E50,"ok","no") -> #N/A | I50: =IF(B50=F50,"ok","no") -> #N/A | J50: =IF(C50=G50,"ok","no") -> #N/A
A51: Baum-, Strauch- und Heckenschnitt | C51: Wertstoffhof,Biotonne,Grüngutannahmestellen,Deponie | D51: Bei den Wertstoffhöfen und Grüngutannahmestellen werden Baum-, Strauch- und Heckenschnitt (bis 15 cm Astdurchmesser und einer maximalen Länge von 150 cm) aus Privathaushalten in einer Anlieferung pro Kalendertag bis zu einer Gesamtmenge von insgesamt 1 m³ kostenlos angenommen.,Wenn gelegentlich mehr Abfall entsteht, kann er im Kompostwerk der Deponien kostenpflichtig angeliefert werden., | E51: =VLOOKUP(A51,All!$C$2:$D$2424,2,FALSE) -> #N/A | F51: =VLOOKUP(A51,All!$C$2:$F$2424,4,FALSE) -> #N/A | G51: =VLOOKUP(A51,All!$C$2:$G$2424,5,FALSE) -> #N/A | H51: =IF(D51=E51,"ok","no") -> #N/A | I51: =IF(B51=F51,"ok","no") -> #N/A | J51: =IF(C51=G51,"ok","no") -> #N/A
A52: Baumnadeln | B52: Grüngut | C52: Wertstoffhof,Biotonne | D52: Bamnadeln sind Grünabfälle. Grünabfälle sind zum Beispiel:,Sammeln Sie Grünabfälle in der Biotonne. Besser noch: Sie kompostieren alle anfallenden kompostierbaren Abfälle auf Ihrem Grundstück., , <link 25>Infos zum Kompostieren</link> | E52: =VLOOKUP(A52,All!$C$2:$D$2424,2,FALSE) -> Bamnadeln sind Grünabfälle. Grünabfälle sind zum Beispiel:Sammeln Sie Grünabfälle in der Biotonne oder im Biosack. Besser noch: Sie kompostieren alle anfallenden kompostierbaren Abfälle auf Ihrem Grundstück. | F52: =VLOOKUP(A52,All!$C$2:$F$2424,4,FALSE) -> Grüngut | G52: =VLOOKUP(A52,All!$C$2:$G$2424,5,FALSE) -> Wertstoffhof, Biotonne, Biosack | H52: =IF(D52=E52,"ok","no") -> no | I52: =IF(B52=F52,"ok","no") -> ok | J52: =IF(C52=G52,"ok","no") -> no
A53: Baumstümpfe, -stubben | C53: Deponie | D53: Bis zu 1m ³ Ihrer Rodungsmaterialen wie Wurzelballen, Stammhölzer oder Stubben (mit einem Durchmesser über 15cm) können kostenlos auf den drei Deponien der Region Hannover abgegeben werden. Eine Annahme von Rodungsmaterialien auf den Wertstoffhöfen ist nicht möglich. Kleineres Wurzelmaterial können Sie über die kostenlose Grünabfallabgabestelle auf den Deponien entsorgen. Sollten Sie einmal eine größere Menge an Wurzelballen als 1 m³ entsorgen wollen, können Sie diese kostenpflichtig auf unseren Deponien anliefern. | E53: =VLOOKUP(A53,All!$C$2:$D$2424,2,FALSE) -> #N/A | F53: =VLOOKUP(A53,All!$C$2:$F$2424,4,FALSE) -> #N/A | G53: =VLOOKUP(A53,All!$C$2:$G$2424,5,FALSE) -> #N/A | H53: =IF(D53=E53,"ok","no") -> #N/A | I53: =IF(B53=F53,"ok","no") -> #N/A | J53: =IF(C53=G53,"ok","no") -> #N/A
A54: Bauschaum | B54: Sonderabfall | C54: Wertstoffhof,Deponie Hannover - Sonderabfallannahmestelle | D54: Bis zu 30 Kg (Gesamtmenge/ haushaltsübliche Mengen) Ihrer gefährlichen Abfälle täglich können Sie kostenlos auf den Wertstoffhöfen der Region Hannover oder der Deponie Hannover im Sonderabfallzwischenlager abgeben. Größere Mengen können Sie kostenpflichtig an der Sonderannahmestelle auf der Deponie Hannover abgeben. Bitte beachten Sie hierzu die Preisliste für Sonderabfall.,Bitte achten Sie bei dem Transport darauf, die Gebinde gut zu kennzeichnen und auf keinen Fall mit anderen Flüssigkeiten zu vermischen. Am sichersten transportieren Sie Sonderabfälle nur dicht verschlossen in den originalen Behältern (Gebinden) sowie aufrecht stehend (z.B in einer Wanne, die Behälter aufrecht hält)., Nutzen Sie bitte die Abgabezeiten für Gewerbekunden (Mo. bis Do. von 7.00 – 14.00 Uhr und Fr. von 7.00 – 12.00 Uhr), wenn Sie größere Mengen an Sonderabfällen abgeben wollen.,Ausgehärtete Schaum ist ungefährlich, er kann als Restabfall über den Restabfall entsorgt werden. | E54: =VLOOKUP(A54,All!$C$2:$D$2424,2,FALSE) -> Bis zu 30 Kg (Gesamtmenge/ haushaltsübliche Mengen) Ihrer gefährlichen Abfälle täglich können Sie kostenlos auf den Wertstoffhöfen der Region Hannover oder der Deponie Hannover im Sonderabfallzwischenlager abgeben. Größere Mengen können Sie kostenpflichtig an der Sonderannahmestelle auf der Deponie Hannover abgeben. Bitte beachten Sie hierzu die Preisliste für Sonderabfall. Bitte achten Sie bei dem Transport darauf, die Gebinde gut zu kennzeichnen und auf keinen Fall mit anderen Flüssigkeiten zu vermischen. Am sichersten transportieren Sie Sonderabfälle nur dicht verschlossen in den originalen Behältern (Gebinden) sowie aufrecht stehend (z.B in einer Wanne, die Behälter aufrecht hält). | F54: =VLOOKUP(A54,All!$C$2:$F$2424,4,FALSE) -> Sonderabfall | G54: =VLOOKUP(A54,All!$C$2:$G$2424,5,FALSE) -> Wertstoffhof, Deponie | H54: =IF(D54=E54,"ok","no") -> no | I54: =IF(B54=F54,"ok","no") -> ok | J54: =IF(C54=G54,"ok","no") -> no
A55: Bauschutt | B55: Bauabfall | C55: Wertstoffhof | D55: Aus Privathaushalten wird Bauschutt (mineralische Abfälle wie z. B. Ziegel, Steine, Fliesen, Mörtel, Sanitärkeramik und auch Porzellan, Tontöpfe) bis zur Menge von 1 m³ pro Tag an den Wertstoffhöfen kostenlos angenommen.,Größere Anlieferungen an Bauschutt können kostenpflichtig auf der Deponie Lahe abgebeben werden. Wichtig: Der angelieferte Bauschutt muss eigenhändig abgeladen werden.,Der Bauschutt sollte möglichst keine Verunreinigungen wie z.B. Gasbetonsteine, Bimssteine, usw. enthalten. Ebenfalls sollten auch keine wassergefährdenden Stoffe, Teerprodukte, asbesthaltige Materialien oder andere Sonderabfälle den Bauschutt verunreinigen, belasteter Bauschutt, z.B. Schornsteinabbruch, wird nicht angenommen. | E55: =VLOOKUP(A55,All!$C$2:$D$2424,2,FALSE) -> Aus Privathaushalten wird Bauschutt (mineralische Abfälle wie z. B. Ziegel, Steine, Fliesen, Mörtel, Sanitärkeramik und auch Porzellan, Tontöpfe) bis zur Menge von 1 m³ pro Tag an den Wertstoffhöfen kostenlos angenommen. Es dürfen keine Verunreinigungen wie z.B. Gasbetonsteine, Bimssteine, usw. enthalten sein. Es dürfen auch keine wassergefährdenden Stoffe, Teerprodukte, asbesthaltigen Materialien und andere Sonderabfälle enthalten sein. Ebenfalls sollte der Bauschutt auch keine wassergefährdenden Stoffe, Teerprodukte, asbesthaltige Materialien oder andere Sonderabfälle enthalten. Belasteter Bauschutt, z.B. Schornsteinabbruch, wird nicht angenommen. | F55: =VLOOKUP(A55,All!$C$2:$F$2424,4,FALSE) -> Bauabfall | G55: =VLOOKUP(A55,All!$C$2:$G$2424,5,FALSE) -> Wertstoffhof | H55: =IF(D55=E55,"ok","no") -> no | I55: =IF(B55=F55,"ok","no") -> ok | J55: =IF(C55=G55,"ok","no") -> ok
A56: Baustellenabfälle | B56: Bauabfall | C56: Deponie | D56: Kleinere Mengen Baustellenabfälle aus privaten Haushalten, wie z.B. Fußbodenbeläge (asbestfrei), Dämmungen, Mineralfaserabfälle, Gipskarton, Teppichreste, Baukunststoffe, Plastikrohre, Dachbahnen (nachweislich teerfrei) usw., können Sie bis 1m³ kostenlos nur auf den Wertstoffhöfen der Deponien abgeben. Der Abfall muss sortiert nach den einzelnen Fraktionen angeliefert werden. Größere Mengen nehmen wir gegen Gebühr auf den Deponien Hannover-Lahe und Kolenfeld an.,Dämmstoffe, HBCD belastet, sowie teerhaltige Dachpappe werden nur auf der Deponie Hannover-Lahe angenommen.,Tapetenreste und verschmutzte Malerfolien gehören in den Restabfall. Sollte der Restabfallbehälter nicht ausreichen, können Zusatzsäcke gegen eine Gebühr an den Wertstoffhöfen erworben werden. Diese Säcke werden bei der Restabfallabfuhr mitgenommen. Auch unverbrauchte Tapetenreste können nicht wiederverwertet werden und gehören deshalb ebenfalls in den Restabfall., | E56: =VLOOKUP(A56,All!$C$2:$D$2424,2,FALSE) -> Kleinere Mengen Baustellenabfälle aus privaten Haushalten, wie z.B. Fußbodenbeläge (asbestfrei), Dämmungen, Mineralfaserabfälle, Gipskarton, Teppichreste, Baukunststoffe, Plastikrohre, Dachbahnen (nachweislich teerfrei) usw. können Sie bis 1m³ kostenlos nur auf den Wertstoffhöfen der Deponien abgeben. Der Abfall muss sortiert nach den einzelnen Fraktionen angeliefert werden. Größere Mengen nehmen wir gegen Gebühr auf den Deponien Hannover-Lahe und Kolenfeld an. Dämmstoffe, HBCD belastet, sowie teerhaltige Dachpappe werden nur auf der Deponie Hannover-Lahe angenommen. Tapetenreste und verschmutzte Malerfolien gehören in den Restabfall. Sollte der Restabfallbehälter nicht ausreichen, können Zusatzsäcke gegen eine Gebühr an den Wertstoffhöfen erworben werden. Diese Säcke werden bei der Restabfallabfuhr mitgenommen. Auch unverbrauchte Tapetenreste können nicht wiederverwertet werden und gehören deshalb ebenfalls in den Restabfall. | F56: =VLOOKUP(A56,All!$C$2:$F$2424,4,FALSE) -> Bauabfall | G56: =VLOOKUP(A56,All!$C$2:$G$2424,5,FALSE) -> Deponie | H56: =IF(D56=E56,"ok","no") -> no | I56: =IF(B56=F56,"ok","no") -> ok | J56: =IF(C56=G56,"ok","no") -> ok
A57: Behandeltes Holz | B57: Holzabfall | C57: Deponie,Deponie Hannover Lahe | D57: Bis zu 1 m³ (Gesamtmenge/ haushaltsübliche Mengen) ihrer behandelten Holzabfälle täglich können Sie kostenlos auf den Deponien Lahe und Kolenfeld der Region Hannover abgeben. Größere Mengen können Sie ebenfalls kostenpflichtig dort abgeben. Bitte beachten Sie hierzu die Preisliste für die Deponieanlieferung. Die Annahmebedingungen unserer Deponien und Wertstoffhöfe finden Sie hier (Deponien) und hier (Wertstoffhöfe). | E57: =VLOOKUP(A57,All!$C$2:$D$2424,2,FALSE) -> Bis zu 1 m³ (Gesamtmenge/ haushaltsübliche Mengen) ihrer behandelten Holzabfälle täglich können Sie kostenlos auf den Deponien Lahe und Kolenfeld der Region Hannover abgeben. Größere Mengen können Sie ebenfalls kostenpflichtig dort abgeben. Bitte beachten Sie hierzu die Preisliste für die Deponieanlieferung. Die Annahmebedingungen unserer Deponien und Wertstoffhöfe finden Sie , und ,. | F57: =VLOOKUP(A57,All!$C$2:$F$2424,4,FALSE) -> Holzabfall | G57: =VLOOKUP(A57,All!$C$2:$G$2424,5,FALSE) -> Deponie, Deponie | H57: =IF(D57=E57,"ok","no") -> no | I57: =IF(B57=F57,"ok","no") -> ok | J57: =IF(C57=G57,"ok","no") -> no
A58: Benzin | B58: Sonderabfall | C58: Wertstoffhof,Deponie Hannover - Sonderabfallannahmestelle | D58: Bis zu 30kg (Gesamtmenge/ haushaltsübliche Mengen) Ihrer gefährlichen Abfälle, können Sie täglich kostenlos auf allen Wertstoffhöfen abgeben. Auf den Wertstoffhöfen der Region werden Sonderabfälle in Gebinden bis zu einer Größe von max. 10 Litern entgegengenommen. Größere Mengen oder Gebinde können kostenpflichtig an der Sonderannahmestelle auf der Deponie Hannover Lahe abgeben. Gebinde über 10 Liter sind ebenfalls an der Deponie in Hannover anzuliefern.,Bitte beachten Sie die Mengenbegrenzung der einzelnen Abfälle, auf der Preisliste für Sonderabfall.,Bitte achten Sie bei dem Transport darauf, die Gebinde gut zu kennzeichnen und auf keinen Fall mit anderen Flüssigkeiten zu vermischen. Am sichersten transportieren Sie Sonderabfälle nur dicht verschlossen in den originalen Behältern (Gebinden) sowie aufrechtstehend (z.B. in einer Wanne, die Behälter aufrecht hält).,Wichtig: Nutzen Sie bitte die Abgabezeiten für Gewerbekunden (Mo. bis Do. von 7.00 – 14.00 Uhr und Fr. von 7.00 – 12.00 Uhr), wenn Sie größere Mengen an Sonderabfällen abgeben wollen.,Sachstand 19.07.2023 | E58: =VLOOKUP(A58,All!$C$2:$D$2424,2,FALSE) -> Bis zu 30 Kg (Gesamtmenge/ haushaltsübliche Mengen) Ihrer gefährlichen Abfälle täglich können Sie kostenlos auf den Wertstoffhöfen der Region Hannover oder der Deponie Hannover im Sonderabfallzwischenlager abgeben. Größere Mengen können Sie kostenpflichtig an der Sonderannahmestelle auf der Deponie Hannover abgeben. Bitte beachten Sie hierzu die Preisliste für Sonderabfall. Bitte achten Sie bei dem Transport darauf, die Gebinde gut zu kennzeichnen und auf keinen Fall mit anderen Flüssigkeiten zu vermischen. Am sichersten transportieren Sie Sonderabfälle nur dicht verschlossen in den originalen Behältern (Gebinden) sowie aufrecht stehend (z.B in einer Wanne, die Behälter aufrecht hält). | F58: =VLOOKUP(A58,All!$C$2:$F$2424,4,FALSE) -> Sonderabfall | G58: =VLOOKUP(A58,All!$C$2:$G$2424,5,FALSE) -> Wertstoffhof, Deponie | H58: =IF(D58=E58,"ok","no") -> no | I58: =IF(B58=F58,"ok","no") -> ok | J58: =IF(C58=G58,"ok","no") -> no
A59: Benzinfeuerzeug | B59: Sonderabfall | C59: Wertstoffhof,Deponie Hannover - Sonderabfallannahmestelle | D59: Ein entleertes Feuerzeug gehört in den Restabfall. Ein nicht entleertes Feuerzeug bitte als Sonderabfall abgeben., Bis zu 30 kg Ihrer gefährlichen Abfälle können Sie entgeltfrei auf den Wertstoffhöfen der Region Hannover abgeben. Dort sind entsprechende Sammelstellen eingerichtet. Des Weiteren besteht die Möglichkeit, die gefährlichen Abfälle an der Sonderabfallannahmestelle der Deponie Hannover abzugeben. | E59: =VLOOKUP(A59,All!$C$2:$D$2424,2,FALSE) -> Ein entleertes Feuerzeug gehört in den Restabfall. Ein nicht entleertes Feuerzeug bitte als Sonderabfall abgeben. Bis zu 30 kg Ihrer gefährlichen Abfälle können Sie entgeltfrei auf den Wertstoffhöfen der Region Hannover abgeben. Dort sind entsprechende Sammelstellen eingerichtet. Des Weiteren besteht die Möglichkeit, die gefährlichen Abfälle an der Sonderabfallannahmestelle der , abzugeben. | F59: =VLOOKUP(A59,All!$C$2:$F$2424,4,FALSE) -> Sonderabfall | G59: =VLOOKUP(A59,All!$C$2:$G$2424,5,FALSE) -> Wertstoffhof, Deponie | H59: =IF(D59=E59,"ok","no") -> no | I59: =IF(B59=F59,"ok","no") -> ok | J59: =IF(C59=G59,"ok","no") -> no
A60: Benzinkanister | B60: Sonderabfall | C60: Wertstoffhof,Deponie Hannover - Sonderabfallannahmestelle | D60: Benzinkanister (leere Gebinde) zählen auf Grund ihrer Restanhaftung zu den ,. | E60: =VLOOKUP(A60,All!$C$2:$D$2424,2,FALSE) -> Benzinkanister (leere Gebinde) zählen auf Grund ihrer Restanhaftung zu den ,. | F60: =VLOOKUP(A60,All!$C$2:$F$2424,4,FALSE) -> Sonderabfall | G60: =VLOOKUP(A60,All!$C$2:$G$2424,5,FALSE) -> Wertstoffhof, Deponie | H60: =IF(D60=E60,"ok","no") -> ok | I60: =IF(B60=F60,"ok","no") -> ok | J60: =IF(C60=G60,"ok","no") -> no
A61: Beton | B61: Wertstoff | C61: Wertstoffhof | D61: Die Anlieferungen aus Privathaushalten müssen sortenrein und frei von anderen mineralischen Abfällen sein. | E61: =VLOOKUP(A61,All!$C$2:$D$2424,2,FALSE) -> Die Anlieferungen aus Privathaushalten müssen sortenrein und frei von anderen mineralischen Abfällen sein. | F61: =VLOOKUP(A61,All!$C$2:$F$2424,4,FALSE) -> Wertstoff | G61: =VLOOKUP(A61,All!$C$2:$G$2424,5,FALSE) -> Wertstoffhof | H61: =IF(D61=E61,"ok","no") -> ok | I61: =IF(B61=F61,"ok","no") -> ok | J61: =IF(C61=G61,"ok","no") -> ok
A62: Betongrill/Grillkamin | D62: Betongrills sind nach der Benutzung von innen mit Ruß behaftet, auf Grund dieser Behaftung werden sie weder auf den Wertstoffhöfen noch den Deponien entgegengenommen.,Bitte wenden Sie sich für die Entsorgung von Betongrills an eine externe Firma aus dem Branchenbuch/-verzeichnis oder dem Internet. | E62: =VLOOKUP(A62,All!$C$2:$D$2424,2,FALSE) -> #N/A | F62: =VLOOKUP(A62,All!$C$2:$F$2424,4,FALSE) -> #N/A | G62: =VLOOKUP(A62,All!$C$2:$G$2424,5,FALSE) -> #N/A | H62: =IF(D62=E62,"ok","no") -> #N/A | I62: =IF(B62=F62,"ok","no") -> #N/A | J62: =IF(C62=G62,"ok","no") -> #N/A
A63: Betonpulver im Sack (unausgehärtet) | C63: Wertstoffhof,Deponie | D63: Beton/ Zement, welcher noch in Pulverform ist, kann auf den Wertstoffhöfen oder den drei Regionsdeponien kostenlos über den Sperrabfallcontainer entsorgt werden.,Sachstand: 15.05.2024 | E63: =VLOOKUP(A63,All!$C$2:$D$2424,2,FALSE) -> #N/A | F63: =VLOOKUP(A63,All!$C$2:$F$2424,4,FALSE) -> #N/A | G63: =VLOOKUP(A63,All!$C$2:$G$2424,5,FALSE) -> #N/A | H63: =IF(D63=E63,"ok","no") -> #N/A | I63: =IF(B63=F63,"ok","no") -> #N/A | J63: =IF(C63=G63,"ok","no") -> #N/A
A64: Betonschleifstaub | D64: Schleifstäube von Beton-/ Estrich-/ oder Parkettböden werden, auf Grund der von Ihnen ausgehenden Explosionsgefahr, weder auf den Wertstoffhöfen noch den Deponien der Region Hannover entgegengenommen. Bitte wenden Sie sich für die Entsorgung von Schleifstäuben an eine externe Firma aus dem Branchenbuch/-verzeichnis oder dem Internet. | E64: =VLOOKUP(A64,All!$C$2:$D$2424,2,FALSE) -> #N/A | F64: =VLOOKUP(A64,All!$C$2:$F$2424,4,FALSE) -> #N/A | G64: =VLOOKUP(A64,All!$C$2:$G$2424,5,FALSE) -> #N/A | H64: =IF(D64=E64,"ok","no") -> #N/A | I64: =IF(B64=F64,"ok","no") -> #N/A | J64: =IF(C64=G64,"ok","no") -> #N/A
A65: Bettrahmen | B65: Sperrabfall | C65: Wertstoffhof,Sperrabfallabholung | D65: Bettrahmen gehören in den Sperrabfall.,Sperrabfall sind bewegliche Gegenstände aus Privathaushalten, die selbst nach einer zumutbaren Zerkleinerung auf Grund ihrer Sperrigkeit, ihres Gewichtes oder ihrer Materialbeschaffenheit nicht in die Restabfallbehälter und -säcke passen, wie z. B. Tisch und Stühle, Sofas, Sessel, Polster, Bettgestelle aus Holz oder Kunststoff, Matratzen usw., 5 m³ Sperrabfall können Sie kostenlos abholen lassen. Dabei sollten die Gegenstände eine Länge von 2 m und eine Gewicht von max. 75 kg nicht überschreiten. Bitte vereinbaren Sie einen Termin - online oder telefonisch.,Wichtiger Hinweis: Glastische können nicht bei der Sperrabfallabfuhr mitgenommen werden. Bitte bringen Sie diese für die Entsorgung zu den Wertstoffhöfe oder Deponien.,Sachstand:10.05.2024 | E65: =VLOOKUP(A65,All!$C$2:$D$2424,2,FALSE) -> Bettrahmen gehören in den Sperrabfall. Sperrabfall sind bewegliche Gegenstände aus Privathaushalten, die selbst nach einer zumutbaren Zerkleinerung auf Grund ihrer Sperrigkeit, ihres Gewichtes oder ihrer Materialbeschaffenheit nicht in die Restabfallbehälter und -säcke passen. | F65: =VLOOKUP(A65,All!$C$2:$F$2424,4,FALSE) -> Sperrabfall | G65: =VLOOKUP(A65,All!$C$2:$G$2424,5,FALSE) -> Wertstoffhof, Sperrabfallabholung | H65: =IF(D65=E65,"ok","no") -> no | I65: =IF(B65=F65,"ok","no") -> ok | J65: =IF(C65=G65,"ok","no") -> no
A66: Bettwanzengift | B66: Sonderabfall | C66: Wertstoffhof,Deponie Hannover - Sonderabfallannahmestelle,Deponie,Deponie Hannover Lahe | D66: Bis zu 30kg (Gesamtmenge/ haushaltsübliche Mengen) Ihrer gefährlichen Abfälle, können Sie täglich kostenlos auf allen Wertstoffhöfen abgeben. Auf den Wertstoffhöfen der Region werden Sonderabfälle in Gebinden bis zu einer Größe von max. 10 Litern entgegengenommen. Größere Mengen oder Gebinde können kostenpflichtig an der Sonderannahmestelle auf der Deponie Hannover Lahe abgeben. Gebinde über 10 Liter sind ebenfalls an der Deponie in Hannover anzuliefern.,Bitte beachten Sie die Mengenbegrenzung der einzelnen Abfälle, auf der Preisliste für Sonderabfall.,Bitte achten Sie bei dem Transport darauf, die Gebinde gut zu kennzeichnen und auf keinen Fall mit anderen Flüssigkeiten zu vermischen. Am sichersten transportieren Sie Sonderabfälle nur dicht verschlossen in den originalen Behältern (Gebinden) sowie aufrechtstehend (z.B. in einer Wanne, die Behälter aufrecht hält).,Wichtig: Nutzen Sie bitte die Abgabezeiten für Gewerbekunden (Mo. bis Do. von 7.00 – 14.00 Uhr und Fr. von 7.00 – 12.00 Uhr), wenn Sie größere Mengen an Sonderabfällen abgeben wollen. | E66: =VLOOKUP(A66,All!$C$2:$D$2424,2,FALSE) -> #N/A | F66: =VLOOKUP(A66,All!$C$2:$F$2424,4,FALSE) -> #N/A | G66: =VLOOKUP(A66,All!$C$2:$G$2424,5,FALSE) -> #N/A | H66: =IF(D66=E66,"ok","no") -> #N/A | I66: =IF(B66=F66,"ok","no") -> #N/A | J66: =IF(C66=G66,"ok","no") -> #N/A
A67: Bilderrahmen | B67: Sperrabfall | C67: Wertstoffhof,Sperrabfallabholung | D67: Bilderrahmen gehören in den Sperrabfall.,Sperrabfall sind bewegliche Gegenstände aus Privathaushalten, die selbst nach einer zumutbaren Zerkleinerung auf Grund ihrer Sperrigkeit, ihres Gewichtes oder ihrer Materialbeschaffenheit nicht in die Restabfallbehälter und -säcke passen, wie z. B. Tisch und Stühle, Sofas, Sessel, Polster, Bettgestelle aus Holz oder Kunststoff, Matratzen usw., 5 m³ Sperrabfall können Sie kostenlos abholen lassen. Dabei sollten die Gegenstände eine Länge von 2 m und eine Gewicht von max. 75 kg nicht überschreiten. Bitte vereinbaren Sie einen Termin - online oder telefonisch.,Wichtiger Hinweis: Glastische können nicht bei der Sperrabfallabfuhr mitgenommen werden. Bitte bringen Sie diese für die Entsorgung zu den Wertstoffhöfe oder Deponien.,Sachstand:10.05.2024 | E67: =VLOOKUP(A67,All!$C$2:$D$2424,2,FALSE) -> Bilderrahmen gehören in den Sperrabfall. Sperrabfall sind bewegliche Gegenstände aus Privathaushalten, die selbst nach einer zumutbaren Zerkleinerung auf Grund ihrer Sperrigkeit, ihres Gewichtes oder ihrer Materialbeschaffenheit nicht in die Restabfallbehälter und -säcke passen. | F67: =VLOOKUP(A67,All!$C$2:$F$2424,4,FALSE) -> Sperrabfall | G67: =VLOOKUP(A67,All!$C$2:$G$2424,5,FALSE) -> Wertstoffhof, Sperrabfallabholung | H67: =IF(D67=E67,"ok","no") -> no | I67: =IF(B67=F67,"ok","no") -> ok | J67: =IF(C67=G67,"ok","no") -> no
A68: Bildschirm | B68: Elektrogeräte | C68: Wertstoffhof | D68: Alte Bildschirme können Sie kostenfrei auf den Wertstoffhöfen abgeben.,Sachstand: 09.04.2024 | E68: =VLOOKUP(A68,All!$C$2:$D$2424,2,FALSE) -> Am 1.12.2018 traten Anpassungen des Elektro- und Elektronikgesetzes inkraft, die Änderungen bei der Annahme von Elektrogeräten erforderten. Die Sammlung der Elektrogeräte muss in verschiedenen Gruppen in getrennten Containern erfolgen. Die Bereitstellung dieser Container erfordert zusätzlichen Platz auf den Wertstoffhöfen. Da dieser nicht überall zur Verfügung steht, können Elektro-Großgeräte (wie Waschmaschine oder Kühlschrank) seit Dezember 2018 nur noch auf den Deponien in Hannover (Lahe), Burgdorf und Kolenfeld sowie auf den Wertstoffhöfen Schörlingstraße (Hannover), Bissendorf und Sehnde abgegeben werden (max. 2 Großgeräte pro Tag). Elektro-Kleingeräte können Sie weiterhin auf allen Wertstoffhöfen entsorgen. Pro Tag können zwei Großgeräte und eine haushaltsübliche Menge an Kleingeräten abgegeben werden, größere Mengen nehmen nur die Deponien in Burgdorf und Wunstorf an. Bitte denken Sie daran, vor der Entsorgung ggf. Ihre persönlichen Daten zu löschen. Zuerst ist eine Terminanmeldung beim aha-Service, Tel: 0800 999 11 99 erforderlich, dabei kann auch eine Zahlung auf Rechnung vereinbart werden. aha holt dann Großgeräte vor dem Grundstück ab. Bitte stellen Sie das Gerät in kürzester Entfernung zum Fahrbahnrand bzw. zum nächstmöglichen Halteplatz des Entsorgungsfahrzeuges ab. Kostenpflichtige Plaketten gibt es auf den Wertstoffhöfen und bei vielen Bürgerbüros. | F68: =VLOOKUP(A68,All!$C$2:$F$2424,4,FALSE) -> Elektrogeräte | G68: =VLOOKUP(A68,All!$C$2:$G$2424,5,FALSE) -> Wertstoffhof | H68: =IF(D68=E68,"ok","no") -> no | I68: =IF(B68=F68,"ok","no") -> ok | J68: =IF(C68=G68,"ok","no") -> ok
A69: Billiard-Tisch | B69: Container | C69: Containerdienst | D69: Eine Abholung als Sperrabfall ist nicht möglich, ein solcher Tisch überschreitet das maximal zulässige Gewicht von 75 kg für Teile zur Abholung ebenso wie die maximale Länge von 2 m.,aha stellt Ihnen auf Bestellung einen kostenpflichtigen Container für die Entsorgung zur Verfügung. ,Rufen Sie unseren Containerdienst an unter der Tel.-Nr: 0511 - 99 11 - 4 78 99. | E69: =VLOOKUP(A69,All!$C$2:$D$2424,2,FALSE) -> Eine Abholung als Sperrabfall ist nicht möglich, ein solcher Tisch überschreitet das maximal zulässige Gewicht von 75 kg für Teile zur Abholung ebenso wie die maximale Länge von 2 m. aha stellt Ihnen auf Bestellung einen kostenpflichtigen Container für die Entsorgung zur Verfügung. ,Rufen Sie unseren Containerdienst an unter der Tel.-Nr: 0511 - 99 11 - 4 78 99. | F69: =VLOOKUP(A69,All!$C$2:$F$2424,4,FALSE) -> Container | G69: =VLOOKUP(A69,All!$C$2:$G$2424,5,FALSE) -> Containerdienst | H69: =IF(D69=E69,"ok","no") -> no | I69: =IF(B69=F69,"ok","no") -> ok | J69: =IF(C69=G69,"ok","no") -> ok
A70: Bimssteine | C70: Deponie | D70: Bimsstein ist natürlich vorkommendes Vulkangestein in den Farben von weiß bis fast schwarz. Bis zu 1m³ an Bimssteinen aus privaten Haushalten können kostenfrei auf den Regionsdeponien entsorgt werden.,Sachstand: 10.05.2024 | E70: =VLOOKUP(A70,All!$C$2:$D$2424,2,FALSE) -> #N/A | F70: =VLOOKUP(A70,All!$C$2:$F$2424,4,FALSE) -> #N/A | G70: =VLOOKUP(A70,All!$C$2:$G$2424,5,FALSE) -> #N/A | H70: =IF(D70=E70,"ok","no") -> #N/A | I70: =IF(B70=F70,"ok","no") -> #N/A | J70: =IF(C70=G70,"ok","no") -> #N/A
A71: Binden | B71: Restabfall | C71: Restabfalltonne | D71: Nach dem Aussortieren von Wertstoffen (z.B. Papier oder Glas), Bio-, Bau- (z. B. Steine) und Sonderabfällen bleibt noch der so genannte Restabfall, der in die Restabfalltonne gehört, wie z. B. Asche, Essensreste, Brot- und Kuchenreste, Fleisch- und Fischreste, Glühlampen, Kehricht usw. übrig. Zur Grillzeit gehört Grillkohle (vollständig ausgeglüht), Schaschlikspieße, Streichhölzer, Feuerzeuge (wenn sie leer sind) und Servietten in die Restabfalltonne.,Wenn gelegentlich mehr Abfall anfällt, können Sie beim Wertstoffhof ,einen Zusatzsack kaufen. Stellen Sie diesen am Leerungstag einfach zu dem Restabfallbehälter - wir nehmen ihn mit.,Sachstand: 03.05.2024 | E71: =VLOOKUP(A71,All!$C$2:$D$2424,2,FALSE) -> #N/A | F71: =VLOOKUP(A71,All!$C$2:$F$2424,4,FALSE) -> #N/A | G71: =VLOOKUP(A71,All!$C$2:$G$2424,5,FALSE) -> #N/A | H71: =IF(D71=E71,"ok","no") -> #N/A | I71: =IF(B71=F71,"ok","no") -> #N/A | J71: =IF(C71=G71,"ok","no") -> #N/A
A72: Binderfarben | B72: Sonderabfall,Restabfall,Wertstoff | C72: Wertstoffhof,Deponie Hannover - Sonderabfallannahmestelle | D72: Binderfarben sind wasserlöslich und zählen nicht zu den gefährlichen Abfällen, verursachen uneingedickt allerding böse Flecken. Eingetrocknete oder eingedickte (mit Sand, Gips oder Sägespäne vermischte Binderfarbe) können dem Restabfall über die Restabfalltonne zugeführt werden.,Flüssige Binderfarben geben Sie bitte an den Wertstoffhöfen der Region Hannover oder der Deponie Hannover im Sonderabfallzwischenlager ab.,Sachstand 07.05.2024 | E72: =VLOOKUP(A72,All!$C$2:$D$2424,2,FALSE) -> #N/A | F72: =VLOOKUP(A72,All!$C$2:$F$2424,4,FALSE) -> #N/A | G72: =VLOOKUP(A72,All!$C$2:$G$2424,5,FALSE) -> #N/A | H72: =IF(D72=E72,"ok","no") -> #N/A | I72: =IF(B72=F72,"ok","no") -> #N/A | J72: =IF(C72=G72,"ok","no") -> #N/A
A73: Bioabfall | D73: Bioabfall wird im Bioabfallkompostwerk von aha zu hochwertigem RAL-gütegesichertem Kompost verarbeitet. Die Annahme erfolgt über die Biotonne. Bei nachgewiesener Eigenkompostierung, kann es auch auf dem eigenen Grundstück verwertet werden. Die Annahmebedingungen sind abhängig von der Art des Bioabfalls.,Bioabfälle sind z.B.:,In die Biotonne können zusätzlich folgende Grünabfälle gegeben werden:,Bei einer Vermischung der Grün- und Bioabfälle könne diese nur über die zuvor genannten Behältnisse oder aber per Anlieferung auf einer der drei aha-Deponien gegen Gebühr angeliefert werden.,Wichtiger Hinweis: Ungebleichtes Papier und Küchentücher können in kleinen Mengen (nur Einzelblätter) zum Einwickeln des feuchten Bioabfalls in der Biotonne verwendet werden.,Sachstand: 02.10.2024 | E73: =VLOOKUP(A73,All!$C$2:$D$2424,2,FALSE) -> #N/A | F73: =VLOOKUP(A73,All!$C$2:$F$2424,4,FALSE) -> #N/A | G73: =VLOOKUP(A73,All!$C$2:$G$2424,5,FALSE) -> #N/A | H73: =IF(D73=E73,"ok","no") -> #N/A | I73: =IF(B73=F73,"ok","no") -> #N/A | J73: =IF(C73=G73,"ok","no") -> #N/A
A74: Bioabfall-Sammelbeutel aus Papier | D74: Im Stadtgebiet von Hannover besteht die Möglichkeit, die Bioabfälle über die Biotonne zu entsorgen. Papier zum Einwickeln ist in geringen Schichtdicken zugelassen.,Sachstand: 08.10.2024 | E74: =VLOOKUP(A74,All!$C$2:$D$2424,2,FALSE) -> #N/A | F74: =VLOOKUP(A74,All!$C$2:$F$2424,4,FALSE) -> #N/A | G74: =VLOOKUP(A74,All!$C$2:$G$2424,5,FALSE) -> #N/A | H74: =IF(D74=E74,"ok","no") -> #N/A | I74: =IF(B74=F74,"ok","no") -> #N/A | J74: =IF(C74=G74,"ok","no") -> #N/A
A75: Bioplastik-Abfallbeutel | B75: Restabfall | C75: Restabfalltonne | D75: "Kompostierbare" Abfallbeutel aus Bioplastik brauchen in der herkömmlichen Kompostierung zu lange, um sich vollständig zu zersetzen. Außerdem ist Bioplastik nicht vollständig biologisch abbaubar. Abfallbeutel und andere Tüten aus Bioplastik gehören daher in den Restabfall. Weitere Infos zum Thema Bioplastik finden Sie | E75: =VLOOKUP(A75,All!$C$2:$D$2424,2,FALSE) -> "Kompostierbare" Abfallbeutel aus Bioplastik brauchen in der herkömmlichen Kompostierung zu lange, um sich vollständig zu zersetzen. Außerdem ist Bioplastik nicht vollständig biologisch abbaubar. Abfallbeutel und andere Tüten aus Bioplastik gehören daher in den Restabfall. Weitere Infos zum Thema Bioplastik finden Sie | F75: =VLOOKUP(A75,All!$C$2:$F$2424,4,FALSE) -> Restabfall | G75: =VLOOKUP(A75,All!$C$2:$G$2424,5,FALSE) -> Restabfalltonne | H75: =IF(D75=E75,"ok","no") -> no | I75: =IF(B75=F75,"ok","no") -> ok | J75: =IF(C75=G75,"ok","no") -> ok
A76: Bitumen | B76: Andere | C76: Deponie,Deponie Hannover Lahe | D76: Bitumen, das in Straßenaufbruch enthalten ist, wird bei aha nicht angenommen. Bitte wenden Sie sich an andere Entsorgungsbetriebe aus den Gelben Seiten.,Bitumen-Dachpappe aus Privathaushalten bis zu einer Menge 1 m³ pro Tag kann ausschließlich auf der Deponie Hannover in Lahe kostenlos als Baustellenabfall entsorgt werden. | E76: =VLOOKUP(A76,All!$C$2:$D$2424,2,FALSE) -> Bitumen, das in Straßenaufbruch enthalten ist, wird bei aha nicht angenommen. Bitte wenden Sie sich an andere Entsorgungsbetriebe aus den Gelben Seiten. Bitumen-Dachpappe aus Privathaushalten bis zu einer Menge 1 m³ pro Tag kann ausschließlich auf der Deponie Hannover in Lahe kostenlos als Baustellenabfall entsorgt werden. Mengen größer als 1 m³ werden dort gegen Gebühr angenommen. | F76: =VLOOKUP(A76,All!$C$2:$F$2424,4,FALSE) -> Andere | G76: =VLOOKUP(A76,All!$C$2:$G$2424,5,FALSE) -> Deponie | H76: =IF(D76=E76,"ok","no") -> no | I76: =IF(B76=F76,"ok","no") -> ok | J76: =IF(C76=G76,"ok","no") -> no
A77: Blähton | B77: Restabfall | C77: Restabfalltonne | D77: Kleine Mengen Blähton (Erdersatz) aus privaten Haushalten, die beim Umtopfen von Pflanzen anfallen, können über den Restabfallbehälter entsorgt werden.,Sachstand: 10.05.2024 | E77: =VLOOKUP(A77,All!$C$2:$D$2424,2,FALSE) -> Kleine Mengen Blähton (Erdersatz) aus privaten Haushalten, die beim Umtopfen von Pflanzen anfallen, können über den Restabfall (Restabfallbehälter/-säcke) entsorgt werden. | F77: =VLOOKUP(A77,All!$C$2:$F$2424,4,FALSE) -> Restabfall | G77: =VLOOKUP(A77,All!$C$2:$G$2424,5,FALSE) -> Restabfalltonne | H77: =IF(D77=E77,"ok","no") -> no | I77: =IF(B77=F77,"ok","no") -> ok | J77: =IF(C77=G77,"ok","no") -> ok
A78: Bläueschutzmittel | B78: Sonderabfall | C78: Wertstoffhof,Deponie Hannover - Sonderabfallannahmestelle | D78: Bis zu 30kg (Gesamtmenge/ haushaltsübliche Mengen) Ihrer gefährlichen Abfälle, können Sie täglich kostenlos auf allen Wertstoffhöfen abgeben. Auf den Wertstoffhöfen der Region werden Sonderabfälle in Gebinden bis zu einer Größe von max. 10 Litern entgegengenommen. Größere Mengen oder Gebinde können kostenpflichtig an der Sonderannahmestelle auf der Deponie Hannover Lahe abgeben. Gebinde über 10 Liter sind ebenfalls an der Deponie in Hannover anzuliefern.,Bitte beachten Sie die Mengenbegrenzung der einzelnen Abfälle, auf der Preisliste für Sonderabfall.,Bitte achten Sie bei dem Transport darauf, die Gebinde gut zu kennzeichnen und auf keinen Fall mit anderen Flüssigkeiten zu vermischen. Am sichersten transportieren Sie Sonderabfälle nur dicht verschlossen in den originalen Behältern (Gebinden) sowie aufrechtstehend (z.B. in einer Wanne, die Behälter aufrecht hält).,Wichtig: Nutzen Sie bitte die Abgabezeiten für Gewerbekunden (Mo. bis Do. von 7.00 – 14.00 Uhr und Fr. von 7.00 – 12.00 Uhr), wenn Sie größere Mengen an Sonderabfällen abgeben wollen.,Sachstand 19.07.2023 | E78: =VLOOKUP(A78,All!$C$2:$D$2424,2,FALSE) -> Bis zu 30 Kg (Gesamtmenge/ haushaltsübliche Mengen) Ihrer gefährlichen Abfälle täglich können Sie kostenlos auf den Wertstoffhöfen der Region Hannover oder der Deponie Hannover im Sonderabfallzwischenlager abgeben. Größere Mengen können Sie kostenpflichtig an der Sonderannahmestelle auf der Deponie Hannover abgeben. Bitte beachten Sie hierzu die Preisliste für Sonderabfall. Bitte achten Sie bei dem Transport darauf, die Gebinde gut zu kennzeichnen und auf keinen Fall mit anderen Flüssigkeiten zu vermischen. Am sichersten transportieren Sie Sonderabfälle nur dicht verschlossen in den originalen Behältern (Gebinden) sowie aufrecht stehend (z.B in einer Wanne, die Behälter aufrecht hält). | F78: =VLOOKUP(A78,All!$C$2:$F$2424,4,FALSE) -> Sonderabfall | G78: =VLOOKUP(A78,All!$C$2:$G$2424,5,FALSE) -> Wertstoffhof, Deponie | H78: =IF(D78=E78,"ok","no") -> no | I78: =IF(B78=F78,"ok","no") -> ok | J78: =IF(C78=G78,"ok","no") -> no
A79: Bleiabfälle | B79: Sonderabfall | C79: Wertstoffhof,Deponie Hannover - Sonderabfallannahmestelle | D79: Bis zu 30kg (Gesamtmenge/ haushaltsübliche Mengen) Ihrer gefährlichen Abfälle, können Sie täglich kostenlos auf allen Wertstoffhöfen abgeben. Auf den Wertstoffhöfen der Region werden Sonderabfälle in Gebinden bis zu einer Größe von max. 10 Litern entgegengenommen. Größere Mengen oder Gebinde können kostenpflichtig an der Sonderannahmestelle auf der Deponie Hannover Lahe abgeben. Gebinde über 10 Liter sind ebenfalls an der Deponie in Hannover anzuliefern.,Bitte beachten Sie die Mengenbegrenzung der einzelnen Abfälle, auf der Preisliste für Sonderabfall.,Bitte achten Sie bei dem Transport darauf, die Gebinde gut zu kennzeichnen und auf keinen Fall mit anderen Flüssigkeiten zu vermischen. Am sichersten transportieren Sie Sonderabfälle nur dicht verschlossen in den originalen Behältern (Gebinden) sowie aufrechtstehend (z.B. in einer Wanne, die Behälter aufrecht hält).,Wichtig: Nutzen Sie bitte die Abgabezeiten für Gewerbekunden (Mo. bis Do. von 7.00 – 14.00 Uhr und Fr. von 7.00 – 12.00 Uhr), wenn Sie größere Mengen an Sonderabfällen abgeben wollen.,Sachstand 19.07.2023 | E79: =VLOOKUP(A79,All!$C$2:$D$2424,2,FALSE) -> Bis zu 30 Kg (Gesamtmenge/ haushaltsübliche Mengen) Ihrer gefährlichen Abfälle täglich können Sie kostenlos auf den Wertstoffhöfen der Region Hannover oder der Deponie Hannover im Sonderabfallzwischenlager abgeben. Größere Mengen können Sie kostenpflichtig an der Sonderannahmestelle auf der Deponie Hannover abgeben. Bitte beachten Sie hierzu die Preisliste für Sonderabfall. Bitte achten Sie bei dem Transport darauf, die Gebinde gut zu kennzeichnen und auf keinen Fall mit anderen Flüssigkeiten zu vermischen. Am sichersten transportieren Sie Sonderabfälle nur dicht verschlossen in den originalen Behältern (Gebinden) sowie aufrecht stehend (z.B in einer Wanne, die Behälter aufrecht hält). | F79: =VLOOKUP(A79,All!$C$2:$F$2424,4,FALSE) -> Sonderabfall | G79: =VLOOKUP(A79,All!$C$2:$G$2424,5,FALSE) -> Wertstoffhof, Deponie | H79: =IF(D79=E79,"ok","no") -> no | I79: =IF(B79=F79,"ok","no") -> ok | J79: =IF(C79=G79,"ok","no") -> no
A80: Bleiakkumilatoren | B80: Sonderabfall | C80: Wertstoffhof,Deponie Hannover - Sonderabfallannahmestelle | D80: aha nimmt Gerätebatterien, z. B. aus Taschenlampen, Uhren, Radios usw. an. Bis zu 30 kg Ihrer gefährlichen Abfälle täglich können Sie kostenlos auf den Wertstoffhöfen der Region Hannover oder der Deponie Hannover im Sonderabfallzwischenlager abgeben.,Ausgediente Akkus von E-Bikes und E-Scootern gehören zu laut §8 Batteriegesetz zu den Industriebatterien. Industriebatterien werden von aha nicht angenommen. Bitte geben Sie diese an den Fachhandel zurück.,Die einzige Ausnahme von dieser Regel stellen Starterbatterien auf Bleibasis von LKWs und PKWs sowie Motorrädern dar. | E80: =VLOOKUP(A80,All!$C$2:$D$2424,2,FALSE) -> aha nimmt Gerätebatterien, z. B. aus Taschenlampen, Uhren, Radios usw. an. Bis zu 30 kg Ihrer gefährlichen Abfälle täglich können Sie kostenlos auf den Wertstoffhöfen der Region Hannover oder der Deponie Hannover im Sonderabfallzwischenlager abgeben. Ausgediente Akkus von E-Bikes und E-Scootern gehören zu laut §8 Batteriegesetz zu den Industriebatterien. Industriebatterien werden von aha nicht angenommen. Bitte geben Sie diese an den Fachhandel zurück. Die einzige Ausnahme von dieser Regel stellen Starterbatterien auf Bleibasis von LKWs und PKWs sowie Motorrädern dar. Ausgediente Akkus von E-Bikes, E-Scootern und Motorrädern gehören zu laut §8 Batteriegesetz zu den Industriebatterien. Industriebatterien werden von aha nicht angenommen. Bitte geben Sie diese an den Fachhandel zurück. | F80: =VLOOKUP(A80,All!$C$2:$F$2424,4,FALSE) -> Sonderabfall | G80: =VLOOKUP(A80,All!$C$2:$G$2424,5,FALSE) -> Wertstoffhof, Deponie | H80: =IF(D80=E80,"ok","no") -> no | I80: =IF(B80=F80,"ok","no") -> ok | J80: =IF(C80=G80,"ok","no") -> no
A81: Bleiglas | B81: Restabfall | C81: Restabfalltonne | D81: Dieses Glas darf nicht in den Glascontainer gegeben werden. Die Beimischungen, die im Glas enthalten sind, können den Wiederverwertungsprozess erheblich beeinträchtigen. Geschliffenes Bleiglas wird oft auch als Bleikristall bezeichnet,Aufgrund der hohen Dichte werden Fenster mit Bleiglas zur Abschirmung von Strahlungsquellen in der Radiologie, Nuklearmedizin, der Technik und bei der Herstellung von Kathodenstrahlröhren (z. B. im Fernseher) verwendet.,Bleiglas ist kein Sonderabfall, kleine Mengen werden über den Restabfallbehälter entsorgt.,Sachstand: 10.05.2024 | E81: =VLOOKUP(A81,All!$C$2:$D$2424,2,FALSE) -> Dieses Glas darf nicht in den Glascontainer gegeben werden. Die Beimischungen, die im Glas enthalten sind, können den Wiederverwertungsprozess erheblich beeinträchtigen. Geschliffenes Bleiglas wird oft auch als Bleikristall bezeichnet. Bleikristallglas ist auch in dickwandigen Gefäßen klar und lässt sich gut schleifen. ,Aufgrund der hohen Dichte werden Fenster mit Bleiglas zur Abschirmung von Strahlungsquellen in der Radiologie, Nuklearmedizin, der Technik und bei der Herstellung von Kathodenstrahlröhren (z. B. im Fernseher) verwendet. Bleiglas ist kein Sonderabfall, kleine Mengen werden über den Restabfall entsorgt. | F81: =VLOOKUP(A81,All!$C$2:$F$2424,4,FALSE) -> Restabfall | G81: =VLOOKUP(A81,All!$C$2:$G$2424,5,FALSE) -> Restabfalltonne | H81: =IF(D81=E81,"ok","no") -> no | I81: =IF(B81=F81,"ok","no") -> ok | J81: =IF(C81=G81,"ok","no") -> ok
A82: Bleischürzen | B82: Sonderabfall | D82: Bleischürzen werden auf Grund Ihrer Strahlenbelastung weder auf den Wertstoffhöfen noch auf den Deponien entgegengenommen. Bitte wende Sie sich für die Entsorgung dieser an eine externe Firma aus dem Branchenbuch/-verzeichnis oder dem Internet.,Sachstand: 10.05.2024 | E82: =VLOOKUP(A82,All!$C$2:$D$2424,2,FALSE) -> Bis zu 30 Kg (Gesamtmenge/ haushaltsübliche Mengen) Ihrer gefährlichen Abfälle täglich können Sie kostenlos auf den Wertstoffhöfen der Region Hannover oder der Deponie Hannover im Sonderabfallzwischenlager abgeben. Größere Mengen können Sie kostenpflichtig an der Sonderannahmestelle auf der Deponie Hannover abgeben. Bitte beachten Sie hierzu die Preisliste für Sonderabfall. Bitte achten Sie bei dem Transport darauf, die Gebinde gut zu kennzeichnen und auf keinen Fall mit anderen Flüssigkeiten zu vermischen. Am sichersten transportieren Sie Sonderabfälle nur dicht verschlossen in den originalen Behältern (Gebinden) sowie aufrecht stehend (z.B in einer Wanne, die Behälter aufrecht hält). | F82: =VLOOKUP(A82,All!$C$2:$F$2424,4,FALSE) -> Sonderabfall | G82: =VLOOKUP(A82,All!$C$2:$G$2424,5,FALSE) -> Wertstoffhof, Deponie | H82: =IF(D82=E82,"ok","no") -> no | I82: =IF(B82=F82,"ok","no") -> ok | J82: =IF(C82=G82,"ok","no") -> no
A83: Blumen- und Pflanzenreste | C83: Wertstoffhof,Biotonne,Deponie | D83: Bei den Wertstoffhöfen werden diese Abfälle aus Privathaushalten in einer Anlieferung pro Kalendertag bis zu einer Gesamtmenge von insgesamt 1 m³ kostenlos angenommen,Bitte vor der Anlieferung Erdanhaftungen entfernen.,Wenn gelegentlich mehr Abfall entsteht, kann er im Kompostwerk der Deponien kostenpflichtig angeliefert werden. | E83: =VLOOKUP(A83,All!$C$2:$D$2424,2,FALSE) -> #N/A | F83: =VLOOKUP(A83,All!$C$2:$F$2424,4,FALSE) -> #N/A | G83: =VLOOKUP(A83,All!$C$2:$G$2424,5,FALSE) -> #N/A | H83: =IF(D83=E83,"ok","no") -> #N/A | I83: =IF(B83=F83,"ok","no") -> #N/A | J83: =IF(C83=G83,"ok","no") -> #N/A
A84: Blumenerde | B84: Bioabfall | C84: Wertstoffhof,Biotonne,Deponie | D84: Wir empfehlen, Blumenerde wiederzuverwenden. Sie können z.B. die alte Erde auf dem Gartenbeet, im Vorgarten oder auf dem Komposthaufen verteilen bzw. einarbeiten. Balkonkastenerde aus dem Vorjahr kann mit einem Drittel unseres Kompostes versetzt und im neuen Jahr wieder genutzt werden.,Wenn es nicht anders geht, kann die Erde bei aha folgendermaßen entsorgt werden: Ein paar Schaufeln alter Erde können Sie im Bioabfall entsorgen. Aber Vorsicht: Ist zu viel davon in der Tonne, kann es sein, dass sie deshalb nicht geleert oder mitgenommen wird. Größere Mengen bis zu 1 m³ können auf dem Wertstoffhof der Deponie entsorgt werden. | E84: =VLOOKUP(A84,All!$C$2:$D$2424,2,FALSE) -> Kleine Mengen Blumenerde können über den Bioabfall (Biotonne/ Biosäcke) entsorgt werden. Wichtig ist bei der Befüllung darauf zu achten, dass der Behälter und die Säcke nicht zu schwer werden, sonst können Sie nicht bei der Müllabfuhr geladen werden. Größere Mengen von Blumenerde können Sie auf den Deponien und den Wertstoffhöfen der Region Hannover entsorgen. Hierbei werden täglich bis zu 1m³ Blumenerde kostenlos angenommen, größere Mengen können kostenpflichtig auf den Deponien entsorgt werden. | F84: =VLOOKUP(A84,All!$C$2:$F$2424,4,FALSE) -> Bioabfall | G84: =VLOOKUP(A84,All!$C$2:$G$2424,5,FALSE) -> Wertstoffhof, Biotonne, Biosack, Deponie | H84: =IF(D84=E84,"ok","no") -> no | I84: =IF(B84=F84,"ok","no") -> ok | J84: =IF(C84=G84,"ok","no") -> no
A85: Blumentöpfe | C85: Restabfalltonne,Gelbe Tonne | D85: gehören im Umland Hannover in den gelben Sack oder im Stadtgebiet von Hannover in den gelben Container., , kommen in den Restabfallbehälter. Größere Mengen, bis 1 m³, können kostenfrei auf den Wertstoffhöfen und Deponien über den Bauschuttcontainer entsorgt werden.,Sachstand: 10.05.2024 | E85: =VLOOKUP(A85,All!$C$2:$D$2424,2,FALSE) -> #N/A | F85: =VLOOKUP(A85,All!$C$2:$F$2424,4,FALSE) -> #N/A | G85: =VLOOKUP(A85,All!$C$2:$G$2424,5,FALSE) -> #N/A | H85: =IF(D85=E85,"ok","no") -> #N/A | I85: =IF(B85=F85,"ok","no") -> #N/A | J85: =IF(C85=G85,"ok","no") -> #N/A
A86: Bodenaushub/ Erde | C86: Deponie | D86: Bis zu einer Menge von 1 m³ pro Anlieferung und Tag an Bodenaushub aus Privathaushalten wird auf den Wertstoffhöfen der drei Deponien (Hannover, Kolenfeld und Burgdorf) kostenlos angenommen.,Der Boden darf geringe Anteile von Steinen, Findlingen und Wurzelwerk (Kantenlänge max. 15cm) enthalten.,Bitte beachten Sie, dass eine Abladung händisch erfolgen muss, da das Abkippen eines Anhängers nicht möglich ist. Für die Abladung empfehlen wir Schaufeln mitzubringen.,Bitte beauftragen Sie zur Entsorgung von größeren Mengen an Bodenaushub eine externe Firma aus dem Branchenverzeichnis/ -buch oder dem Internet., Sachstand: 13.03.2024, | E86: =VLOOKUP(A86,All!$C$2:$D$2424,2,FALSE) -> #N/A | F86: =VLOOKUP(A86,All!$C$2:$F$2424,4,FALSE) -> #N/A | G86: =VLOOKUP(A86,All!$C$2:$G$2424,5,FALSE) -> #N/A | H86: =IF(D86=E86,"ok","no") -> #N/A | I86: =IF(B86=F86,"ok","no") -> #N/A | J86: =IF(C86=G86,"ok","no") -> #N/A
